Workbook

Sheet ПК с 1 владельцем
B1: Табельный номер / Employee ID | C1: Физлицо / Owner | D1: Статус пк ( была ли модернизация) / Modernisation, repairing history | E1: Тип домена / Domain Type | F1: Имя на английском / English name | G1: Должность / Position (Rus / Eng) | H1: Отдел / Department | I1: Комплектация / Equipment | J1: Тип и модель ПК / PC type and model | K1: Инвентарный номер / Inventory number | L1: Инвентарный номер наклеен? / Is the inventory number affixed? | M1: где хранится информация о компе | N1: Местоположение ПК / Location | O1: Серийный номер / Serial Number | P1: Имя компьютера / PC Domain Name | Q1: Passwork | R1: Тип ПО офис / Office type | S1: Ключ офиса / License key Office | T1: ОС тип / OS Type | U1: Ключ ОС / Key OS | V1: ПО удалённого управления / Remote control | W1: Админ права / Admin permissions | X1: Кто подготовил / Who installed | Y1: Дата выдачи / Issue Date | Z1: Дата покупки / Purchasing Date | AA1: Примечание / Comment
A2: =A1+1 -> 1 | B2: 36 | C2: Живов Сергей Викторович | D2: Модернизация не требуется/normal (no need to upgrade) | E2: Rus | G2: Заместитель генерального директора по производству | H2: MD | I2: Laptop,mouse | J2: Laptop ThinkBook 16 G7 ARP 3 | O2: PW0LW3V5 | P2: ="RUTL-" & RIGHT(O2,8) -> RUTL-PW0LW3V5 | R2: Libre office | T2: Windows 11 Pro | U2: 93TQN-DYGPM-FPQ9C-2X3QP-4RHJ6 | V2: ULTRAVNC / MESH | W2: No Administrator rights | X2: Мелёшкин С. | AA2: С НДС 64660 БЕЗ НДС 53000
A3: ='Склад, ремонт, ожидающие'!A44+1 -> #REF! | B3: 42 | C3: Денисов Леонид Алексеевич | D3: Модернизация не требуется/normal (no need to upgrade) | E3: Rus | F3: Denisov Leonid | G3: Ведущий специалист | H3: GD, GA, RMG | I3: AiO, mouse, keyboard | J3: AiO Lenovo S400Z | K3: 150000016/Z000014 | L3: Наклеить | N3: 1-07 третий этаж | O3: P901FSLR | P3: ="RUTL-" & RIGHT(O3,8) -> RUTL-P901FSLR | U3: QDRN8-XWVBK-KKTG9-7HM6W-7FTGC | V3: ULTRAVNC | W3: Уточнить | Y3: 2017
A4: =A3+1 -> #REF! | B4: 47 | C4: Верняев Александр Сергеевич (MSI+o) | D4: Модернизация не требуется/normal (no need to upgrade) | E4: Rus | F4: Vernyaev Aleksandr | G4: Заместитель директора департамента | H4: HRD | I4: Laptop, mouse, bag | J4: Laptop IRBIS 17NBP4502 | K4: поставить на учет | L4: Наклеить | N4: 1-07 третий этаж | O4: F2717NBP4502103035 | P4: ="RUTL-" & RIGHT(O4,8) -> RUTL-02103035 | Q4: Внесены в Passwork | R4: Libre office | S4: 39D7B-N3MY4-H97DG-KW8RW-78TTG | T4: Windows 10 Pro | U4: VK7JG-NPHTM-C97JM-9MPGT-3V66T | V4: ULTRAVNC / MESH | W4: No Administrator rights | X4: Кудрявцев Д. | Y4: Акт 24.03.2025
A5: =#REF!+1 -> #REF! | B5: 52 | C5: Онуфриев Сергей Юрьевич (052) | D5: Модернизация не требуется/normal (no need to upgrade) | E5: Rus | F5: Onufriev Sergey | G5: Директор департамента | H5: M&U | I5: Laptop, mouse,bag | J5: Laptop MSI Modern 15 F1MG-800XRU | K5: поставить на учет | L5: Наклеить | N5: 1-09 второй этаж | O5: C2507N0002971 | P5: ="RUTL-" & RIGHT(O5,8) -> RUTL-N0002971 | Q5: Внесены в Passwork | R5: 2019 for home and business | T5: Windows 11 Pro | U5: FNKPJ-D474G-6KX2R-DHVCM-TXX2P | V5: ULTRAVNC / MESH | W5: No administrator rights | X5: Летунов А. | Y5: Акт 04,04,2026 | Z5: 45987 | AA5: Стоимость ПК без НДС 59 160руб
A6: ='Склад, ремонт, ожидающие'!A37+1 -> #REF! | B6: 59 | C6: Самойленко Антон Викторович | D6: Модернизация не требуется/normal (no need to upgrade) | E6: Rus | F6: Samoylenko Anton | G6: Заместитель директора департамента | H6: M&U | I6: Laptop, mouse, bag | J6: Laptop MSI Modern 15 F1MG-800XRU | K6: поставить на учет | L6: Наклеить | N6: 1-13 крыло ютилити 2 эт | O6: C2509N0008357 | P6: ="RUTL-" & RIGHT(O6,8) -> RUTL-N0008357 | Q6: Внесены в Passwork | R6: MS Office 2019 Pro Plus | S6: NVP38-3P3F3-FDCCY-CPFYW-MTFW6 | T6: Windows 11 Pro | U6: HN6RT-B4HJP-KMKFG-G3VPV-4C2TC | V6: ULTRAVNC / MESH | W6: No Administrator rights | X6: Кудрявцев Д. | Y6: Акт 25.02.2026 | Z6: 45989 | AA6: Стоимость ПК без НДС 59 160руб
A7: =A6+1 -> #REF! | B7: 72 | C7: Зорин Сергей Александрович | D7: Модернизация не требуется/normal (no need to upgrade) Заменён SSD 256гб. | E7: Rus | F7: Zorin Sergey | G7: Руководитель отдела | H7: GD, CONSTR | I7: Workstation, Монитор Lenovo ThinkVision T2424z | J7: Workstation Lenovo ThinkStation P310 | K7: 150000029/Z000114 | L7: Наклеить | N7: строительный городок | O7: S4BP0247 | P7: ="RUTL-" & RIGHT(O7,8) -> RUTL-S4BP0247 | Q7: Внесены в Passwork | U7: P3W88-4NBCQ-K46F6-GPYDV-DRR9C | V7: ULTRAVNC | W7: No Administrator rights | Y7: 2016
A8: =A7+1 -> #REF! | B8: 85 | C8: Каприца Светлана Олеговна | D8: Модернизация не требуется/normal (no need to upgrade) | E8: Rus | F8: Kapritsa Svetlana | G8: Руководитель офисной группы | H8: NOBO GA | I8: Laptop, mouse,+lan USB | J8: Laptop Dell Inspiron 15 3511 | K8: 100000001659 | L8: Наклеить | O8: 5MB0JK3 | P8: ="RUTL-" & RIGHT(O8,8) -> RUTL-5MB0JK3 | Q8: Внесены в Passwork | T8: Windows 10 Pro | V8: ULTRAVNC / MESH | W8: No Administrator rights | X8: Мартынов Д. | Y8: Акт 26.01.2026 | Z8: 44551 | AA8: БЕЗ НДС 81250,00 с НДС 97500
A9: =A8+1 -> #REF! | B9: 92 | C9: Райкова Любовь Владимировна | D9: Модернизация не требуется/normal (no need to upgrade) | E9: Rus | F9: Raikova Lyubov | G9: Руководитель группы | H9: RDC, BSSS | I9: Laptop, mouse, Monitor MSI-27 | J9: Laptop MSI Modern 15 F1MG-800XRU | K9: поставить на учет | L9: Наклеить | N9: 1-07 2 этаж | O9: C2507N0002983 | P9: ="RUTL-" & RIGHT(O9,8) -> RUTL-N0002983 | Q9: Внесены в Passwork | R9: 2019 for home and business | T9: Windows 11 Pro | U9: R767N-6J8WQ-GC3FW-R6YC8-W44C2 | V9: ULTRAVNC / MESH | W9: Admin | X9: Летунов А. | Y9: Акт 03.12.2025 | Z9: 45989 | AA9: Стоимость ПК без НДС 59 160руб
A10: =A9+1 -> #REF! | B10: 101 | C10: Терехов Максим Сергеевич | D10: Модернизация не требуется/normal (no need to upgrade) \ Отказ от замены Пк | E10: Rus | F10: Terekhov Maksim | G10: Заместитель главного энергетика | H10: M&U, UTL | I10: Workstation,mouse, keyboard+ Monitor LG | J10: Workstation Lenovo ThinkStation P 320 | K10: 140000256 | L10: инвентарник ОС наклеен | N10: 1-13 крыло ютилити 2 эт | O10: PC10AS8Y | P10: ="RUTL-" & RIGHT(O10,8) -> RUTL-PC10AS8Y | Q10: Внесены в Passwork | R10: Microsoft Office профессиональный плюс 2016 | T10: Windows 10 Pro | U10: C84R9-KTNCH-DF739-H3KD4-YTDGP | V10: ULTRAVNC | W10: No Administrator rights | Y10: Акт 03.07.2019
A11: =A10+1 -> #REF! | B11: 119 | C11: Денисов Роман Альбертович | D11: Модернизация не требуется/normal (no need to upgrade) | E11: Rus | F11: Denisov Roman | G11: Руководитель группы | H11: ILD, CO | I11: Laptop,mouse+Lan-USB | J11: Laptop Asus VivoBook SS533 | K11: 10000001730 | L11: наклеить | N11: 1-06 второй этаж | O11: M3N0CV15E20911A | P11: ="RUTL-" & RIGHT(O11,8) -> RUTL-5E20911A | Q11: Внесены в Passwork | R11: Libre office | T11: Windows 10 Pro | V11: ULTRAVNC | W11: Уточнить | Y11: Акт 10.09.2021
A12: =A11+1 -> #REF! | B12: 120 | C12: Душкин Иван Александрович | D12: Модернизация не требуется/normal (no need to upgrade) | E12: Rus | F12: Dushkin Ivan | G12: Директор по правовым вопросам и внешним связям | H12: GD, LEG | I12: Laptop, mouse,bag | J12: Laptop Lenovo L340 | K12: 10000001791 | L12: инвентарник ОС наклеен | N12: 1-07 третий этаж | O12: PF24A8SV | P12: ="RUTL-" & RIGHT(O12,8) -> RUTL-PF24A8SV | Q12: Внесены в Passwork | R12: 2019 for home and business | T12: Windows 10 Pro | V12: ULTRAVNC | W12: Уточнить | Y12: Акт 26.02.2021
A13: =A12+1 -> #REF! | B13: 125 | C13: Морозов Антон Вячеславович | D13: требуется модернизация/ЗАМЕНА | E13: Rus | F13: Morozov Anton | G13: Инженер-электроник 2 категории | H13: M&U,MTC ASPC | I13: AiO, mouse, keyboard | J13: AiO Lenovo M800Z | K13: 140000064/Z000099 | L13: Наклеить | N13: 1-03 офис MU окраски 1эт | O13: PC0KL0LH | P13: ="RUTL-" & RIGHT(O13,8) -> RUTL-PC0KL0LH | Q13: Внесены в Passwork | T13: Windows 10 Pro | U13: CHN29-XHCDQ-8JCF9-8DTMQ-4GDGP | V13: ULTRAVNC | W13: No Administrator rights | Y13: 2018
A14: =A13+1 -> #REF! | B14: 135 | C14: Дудукина Ольга | D14: Модернизация не требуется/normal (no need to upgrade) | E14: Rus | F14: Dudukina Olga | G14: Руководитель группы | H14: GD, FPW | I14: Laptop,mouse | J14: Laptop Acer Extensa 15 | K14: 100000003330 | N14: 1-07 второй этаж | O14: NXEGYER00H3200884B3400 | P14: ="RUTL-" & RIGHT(O14,8) -> RUTL-884B3400 | Q14: Внесены в Passwork | R14: 2019 for home and business | T14: Windows 10 Pro | V14: ULTRAVNC | W14: Уточнить | Y14: Акт 08.05.2024 | Z14: 2024 | AA14: БЕЗ НДС 60440.50
A15: =A14+1 -> #REF! | B15: 140 | C15: Фадеева Надежда Петровна | D15: была модернизация/upgraded (SSD+RAM 8) | E15: Rus | F15: Fadeeva Nadezhda | G15: Ведущий инженер-эколог | H15: M&U, HSE | I15: AiO, mouse, keyboard | J15: AiO Lenovo V410Z | K15: 140000067/Z000098 | L15: (Забаланс) Инвентарник наклеен | N15: 1-09 второй этаж HSE | O15: YJ009HNY | P15: ="RUTL-" & RIGHT(O15,8) -> RUTL-YJ009HNY | Q15: Внесены в Passwork | R15: 2016 for home and business (BOX) | T15: Windows 10 Pro | U15: WM9FN-M2YQ7-BHFPM-WXM44-FC2KC | V15: ULTRAVNC | W15: Admin | Y15: 2018
A16: =A15+1 -> #REF! | B16: 141 | C16: Мут Александр Владимирович | D16: была модернизация/upgraded (RAM +4) | E16: Rus | F16: Mut Aleksandr | G16: Инженер по надзору за строительством | H16: GD, CONSTR | I16: AiO, mouse, keyboard | J16: AiO Lenovo V410Z | K16: 140000068/Z000120 | L16: (Забаланс) Инвентарник наклеен | N16: строительный городок | O16: YJ009HNG | P16: ="RUTL-" & RIGHT(O16,8) -> RUTL-YJ009HNG | Q16: Внесены в Passwork | R16: Microsoft Office профессиональный плюс 2016 | T16: Windows 10 Pro | V16: ULTRAVNC | W16: Admin | Y16: 2018
A17: =A16+1 -> #REF! | B17: 152 | C17: Ермакова Светлана Николаевна | D17: Модернизация не требуется/normal (no need to upgrade) | E17: Rus | F17: Ermakova Svetlana | G17: Руководитель группы | H17: Q&T, QA | I17: Laptop, mouse,bag | J17: Laptop IRBIS 17NBP4502 | K17: поставить на учет | N17: 1-09 второй этаж | O17: F2717NBP4502103188 | P17: ="RUTL-" & RIGHT(O17,8) -> RUTL-02103188 | Q17: Внесены в Passwork | R17: Libre office | T17: Windows 10 Pro | V17: ULTRAVNC / MESH | W17: No Administrator rights | X17: Кудрявцев Д. | Y17: Акт 07.10.2025 | Z17: 2024 | AA17: Норм
A18: =A17+1 -> #REF! | B18: 168 | C18: Самойленко Иван Викторович | D18: Модернизация не требуется/normal (no need to upgrade) | E18: Rus | F18: Samoylenko Ivan | G18: Начальник смены | H18: PLD,WL | I18: Laptop, mouse | J18: Laptop IRBIS 15NBP3506 | K18: 100000003637 | L18: Наклеить | N18: СКЛАД | O18: F2715NBP35060821409 | P18: ="RUTL-" & RIGHT(O18,8) -> RUTL-60821409 | Q18: Внесены в Passwork | R18: Libre office | V18: ULTRAVNC / MESH | X18: Климанов А. | Y18: Акт 13.02.2026
A19: =A18+1 -> #REF! | B19: 189 | C19: Реутов Николай Викторович | D19: Модернизация не требуется/normal (no need to upgrade) | E19: Rus | F19: Reutov Nikolay | G19: Заместитель руководителя отдела | H19: GD, LEG | I19: Laptop, mouse,bag | J19: Laptop MSI Modern 15 F1MG-800XRU | K19: поставить на учет | N19: 1-07 третий этаж | O19: C2507N0002834 | P19: ="RUTL-" & RIGHT(O19,8) -> RUTL-N0002834 | Q19: Внесены в Passwork | R19: Microsoft Office профессиональный плюс 2016 | T19: Windows 10 Pro | U19: 7D4NY-6D4V4-6BFYX-8JHWT-9KX2P | V19: ULTRAVNC | W19: No Administrator rights | X19: Летунов А. | Y19: Акт 05.12.2025 | Z19: 45989 | AA19: Стоимость ПК без НДС 59 160руб
A20: =A19+1 -> #REF! | B20: 200 | C20: Тараканов Илья Алексеевич | D20: Модернизация не требуется/normal (no need to upgrade) | E20: Rus | F20: Tarakanov Ilya | G20: Заместитель начальника цеха | H20: MD, WELD | I20: Laptop, mouse, bag | J20: Laptop MSI Modern 15 F1MG-800XRU | K20: поставить на учет | L20: Наклеить | N20: 1-02 офис цеха сварки 2 эт | O20: C2509N0008392 | P20: ="RUTL-" & RIGHT(O20,8) -> RUTL-N0008392 | Q20: Внесены в Passwork | R20: Microsoft Office профессиональный плюс 2019 | S20: M6K4N-HK7Y8-MJFXF-2HM6V-VVB86 | T20: Windows 11 Pro | U20: C8Q3W-F9N74-J944M-X7P2F-3692P | V20: ULTRAVNC / MESH | W20: No Administrator rights | X20: Кудрявцев Д. | Y20: Акт 23.03.2026 | Z20: 45985 | AA20: Стоимость ПК без НДС 59 160руб
A21: =A20+1 -> #REF! | B21: 217 | C21: Филимонов Алексей Михайлович | D21: Модернизация не требуется/normal (no need to upgrade) | E21: Rus | G21: Комплаенс-менеджер | H21: GD, LEG, ER | I21: Laptop, mouse | J21: Laptop IRBIS 15NBP3506 | K21: 100000003624 | L21: Наклеить | N21: 1-09 2 этаж | O21: F2715NBP35060821504 | P21: ="RUTL-" & RIGHT(O21,8) -> RUTL-60821504 | Q21: Внесены в Passwork | R21: Libre office | T21: Windows 11 Pro | U21: DNYKM-2BGKT-WCCHC-7M3C2-27JXC | V21: ULTRAVNC / MESH | W21: No Administrator rights | X21: Мартынов Д. | Y21: Акт 06.05.2025
A22: =A21+1 -> #REF! | B22: 223 | C22: Щербакова Елена Васильевна | D22: Модернизация не требуется/normal (no need to upgrade) | E22: Rus | F22: Sherbakova Elena | G22: Руководитель группы | H22: FD, FUND | I22: Laptop, mouse,bag | J22: Laptop MSI Modern 15 F1MG-800XRU | K22: поставить на учет | N22: 1-07 третий этаж FD, Cost | O22: C2507N0003051 | P22: ="RUTL-" & RIGHT(O22,8) -> RUTL-N0003051 | Q22: Внесены в Passwork | R22: 2016 for home and business (BOX) | T22: Windows 11 Pro | U22: N6FG2-P73MD-TRGXK-QGYGW-7FR9C | V22: ULTRAVNC / MESH | W22: No Administrator rights | X22: Летунов А. | Y22: Акт 10.12.2025 | Z22: 45989 | AA22: Стоимость ПК без НДС 59 160руб
A23: =A22+1 -> #REF! | B23: 227 | C23: Щербаков Дмитрий Юрьевич | D23: Модернизация не требуется/normal (no need to upgrade) | E23: Rus | F23: Sherbakov Dmitriy | G23: Инженер-электроник 2 категории | H23: M&U, UTL | I23: Laptop,mouse | J23: Laptop HP 250 G8 | K23: 100000002677 | L23: Наклеить | N23: 1-13 диспетчерская | O23: CND2481GQW | P23: ="RUTL-" & RIGHT(O23,8) -> RUTL-D2481GQW | Q23: Внесены в Passwork | V23: ULTRAVNC | W23: Admin | Y23: Акт 22.12.2023
A24: =A23+1 -> #REF! | B24: 239 | C24: Лейко Дарья Александровна | D24: Модернизация не требуется/normal (no need to upgrade) | E24: Rus | F24: Leyko Daria | G24: Заместитель директора цеха трансмиссии | H24: TM | I24: Laptop, mouse, bag | J24: Laptop MSI Modern 15 F1MG-800XRU | K24: поставить на учет | L24: Наклеить | N24: 1-03 офис окраски 2эт | O24: C2507N0002782 | P24: ="RUTL-" & RIGHT(O24,8) -> RUTL-N0002782 | Q24: Внесены в Passwork | R24: Professional Plus 2019 | T24: Windows 11 Pro | U24: KV9NX-4MRR2-B63VM-2JXV8-W44J2 | V24: ULTRAVNC / MESH | W24: No Administrator rights | X24: Кудрявцев Д. | Y24: Акт 27.03.2026 | Z24: 45989 | AA24: Стоимость ПК без НДС 59 160руб
A25: =A24+1 -> #REF! | B25: 243 | C25: Чучалин Роман Сергеевич | D25: Модернизация не требуется/normal (no need to upgrade) | E25: Rus | F25: Chuchalin Roman | G25: Заместитель руководителя отдела в подразделение Отдел контроля качества ТМ | H25: TM | I25: Laptop, mouse,bag | J25: Laptop IRBIS 15NBP3506 | K25: 100000003633 | L25: Наклеить | O25: F2715NBP35060820078 | P25: ="RUTL-" & RIGHT(O25,8) -> RUTL-60820078 | Q25: Внесены в Passwork | R25: Libre office | T25: Windows 10 Pro | U25: C4HD3-QN23F-VDKV2-93X3B-6VJXC | V25: ULTRAVNC / MESH | W25: No Administrator rights | X25: Фоменков В. | Y25: Акт 30.11.2024
A26: =A25+1 -> #REF! | B26: 244 | C26: Чеснокова Елена Николаевна | D26: Модернизация не требуется/normal (no need to upgrade) | E26: Rus | F26: Chesnokova Elena | G26: Лаборант | H26: CH Q&T, CH QA | I26: Laptop,mouse | J26: Laptop Dell Latitude 3450(C2) | K26: 140000014/Z000137 | L26: инвентарник ОС наклеен | M26: Внесен в ITSM AST0001707 | N26: 1-03 лаборатория окраски 1эт | O26: FPNPG22 | P26: ="RUTL-" & RIGHT(O26,8) -> RUTL-FPNPG22 | Q26: Внесены в Passwork | R26: Microsoft Office профессиональный плюс 2016 | T26: Win 7 Pro 64 | U26: 32KD2-K9CTF-M3DJT-4J3WC-733WD | V26: ULTRAVNC / MESH | W26: No Administrator rights | Y26: Акт 20.08.2018 | Z26: 42438 | AA26: БЕЗ НДС 45762,71 С НДС 54000
A27: =A26+1 -> #REF! | B27: 249 | C27: Казазаев Вадим Викторович | D27: Модернизация не требуется/normal (no need to upgrade) | E27: Rus | F27: Kazazaev Vadim | G27: Руководитель группы по переработке и утилизации отходов | H27: GD, GA, WMG | I27: Laptop, mouse | J27: Laptop Acer Extensa 15 | K27: 100000003365 | L27: наклеить | N27: 1-07 третий этаж | O27: NXEGYER00H32008CFE3400 | P27: ="RUTL-" & RIGHT(O27,8) -> RUTL-8CFE3400 | Q27: Внесены в Passwork | R27: Libre office | T27: Windows 10 Pro | V27: ULTRAVNC / MESH | W27: No Administrator rights | X27: Климанов А. | Y27: акт 18.03.2026 | Z27: 2024 | AA27: БЕЗ НДС 60440.50
A28: =A27+1 -> #REF! | B28: 258 | C28: Частников Артур Валерьевич | D28: была модернизация/upgraded (ремонт клавиатуры+SSD 256) | E28: Rus | F28: Chastnikov Artur | G28: Начальник участка | H28: PLD,ED | I28: Laptop,mouse | J28: Laptop Lenovo V510 | K28: 00000015291 | L28: инвентарник MOC наклеен | N28: 1-06 первый этаж | O28: LR0AVC0X | P28: ="RUTL-" & RIGHT(O28,8) -> RUTL-LR0AVC0X | Q28: Внесены в Passwork | U28: H82CM-NJYRT-9WYWR-8JPRQ-B98XC | V28: ULTRAVNC | Y28: Акт 22.09.2021
A29: =A28+1 -> #REF! | B29: 270 | C29: Глазов Евгений Павлович | D29: Модернизация не требуется/normal (no need to upgrade) | E29: Rus | F29: Glazov Evgeniy | G29: Инженер-электроник 2 категории | H29: M&U, UTL | I29: Laptop, mouse,bag | J29: Laptop IRBIS 17NBP4502 | K29: поставить на учет | N29: 1-13 крыло ютилити 2 эт | O29: F2717NBP4502103116 | P29: ="RUTL-" & RIGHT(O29,8) -> RUTL-02103116 | Q29: Внесены в Passwork | R29: 2019 for home and business | S29: Y77CV-RJNXD-472DD-GWBC8-29Y4G | T29: Windows 10 Pro | U29: Installed Key: VK7JG-NPHTM-C97JM-9MPGT-3V66T OEM Key: MQG4W-V8NHH-M8B6B-2382F-JHV22 | V29: ULTRAVNC / MESH | W29: Admin | X29: Кудрявцев Д. | Y29: Акт 19.09.2025 | AA29: Норм
A30: =A29+1 -> #REF! | B30: 278 | C30: Хармаев Василий Гаврилович | D30: Модернизация не требуется/normal (no need to upgrade) | E30: Rus | F30: Kharmaev Vasiliy | G30: Инженер по геометрии автомобиля 2 категории | H30: MD, WELD | I30: Laptop, mouse | J30: Laptop Lenovo V510 | K30: 00000016122 | L30: инвентарник MOC наклеен | N30: 1-02 офис цеха сварки 2 эт | O30: LR0AVC2T | P30: ="RUTL-" & RIGHT(O30,8) -> RUTL-LR0AVC2T | Q30: Внесены в Passwork | R30: SoftMaker FreeOffice 2021 | V30: ULTRAVNC / MESH | W30: No Administrator rights | X30: Климанов А. | Y30: Акт 01.12.2025
A31: =A30+1 -> #REF! | B31: 281 | C31: Дорофеев Иван | D31: Модернизация не требуется/normal (no need to upgrade) | E31: Rus | F31: Dorofeev Ivan | G31: Инженер-электроник 1 категории | H31: M&U, UTL | I31: Laptop,mouse,bag | J31: Laptop IRBIS 17NBP4502 | K31: Поставить на учет | L31: Наклеить | N31: 1-13 диспетчерская | O31: F2717NBP4502103038 | P31: ="RUTL-" & RIGHT(O31,8) -> RUTL-02103038 | Q31: Внесены в Passwork | R31: MS Office 2016/Microsoft Office профессиональный плюс 2019 — ru-ru | T31: Windows 10 Pro | U31: BTFDY-F2NTF-TY42R-4R72F-TVJXC | V31: ULTRAVNC / MESH | W31: Admin | X31: Летунов А. | Y31: Акт 17.03.2025
A32: =A31+1 -> #REF! | B32: 284 | C32: Тимченко Юлия Алексеевна | D32: Модернизация не требуется/normal (no need to upgrade) | E32: Rus | F32: Timchenko Yulia | G32: Начальник смены по качеству и технологии | H32: MD, PAINT | I32: Laptop, mouse | J32: Laptop IRBIS 15NBP3506 | K32: 100000003655 | L32: Наклеить | N32: 1-03 офис окраски 2эт | O32: F2715NBP35060820454 | P32: ="RUTL-" & RIGHT(O32,8) -> RUTL-60820454 | Q32: Внесены в Passwork | R32: Libre office | T32: Windows 10 Pro | U32: 4DN2D-GWYP7-39BJ7-FPHBC-KW3GP | V32: ULTRAVNC / MESH | W32: No Administrator rights | X32: Кудрявцев Д. | Y32: Акт от 07.12.2024
A33: =A32+1 -> #REF! | B33: 288 | C33: Макротаваров Михаил Иванович | D33: Модернизация не требуется/normal (no need to upgrade) | E33: Rus | F33: Makrotavarov Mikhail | G33: Заместитель руководителя отдела | H33: RDC,INFR | I33: Laptop,mouse | J33: Dell Vostro 7500 | K33: 10000001760 | L33: инвентарник ОС наклеен | N33: 1-07 второй этаж | O33: HCS51B3 | P33: ="RUTL-" & RIGHT(O33,8) -> RUTL-HCS51B3 | Q33: Внесены в Passwork | R33: ПАЛЕНКА Microsoft Office ????? 2021 - zh-cn | T33: Windows 10 Pro | U33: J2BNF-YDKKX-DDB37-G2JT2-TMT6P | V33: ULTRAVNC | W33: Admin | Y33: Акт 30.08.2021
A34: =A33+1 -> #REF! | B34: 293 | C34: Зажмилина Юлия Николаевна | D34: Модернизация не требуется/normal (no need to upgrade) | E34: Rus | F34: Zazhmilina Yulia | G34: Руководитель отдела | H34: MD, PM | I34: Laptop,mouse,bag | J34: Laptop MSI Modern 15 F1MG-800XRU | K34: поставить на учет | L34: Наклеить | N34: 1-09 второй этаж | O34: C2509N0008330 | P34: ="RUTL-" & RIGHT(O34,8) -> RUTL-N0008330 | Q34: Внесены в Passwork | T34: Windows 10 Pro | V34: ULTRAVNC / MESH | W34: No Administrator rights | X34: Мартынов Д. | Y34: Акт 22.01.2026
A35: =A734+1 -> #REF! | B35: 311 | C35: Ильин Дмитрий Михайлович | D35: Заменили на новый/Changed to New(no need to upgrade) | E35: Rus | F35: Ilyin Dmitriy | G35: Директор по безопасности и предотвращению рисков | H35: GD, SEC | I35: laptop,mouse, bag | J35: Laptop MSI Modern 15 F1MG-800XRU | K35: поставить на учет | N35: центральный КПП | O35: C2507N0002663 | P35: ="RUTL-" & RIGHT(O35,8) -> RUTL-N0002663 | Q35: Внесены в Passwork | T35: Windows 11 Pro | U35: NQJRW-B87PP-TYY2K-J4C72-HH66P | V35: - | W35: Admin | X35: Летунов А. | Y35: Акт 03.12.2025 | Z35: 45989 | AA35: Стоимость ПК без НДС 59 160руб
A36: =A47+1 -> #REF! | B36: 316 | C36: Тамбовцева Екатерина Юрьевна (316) | D36: Модернизация не требуется/normal (no need to upgrade) | E36: Rus | F36: Tambovtseva Ekaterina | G36: Заместитель руководителя отдела | H36: HRD, DP, HR DATA | I36: Laptop, mouse, Monitor Xiaomi A24i SN:54383/250100059569 | J36: Laptop MSI Modern 15 F1MG-800XRU | K36: поставить на учет | L36: Наклеить | N36: 1-07 третий этаж | O36: C2509N0008356 | P36: ="RUTL-" & RIGHT(O36,8) -> RUTL-N0008356 | Q36: Внесены в Passwork | R36: 2019 for home and business | T36: Windows 11 Pro | U36: 4NG8B-Y2VWK-GTCBC-6JYBR-GXX2P | V36: ULTRAVNC | W36: No Administrator rights | X36: Летунов А. | Y36: Акт 04.04.2026 | Z36: 45987 | AA36: Стоимость ПК без НДС 59 160руб
A37: =A734+1 -> #REF! | B37: 317 | C37: Белицкая Елена Александровна | D37: требуется модернизация/ need to modernisation | E37: Rus | F37: Belitskaya Elena | G37: Начальник участка | H37: PLD,ED | I37: Laptop, mouse,bag+usb ad | J37: Laptop Lenovo V110 | K37: 00000011075 | L37: инвентарник MOC наклеен | M37: Внесен в ITSM AST0002167 | N37: 1-06 второй этаж | O37: R90QN4X9 | P37: ="RUTL-" & RIGHT(O37,8) -> RUTL-R90QN4X9 | Q37: Внесены в Passwork | T37: Windows 10 Pro | U37: 6WNRY-PHJJ3-72YHR-DBDPT-HFR9C | V37: ULTRAVNC / MESH | W37: No Administrator rights | X37: Климанов А. | Y37: Акт 07.02.2026 | Z37: 43368 | AA37: БЕЗ НДС 33806,78, С НДС 39892
A38: =A37+1 -> #REF! | B38: 321 | C38: Мамкина Анастасия Викторовна | D38: Модернизация не требуется/normal (no need to upgrade) | E38: Rus | F38: Mamkina Anastasia | G38: Руководитель группы | H38: MD, PAINT | I38: Laptop,mouse | J38: Laptop IRBIS 15NBP3507 | K38: поставить на учет | L38: наклеить | N38: 1-07 Второй этаж | O38: F2715NBP35070820203 | P38: ="RUTL-" & RIGHT(O38,8) -> RUTL-70820203 | Q38: Внесены в Passwork | R38: Libre office | T38: Windows 10 Pro | U38: 94HGJ-NCRPY-GDJPY-9TCX4-PPQGP | V38: ULTRAVNC / MESH | W38: No Administrator rights | X38: Климанов А. | Y38: Акт 11.03.2026
A39: =A38+1 -> #REF! | B39: 329 | C39: Давыдов Александр Олегович ( 329 ) | D39: Модернизация не требуется/normal (no need to upgrade) | E39: Rus | F39: Davydov Alexander | G39: Заместитель директора департамента | H39: MD | I39: Laptop, mouse, bag | J39: Laptop MSI Modern 15 F1MG-800XRU | K39: поставить на учет | L39: Наклеить | N39: 1-02 офис цеха сварки 2 эт | O39: C2507N0003090 | P39: ="RUTL-" & RIGHT(O39,8) -> RUTL-N0003090 | Q39: Внесены в Passwork | R39: Libre office | T39: Windows 11 Pro | U39: GNMKF-FHVQC-4F6GR-7JVGQ-BG92P | V39: ULTRAVNC | W39: No Administrator rights | X39: Кудрявцев Д. | Y39: Акт 26.03.2026 | Z39: 45988 | AA39: Стоимость ПК без НДС 59 160руб
A40: =A39+1 -> #REF! | B40: 335 | C40: Попов Вадим Михайлович | D40: Модернизация не требуется/normal (no need to upgrade) | E40: Rus | F40: Popov Vadim | G40: Заместитель начальника цеха | H40: MD, Paint | I40: Laptop, mouse | J40: Laptop MSI Modern 15 F1MG-800XRU | K40: поставить на учет | L40: Наклеить | O40: C2507N0003035 | P40: ="RUTL-" & RIGHT(O40,8) -> RUTL-N0003035 | Q40: Внесены в Passwork | R40: 2019 for home and business | T40: Windows 11 Pro | U40: 2P9KR-RBN69-WHW89-MGFBT-H8RJ2 | V40: ULTRAVNC / MESH | W40: No Administrator rights | X40: Летунов А. | Y40: Акт 18.02.2026 | Z40: 45989 | AA40: Стоимость ПК без НДС 59 160руб
A41: =A40+1 -> #REF! | B41: 369 | C41: Омелечко Андрей Николаевич | D41: требуется модернизация/ЗАМЕНА | E41: Rus | F41: Omelechko Andrey | G41: Руководитель группы по качеству | H41: MD, AS | I41: Laptop,mouse | J41: Laptop Lenovo t440p | K41: поставить на учет | L41: МОСКВА | N41: 1-04 офис сборки | O41: PB02JDTF | P41: ="RUTL-" & RIGHT(O41,8) -> RUTL-PB02JDTF | Q41: Внесены в Passwork | U41: RNJMK-CFKPY-YQCT9-3D3CC-P9T72 | V41: ULTRAVNC | Y41: Акт 11.04.2022
A42: =A41+1 -> #REF! | B42: 413 | C42: Дорохов Роман Алексеевич | D42: была модернизация/upgraded (SSD 256) | E42: Rus | F42: Dorokhov Roman | G42: Начальник участка | H42: MD, PAINT | I42: Laptop,mouse | J42: Laptop Lenovo V510 | K42: 00000011592 | L42: инвентарник MOC наклеен | N42: 1-03 офис окраски 2эт | O42: LR08MD8A | P42: ="RUTL-" & RIGHT(O42,8) -> RUTL-LR08MD8A | Q42: Внесены в Passwork | T42: Windows 10 Pro | U42: JN46D-VH4PK-2JDX9-3J8RV-MBH22 | V42: ULTRAVNC / MESH | W42: No Administrator rights | X42: Летунов А. | Y42: Акт 20.01.2023
A43: =A42+1 -> #REF! | B43: 430 | C43: Мартынова Татьяна Сергеевна | D43: была модернизация/upgraded(SSD 480+RAM 8 from RDC reserve) | E43: Rus | F43: Martynova Tatiana | G43: Старший кладовщик | H43: M&U, UTL | I43: Laptop, mouse,bag | J43: Laptop Lenovo V510 | K43: 00000011584 | L43: инвентарник MOC наклеен | M43: Внесен в ITSM AST0001711 | N43: 1-02 склад MU | O43: LR08MDB7 | P43: ="RUTL-" & RIGHT(O43,8) -> RUTL-LR08MDB7 | Q43: Внесены в Passwork | R43: MS Office 2016 | T43: Windows 10 Pro | V43: ULTRAVNC | Y43: Акт от 01.11.2018
A44: =A43+1 -> #REF! | B44: 435 | C44: Гаврилова Екатерина Сергеевна | D44: Модернизация не требуется/normal (no need to upgrade) | E44: Rus | F44: Gavrilova Ekaterina | G44: Начальник участка | H44: CH, PLD | I44: Laptop,mouse | J44: Laptop HP 250 G7 | K44: 100000001600 | L44: Наклеить | M44: Внесен в ITSM AST0000855 | N44: 1-04 аппендикс где логистика | O44: CND1250618 | P44: ="RUTL-" & RIGHT(O44,8) -> RUTL-D1250618 | Q44: Внесены в Passwork | R44: libtre office | T44: Windows 10 Pro | V44: ULTRAVNC | Y44: Акт от 08.08.2024 | Z44: 44551 | AA44: без НДС 39916,67 с НДС 47900
A45: =A44+1 -> #REF! | B45: 442 | C45: Данилов Павел Леонидович | D45: была модернизация/upgraded (SSD 256) но нужна RAM | E45: Rus | F45: Danilov Pavel | G45: Начальник участка | H45: MD, PAINT | I45: Laptop, mouse,bag | J45: Laptop Lenovo V 130(наклеить) | K45: 00000019366(2) | L45: инвентарник MOC наклеен | N45: 20 сгп офис ASSE | O45: R90T947G | P45: ="RUTL-" & RIGHT(O45,8) -> RUTL-R90T947G | Q45: Внесены в Passwork | V45: ULTRAVNC | Y45: акт 12-09-2019 | Z45: 43661
A46: =A45+1 -> #REF! | B46: 444 | C46: Чкунин Юрий Юрьевич | D46: была модернизация/upgraded (SSD 256) ОЗУ 12 | E46: Rus | F46: Chkunin Yuriy | G46: Начальник участка | H46: PLD, DL | I46: Laptop,mouse | J46: Laptop Lenovo L340 | K46: 00000022303(2) | L46: Наклеить | N46: 20 сгп офис ASSE | O46: PF14T18U | P46: ="RUTL-" & RIGHT(O46,8) -> RUTL-PF14T18U | Q46: Внесены в Passwork | R46: Microsoft Office профессиональный плюс 2016 | T46: Windows 10 Pro | U46: 94DHF-NJM4R-MHWPH-GWCCR-844C2 | V46: ULTRAVNC / MESH | W46: No Administrator rights | X46: Кудрявцев Д. | Y46: Акт 22.09.2025
A47: =A46+1 -> #REF! | B47: 445 | C47: Алексеенко Михаил Михайлович | D47: Модернизация не требуется/normal (no need to upgrade) | E47: Rus | F47: Alekseenko Mikhail | G47: Ведущий инженер-технолог | H47: CH, QI | I47: Laptop, mouse,bag | J47: Laptop IRBIS 15NBP3506 | K47: 100000003630 | L47: Наклеить | N47: 1-07 четвертый этаж | O47: F2715NBP35060820191 | P47: ="RUTL-" & RIGHT(O47,8) -> RUTL-60820191 | Q47: Внесены в TeamPass | R47: Libre office | V47: ULTRAVNC / MESH | Y47: 2026
A48: =A47+1 -> #REF! | B48: 455 | C48: Власова Ольга Афанасьевна | D48: Заменили на новый/Changed to New(no need to upgrade) | E48: Rus | F48: Vlasova Olga | G48: Аудитор готового автомобиля | H48: Q&T, QI | I48: Laptop,mouse,bag+Lan-USB | J48: Laptop Lenovo V15 G1+Lan-USB | K48: 100000001624 | L48: Наклеить | N48: 1-09 второй этаж | O48: PF2TYG12 | P48: ="RUTL-" & RIGHT(O48,8) -> RUTL-PF2TYG12 | Q48: Внесены в Passwork | R48: MS Office 2016 | T48: Windows 10 Pro | V48: ULTRAVNC / MESH | W48: No Administrator rights | Y48: акт 30-09-2021/ акт 02-08-24 /акт 05,09,24
A49: =A48+1 -> #REF! | B49: 461 | C49: Смелык Андрей Владимирович | D49: была модернизация/upgraded (480 SSD) | E49: Rus | F49: Smelyk Andrey | G49: Начальник участка обслуживания оборудования | H49: M&U, MTC S&W | I49: AiO, mouse, keyboard | J49: AiO Lenovo S400Z | K49: 150000015/Z000007 | L49: Наклеить | N49: 1-02 офис MU цеха сварки | O49: P901FSL3 | P49: ="RUTL-" & RIGHT(O49,8) -> RUTL-P901FSL3 | Q49: Внесены в Passwork | U49: XNMKK-VG7Y9-YK9JC-TR6WG-4M6GC | V49: ULTRAVNC | Y49: Акт 26.01.2021
A50: =A49+1 -> #REF! | B50: 476 | C50: Володин Сергей Владимирович | D50: Модернизация не требуется/normal (no need to upgrade) | E50: Rus | F50: Volodin Sergey | G50: Ведущий инженер-электроник | H50: M&U, MTC S&W | I50: Laptop,mouse | J50: Laptop IRBIS 17NBP4502 | K50: поставить на учет | L50: Наклеить | N50: 1-02 офис MU цеха сварки | O50: F2717NBP4502103178 | P50: ="RUTL-" & RIGHT(O50,8) -> RUTL-02103178 | Q50: Внесены в Passwork | R50: libtre office | T50: Windows 10 Pro | U50: CKJD4-4NXD8-2HGM9-3HFVW-6MT6P | V50: ULTRAVNC / MESH | W50: Admin | X50: Кудрявцев Д. | Y50: Акт 12.03.2025
A51: =A50+1 -> #REF! | B51: 483 | C51: Цыганков Павел Михайлович | D51: Заменили на новый/Changed to New(no need to upgrade) | E51: Rus | F51: Tsygankov Pavel | G51: Директор департамента | H51: PLD | I51: laptop,mouse, bag | J51: Laptop MSI Modern 15 F1MG-800XRU | K51: поставить на учет | L51: Наклеить | N51: 1-04 аппендикс где логистика | O51: C2507N0002765 | P51: ="RUTL-" & RIGHT(O51,8) -> RUTL-N0002765 | Q51: Внесены в Passwork | R51: 2019 for home and business | T51: Windows 11 Pro | U51: NH2YF-JYC8H-K99BM-79CCV-4C2TC | V51: ULTRAVNC / MESH | W51: No Administrator rights | X51: Кудрявцев Д. | Y51: Акт 09.12.2025 | Z51: 45989 | AA51: Стоимость ПК без НДС 59 160руб
A52: =A51+1 -> #REF! | B52: 495 | C52: Попков Александр Александрович | D52: Модернизация не требуется/normal (no need to upgrade) | E52: Rus | F52: Popkov Aleksander | G52: Начальник участка обслуживания оборудования | H52: CH, MU | I52: Laptop, mouse, bag | J52: Laptop IRBIS 15NBP3506 | K52: 100000003641 | L52: наклеить | N52: 1-07 четвертый этаж | O52: F2715NBP35060820350 | P52: ="RUTL-" & RIGHT(O52,8) -> RUTL-60820350 | Q52: Внесены в Passwork | R52: Libre Office / Only office | T52: Windows 10 Pro | U52: TNKTC-6FMKR-BK4RG-DYMYV-46YP2 | V52: ULTRAVNC / MESH | W52: No administrator rights | X52: Климанов А. | Y52: Акт 07.02.2026
A53: =A51+1 -> #REF! | B53: 504 | C53: Ремизов Дмитрий Викторович | D53: Модернизация не требуется/normal (no need to upgrade) | E53: Rus | F53: Remizov Dmitry | G53: Руководитель инженерной группы | H53: MD, PAINT | I53: Laptop, mouse | J53: Laptop IRBIS 15NBP3506 | K53: 100000003586 | L53: Наклеить | N53: 1-03 офис окраски 2эт | O53: F2715NBP35060820814 | P53: ="RUTL-" & RIGHT(O53,8) -> RUTL-60820814 | Q53: Внесены в Passwork | R53: Libre office | T53: Windows 10 Pro | V53: ULTRAVNC / MESH | W53: No Administrator rights | X53: Мартынов Д. | Y53: Акт 31.03.2026
A54: ='ПК с 1 владельцем'!A684+1 -> #REF! | B54: 511 | C54: Трофимов Владимир Юрьевич | D54: Модернизация не требуется/normal (no need to upgrade) | E54: Rus | F54: Trofimov Vladimir | G54: Заместитель руководителя отдела | H54: CH, PLD | I54: Laptop, mouse,bag | J54: Acer Aspire 5 A515-57-5703 | K54: поставить на учет | L54: наклеить | N54: 1-09 третий этаж (цех chassiс) | O54: NXKN3CD00J43500F113400 | P54: ="RUTL-" & RIGHT(O54,8) -> RUTL-0F113400 | Q54: Внесены в Passwork | R54: Libre office | T54: Windows 11 Pro | U54: 6NPR3-63B7J-W28Q4-8F3DF-DJ3GP | V54: ULTRAVNC / MESH | W54: No administrator rights | X54: Летунов А. | Y54: Акт 13.08.2025 | Z54: 45880 | AA54: БЕЗ НДС 45080, С НДС 54096
A55: =A54+1 -> #REF! | B55: 516 | C55: Кочетов Сергей Михайлович | D55: Модернизация не требуется/normal (no need to upgrade) | E55: Rus | F55: Kochetov Sergey | G55: Начальник смены технического обслуживания оборудования 2 категории | H55: M&U, MTC ASPC | I55: AiO, mouse, keyboard | J55: AiO Lenovo M810Z | K55: 140000160/Z000078 | L55: Наклеить | N55: 1-04 офис MU цеха сборки | O55: S4FM3429 | P55: ="RUTL-" & RIGHT(O55,8) -> RUTL-S4FM3429 | Q55: Внесены в Passwork | T55: Windows 10 Pro | V55: ULTRAVNC | W55: Admin | Y55: Акт 07.03.2023
A56: =A55+1 -> #REF! | B56: 542 | C56: Астаркин Евгений Сергеевич | D56: Модернизация не требуется/normal (no need to upgrade) | E56: Rus | F56: Astarkin Evgeniy | G56: Ведущий инженер-электроник | H56: M&U, MTC ASPC | I56: Laptop,mouse | J56: Laptop Acer NITRO 5 AN 515-55-72ST | K56: поставить на учет | N56: 1-03 офис MU окраски 1эт | O56: NHQB2CN0021070BC303400 | P56: ="RUTL-" & RIGHT(O56,8) -> RUTL-BC303400 | Q56: Внесены в Passwork | R56: Microsoft Office профессиональный плюс 2016 | T56: Windows 10 Pro | U56: BJNX3-F4B2V-WWDD2-F2KBG-2378X | V56: ULTRAVNC / MESH | W56: Admin | Y56: Акт 12.08.2021
A57: =A56+1 -> #REF! | B57: 546 | C57: Черкасова Диана Вячеславовна | D57: Модернизация не требуется/normal (no need to upgrade) | E57: Rus | F57: Cherkasova Diana | G57: Ведущий специалист бюро пропусков | H57: GD, SEC, SG | I57: Laptop,mouse | J57: Laptop Acer Extensa 15 | K57: 100000003331 | L57: Наклеить | O57: NXEGYER00H320088D83400 | P57: ="RUTL-" & RIGHT(O57,8) -> RUTL-88D83400 | Q57: Внесены в Passwork | T57: Windows 10 Pro | V57: ULTRAVNC / MESH | Y57: Акт 31.08.2024 | Z57: 2024 | AA57: БЕЗ НДС 60440.50
A58: =A57+1 -> #REF! | B58: 548 | C58: Наумов Павел Анатольевич | D58: Модернизация не требуется/normal (no need to upgrade) | E58: Rus | F58: Naymov Pavel | G58: Заместитель руководителя отдела | H58: PMD, PS | I58: Laptop, mouse, bag | J58: Laptop Acer Extensa 15 | K58: 100000003335 | L58: Наклеить | O58: NXEGYER00H320086E73400 | P58: ="RUTL-" & RIGHT(O58,8) -> RUTL-86E73400 | Q58: Внесены в Passwork | R58: Libre office | T58: Windows 10 Pro | V58: ULTRAVNC / MESH | W58: No Administrator rights | X58: Летунов А. | Y58: Акт 10.02.2026 | Z58: 2024 БЕЗ НДС 60440.50
A59: =A58+1 -> #REF! | B59: 557 | C59: Федотов Денис Андреевич | D59: Модернизация не требуется/normal (no need to upgrade) | E59: Rus | F59: Fedotov Denis | G59: Руководитель группы учета | H59: PMD, PS | I59: AiO, mouse, keyboard | J59: AiO Lenovo V30A | K59: 10000001770 | L59: Наклеить | N59: 1-07 четвертый этаж | O59: MP1Z7VHR | P59: ="RUTL-" & RIGHT(O59,8) -> RUTL-MP1Z7VHR | Q59: Внесены в Passwork | R59: 2019 for home and business | S59: JT4JK-CXND4-8M9CJ-MGJG8-D9P6G | T59: Windows 10 Pro | V59: ULTRAVNC / MESH | W59: No Administrator rights | X59: Летунов А. | Y59: Акт 14.02.2026
A60: =A59+1 -> #REF! | B60: 565 | C60: Кузнецов Михаил Сергеевич | D60: Модернизация не требуется/normal (no need to upgrade) | E60: Rus | F60: Kuznetsov Mikhail | G60: Заместитель руководителя отдела | H60: TM | I60: Laptop, mouse,bag | J60: Lenovo ThinkBook 16 G7 ARP 3 | K60: поставить на учет | L60: Наклеить | N60: 1-09 второй этаж | O60: PW0LW3P7 | P60: ="RUTL-" & RIGHT(O60,8) -> RUTL-PW0LW3P7 | Q60: Внесены в Passwork | R60: Libre Office / Only office | T60: Windows 11 Pro | U60: CGJTB-N8YP3-4KKDV-KY8JH-94TPT | V60: ULTRAVNC / MESH | W60: No Administrator rights | X60: Кудрявцев Д. | Y60: Акт 28.03.2026 | AA60: С НДС 64660 БЕЗ НДС 53000
A61: =A60+1 -> #REF! | B61: 577 | C61: Веселова Полина Олеговна | D61: была модернизация/upgraded ( 256 SSD +ram from rdc reserve) | E61: Rus | F61: Veselova Polina | G61: Специалист системы менеджмента качества | H61: Q&T, QM | I61: Laptop, mouse,bag | J61: Laptop Lenovo V510 | K61: 00000015288 | L61: инвентарник MOC наклеен | O61: LR0AVC1P | P61: ="RUTL-" & RIGHT(O61,8) -> RUTL-LR0AVC1P | Q61: Внесены в Passwork | R61: Microsoft Office 2007 Service Pack 3 (SP3) | V61: ULTRAVNC / MESH | Y61: Акт 10.09.2019
A62: =A61+1 -> #REF! | B62: 627 | C62: Корзиенко Ирина Викторовна | D62: была модернизация/upgraded(SSD 256+ RAM+4) (8 ram) | E62: Rus | F62: Korzienko Irina | G62: Специалист TPS | H62: MD, PAINT | I62: Laptop,mouse | J62: Laptop Lenovo ThinkPad EDGE E570 | K62: 140000058/Z000106 | L62: инвентарник MOC наклеен | M62: Внесен в ITSM AST0000607 | N62: 1-03 офис окраски 2эт | O62: PF0XKWTE | P62: ="RUTL-" & RIGHT(O62,8) -> RUTL-PF0XKWTE | Q62: Внесены в Passwork | R62: Microsoft Office профессиональный плюс 2016 | T62: Windows 10 Pro | U62: MQVD3-HP4DK-K24K2-D28F9-WTYP2 | V62: ULTRAVNC / MESH | W62: No Administrator rights | Y62: Акт 12.07.2024
A63: =A62+1 -> #REF! | B63: 643 | C63: Афанасьева Елена Романовна | D63: Модернизация не требуется/normal (no need to upgrade) | E63: Rus | F63: Afanasyeva Elena | G63: Экономист | H63: MD, COMP | I63: Laptop, mouse,+lan USB | J63: Laptop Dell Inspiron 15 3511 | K63: 100000001656 | L63: Наклеить | N63: 1-09 второй этаж | O63: 1K50JK3 | P63: ="RUTL-" & RIGHT(O63,8) -> RUTL-1K50JK3 | Q63: Внесены в Passwork | V63: ULTRAVNC / MESH | W63: No Administrator rights | X63: Климанов А. | Y63: Акт 21.03.2026 | Z63: 44551 | AA63: БЕЗ НДС 81250,00 с НДС 97500
A64: =A63+1 -> #REF! | B64: 664 | C64: Люкин Максим Анатольевич | D64: Модернизация не требуется/normal (no need to upgrade) | E64: Rus | F64: Lyukin Maksim | G64: Руководитель инженерной группы | H64: MD, AS | I64: Laptop,mouse | J64: Acer Aspire Lite 15 AL15-41 | K64: поставить на учет | L64: Наклеить | N64: 1-04 офис цеха сборки | O64: UN31ZSI04F533024CA0700 | P64: ="RUTL-" & RIGHT(O64,8) -> RUTL-24CA0700 | Q64: Внесены в Passwork | R64: Microsoft Office профессиональный плюс 2019 | V64: ULTRAVNC / MESH | W64: No Administrator rights | X64: Климанов А. | Y64: Акт 04.12.2025 | Z64: 45975 | AA64: БЕЗ НДС 36790 с НДС -
A65: =A64+1 -> #REF! | B65: 666 | C65: Клеменов Александр Сергеевич | D65: Модернизация не требуется/normal (no need to upgrade) | E65: Rus | F65: Klemenov Alexander | G65: Инженер-технолог 1 категории | H65: MD, AS | I65: Laptop,mouse | J65: Acer Aspire Lite 15 AL15-41 | K65: поставить на учет | L65: Наклеить | N65: 1-04 офис цеха сборки | O65: UN31ZSI04F533023F60700 | P65: ="RUTL-" & RIGHT(O65,8) -> RUTL-23F60700 | Q65: Внесены в Passwork | R65: Libre Office / Only office | T65: Windows 11 Pro | U65: D2PKV-MNQ3R-6TQPC-GP8RF-2KC2T | V65: ULTRAVNC / MESH | W65: No administrator rights | X65: Кудрявцев Д. | Y65: Акт от 11.12.2025 | Z65: 45975 | AA65: БЕЗ НДС 36790 с НДС -
A66: =A65+1 -> #REF! | B66: 668 | C66: Карпунин Артур Александрович | D66: Модернизация не требуется/normal (no need to upgrade) | E66: Rus | F66: Karpunin Artur | G66: Начальник смены | H66: MD, COMP | I66: Laptop,mouse+Lan-USB | J66: Laptop Lenovo V15 G1+Lan-USB | K66: 100000001650 | L66: Наклеить | N66: 1-04 офис дет. Интерьера | O66: PF2VTMA0 | P66: ="RUTL-" & RIGHT(O66,8) -> RUTL-PF2VTMA0 | Q66: Внесены в Passwork | R66: 2019 for home and business | Y66: Акт 29.08.2021
A67: =A66+1 -> #REF! | B67: 673 | C67: Змеев Сергей Викторович | D67: Модернизация не требуется/normal (no need to upgrade) | E67: Rus | F67: Zmeev Sergey | G67: Инженер по производственному оборудованию | H67: M&U, MTC ASPC | I67: Laptop,mouse | J67: Laptop IRBIS 15NBP3506 | K67: 100000003634 | L67: Наклеить | N67: 1-03 Комната инженерной группы | O67: F2715NBP35060820527 | P67: ="RUTL-" & RIGHT(O67,8) -> RUTL-60820527 | Q67: Внесены в Passwork | R67: Libre office | T67: Windows 10 Pro | U67: XNG97-RMBTH-6WK8Q-8828Q-MDWXC | V67: ULTRAVNC / MESH | W67: No Administrator rights | X67: Фоменков В. | Y67: Акт от 30.11.2024
A68: =A67+1 -> #REF! | B68: 681 | C68: Пахалова Ольга Валентиновна | D68: Модернизация не требуется/normal (no need to upgrade) | E68: Rus | F68: Pakhalova Olga | G68: Старший кладовщик | H68: M&U, HSE | I68: AiO, mouse, keyboard | J68: AiO Lenovo M810Z | K68: 140000148/Z000094 | L68: Наклеить | N68: 1-09 второй этаж | O68: S4FM3417 | P68: ="RUTL-" & RIGHT(O68,8) -> RUTL-S4FM3417 | Q68: Внесены в Passwork | U68: 6NY4M-XFMRQ-BFM4H-PFHQK-GJF9C | V68: ULTRAVNC / MESH | W68: No Administrator rights | X68: Кудрявцев Д. | Y68: Акт 04.10.2024
A69: =A68+1 -> #REF! | B69: 689 | C69: Гончаренко Павел Александрович | D69: Модернизация не требуется/normal (no need to upgrade) | E69: Rus | F69: Goncharenko Pavel | G69: Ведущий инженер | H69: M&U, PLE | I69: Laptop,mouse | J69: Laptop Acer NITRO 5 AN515-54 | K69: поставить на учет | N69: 1-02 офис MU цеха сварки | O69: NHQ59ER0179350C6EF3400 | P69: ="RUTL-" & RIGHT(O69,8) -> RUTL-C6EF3400 | Q69: Внесены в Passwork | W69: Admin | Y69: Акт 28.05.2021
A70: =A69+1 -> #REF! | B70: 702 | C70: Миляев Виталий Александрович | D70: Модернизация не требуется/normal (no need to upgrade) | E70: Rus | F70: Milyaev Vitaliy | G70: Начальник участка | H70: PLD, WL | I70: Laptop,mouse,Lan tp-link | J70: Laptop Lenovo ThinkPad EDGE E570 | K70: 140000060/Z000104 | L70: Наклеить | N70: 1-06 первый этаж | O70: PF0W18W7 | P70: ="RUTL-" & RIGHT(O70,8) -> RUTL-PF0W18W7 | Q70: Внесены в Passwork | R70: Microsoft Office профессиональный плюс 2016 | T70: Windows 10 Pro | U70: P4KRW-T63R7-KCDT7-T92FV-6XXTP | V70: ULTRAVNC / MESH | W70: no need | X70: Климанов А.К \ Кудрявцев Д.\ Мартынов Д. | Y70: акт 01.11.2024
A71: =A70+1 -> #REF! | B71: 708 | C71: Белоглазов Андрей Юрьевич | D71: Модернизация не требуется/normal (no need to upgrade) | E71: Rus | F71: Beloglazov Andrey | G71: Руководитель группы обслуживания зданий и сооружений | H71: M&U, UTL | I71: Laptop,mouse,bag | J71: Laptop IRBIS 15NBP3506 | K71: поставить на учет | L71: наклеить | O71: F2715NBP35060821348 | P71: ="RUTL-" & RIGHT(O71,8) -> RUTL-60821348 | Q71: Внесены в Passwork | R71: Libre office | T71: Windows 10 Pro | U71: 8VRHK-NHHHP-RD38F-GW7GY-92FC2 | V71: ULTRAVNC / MESH | W71: No Administrator rights | X71: Фоменков В. | Y71: Акт 07.12.2024
A72: =A71+1 -> #REF! | B72: 711 | C72: Репин Сергей Алексеевич | D72: Модернизация не требуется/normal (no need to upgrade) | E72: Rus | F72: Repin Sergey | G72: Заместитель директора департамента | H72: M&U | I72: Laptop, mouse,bag | J72: Laptop MSI Modern 15 F1MG-800XRU | K72: поставить на учет | L72: наклеить | N72: 1-09 второй этаж | O72: C2507N0002595 | P72: ="RUTL-" & RIGHT(O72,8) -> RUTL-N0002595 | Q72: Внесены в Passwork | R72: 2019 for home and business | S72: 3H8XT-PN3WH-GVQR6-MMGJQ-63CYT | T72: Windows 11 Pro | U72: WJFNF-XGY8Q-DCY3J-QHBXY-XBT6P | V72: ULTRAVNC / MESH | W72: No Administrator rights | X72: Кудрявцев Д. | Y72: Акт 16.12.2025 | Z72: 45989 | AA72: Стоимость ПК без НДС 59 160руб
A73: =A72+1 -> #REF! | B73: 714 | C73: Горох Алексей Алексеевич | D73: Модернизация не требуется/normal (no need to upgrade) | E73: Rus | F73: Gorokh Alexey | G73: Начальник участка | H73: MD, PAINT | I73: Laptop,mouse | J73: Acer Aspire 5 A515-57-506D | K73: поставить на учет | L73: наклеить | N73: цех окраски | O73: NXKN3CD0014511069B3400 | P73: ="RUTL-" & RIGHT(O73,8) -> RUTL-069B3400 | Q73: Внесены в Passwork | T73: Windows 11 Pro | V73: ULTRAVNC / MESH | W73: No Administrator rights | X73: Мартынов Д. | Y73: Акт 06.11.2025 | AA73: БЕЗ НДС 50360, С НДС 60432
A74: =A73+1 -> #REF! | B74: 734 | C74: Карпышев Александр Игоревич | D74: Модернизация не требуется/normal (no need to upgrade) | E74: Rus | F74: Karpyshev Alexander | G74: Инженер по автоматизированным системам | H74: GD, CONSTR | I74: Laptop,mouse,bag | J74: Laptop MSI Modern 15 F1MG-800XRU | L74: Наклеить | O74: C2507N0003092 | P74: ="RUTL-" & RIGHT(O74,8) -> RUTL-N0003092 | Q74: Внесены в Passwork | T74: Windows 11 Pro | U74: 6JNW4-VC8JV-J9PPD-VBP7M-X4R9C | V74: ULTRAVNC / MESH | W74: No Administrator rights | X74: Климанов А. | Y74: Акт 15.01.2026
A75: =A74+1 -> #REF! | B75: 737 | C75: Воробьева Дарья Витальевна | D75: Модернизация не требуется/normal (no need to upgrade) | E75: Rus | F75: Vorobyova Darya | G75: Руководитель группы по внешним связям | H75: GD, LEG, ER | I75: Laptop, mouse | J75: Laptop Acer Extensa 15 | K75: 100000003345 | L75: наклеить | N75: 1-07 третий этаж | O75: NXEGYER00H320089203400 | P75: ="RUTL-" & RIGHT(O75,8) -> RUTL-89203400 | Q75: Внесены в Passwork | T75: Windows 10 Pro | U75: YYN2G-HW73Q-344KD-CPPHX-M98XC | V75: ULTRAVNC / MESH | W75: No Administrator rights | X75: Кудрявцев Д. | Y75: Акт 27.01.2026 | Z75: 2024 | AA75: БЕЗ НДС 60440.50
A76: =A75+1 -> #REF! | B76: 757 | C76: Ларионов Максим Алексеевич | D76: Модернизация не требуется/normal (no need to upgrade) | E76: Rus | F76: Larionov Maksim | G76: Руководитель отдела | H76: Q&T, QT | I76: Laptop,mouse | J76: Laptop MSI Modern 15 F1MG-800XRU | K76: поставить на учет | L76: Наклеить | N76: 1-09 второй этаж | O76: C2509N0008389 | P76: ="RUTL-" & RIGHT(O76,8) -> RUTL-N0008389 | Q76: Внесены в Passwork | R76: MS Office 2019 Pro Plus | S76: QBGDN-JX4VG-BHG28-Q7K6F-BY7PT | T76: Windows 11 Pro | U76: DBY6N-8T84C-3Q8FB-V4T9C-RVV82 | V76: ULTRAVNC / MESH | W76: No Administrator rights | X76: Кудрявцев Д. | Y76: Акт 26.02.2026 | Z76: 45989 | AA76: Стоимость ПК без НДС 59 160руб
A77: =A76+1 -> #REF! | B77: 780 | C77: Моргачев Сергей Андреевич | D77: Модернизация не требуется/normal (no need to upgrade) | E77: Rus | F77: Morgachev Sergey | G77: Инженер по ходовой части и силовым агрегатам автомобиля 3 категории | H77: Q&T, QT | I77: Laptop, mouse,bag | J77: Laptop HP 250 G7 | K77: 100000001598 | L77: Наклеить | M77: Внесен в ITSM AST0000851 | N77: 1-09 второй этаж | O77: CND12505ST | P77: ="RUTL-" & RIGHT(O77,8) -> RUTL-D12505ST | Q77: Внесены в Passwork | R77: Microsoft Office профессиональный плюс 2016 | S77: BN4XJ-R9DYY-96W48-YK8DM-MYZPY | T77: Windows 10 Pro | V77: ULTRAVNC | W77: No Administrator rights | X77: Летунов А. | Y77: Акт 10.03.2025 | Z77: 44551 | AA77: без НДС 39916,67 с НДС 47900
A78: =A77+1 -> #REF! | B78: 786 | C78: Тараторкина Ника Олеговна | D78: была модернизация/upgraded (SSD 480 +RAM8) | E78: Rus | F78: Taratorkina Nika | G78: Ведущий специалист по персоналу | H78: HRD, DP, HR DATA | I78: AiO, mouse, keyboard | J78: IRBIS SMART AIO MB2389 | K78: 100000003578 | L78: Наклеить | N78: 1-07 третий этаж | O78: 2407A12H424I5M2165R00009 | P78: ="RUTL-" & RIGHT(O78,8) -> RUTL-65R00009 | Q78: Внесены в Passwork | R78: Microsoft Office профессиональный плюс 2019 | T78: Windows 10 Pro | U78: F9FN9-G2HWF-WXJ9G-PQ933-3PFC2 | V78: ULTRAVNC / MESH | W78: No Administrator rights | X78: Кудрявцев Д. | Y78: Акт 28.03.2025
A79: =A78+1 -> #REF! | B79: 795 | C79: Лубянкин Максим Александрович | D79: Модернизация не требуется/normal (no need to upgrade) | E79: Rus | F79: Liubyankin Maksim | G79: Ведущий инженер-электроник | H79: M&U, MTC S&W | I79: Laptop,mouse | J79: Laptop Acer Extensa 15 | K79: 100000003332 | L79: Наклеить | N79: 1-04 офис MU цеха сборки | O79: NXEGYER00H3200897C3400 | P79: ="RUTL-" & RIGHT(O79,8) -> RUTL-897C3400 | Q79: Внесены в Passwork | V79: ULTRAVNC | W79: Admin | Y79: Акт 04.07.2024 | Z79: 2024 | AA79: БЕЗ НДС 60440.50
A80: =A79+1 -> #REF! | B80: 818 | C80: Поляков Вадим Алексеевич | D80: Модернизация не требуется/normal (no need to upgrade) | E80: Rus | F80: Polyakov Vadim | G80: Инженер-электроник 1 категории | H80: M&U, MTC ASPC | I80: Laptop,mouse | J80: Laptop IRBIS 15NBP3506 | K80: 100000003583 | L80: Наклеить | N80: 1-03 офис MU | O80: F2715NBP35060821255 | P80: ="RUTL-" & RIGHT(O80,8) -> RUTL-60821255 | Q80: Внесены в Passwork | R80: Libre office | T80: Windows 10 Pro | V80: ULTRAVNC / MESH | W80: No Administrator rights | X80: Кудрявцев Д. | Y80: Акт 28.11.2025
A81: =A80+1 -> #REF! | B81: 856 | C81: Тишин Алексей Викторович | D81: Модернизация не требуется/normal (no need to upgrade) | E81: Rus | F81: Tishin Alexey | G81: Инженер по деталям интерьера и экстерьера 2 категории | H81: Q&T, QT | I81: Laptop,mouse+Lan-USB | J81: Laptop Lenovo V15 G1+Lan-USB | K81: 100000001626 | L81: Наклеить | M81: Внесен в ITSM AST0000876 | N81: 1-09 второй этаж | O81: PF2VTHSH | P81: ="RUTL-" & RIGHT(O81,8) -> RUTL-PF2VTHSH | Q81: Внесены в Passwork | R81: 2019 for home and business | V81: ULTRAVNC | Y81: акт 29-08-2021
A82: =A81+1 -> #REF! | B82: 861 | C82: Болотов Владимир Николаевич | D82: Модернизация не требуется/normal (no need to upgrade) | E82: Rus | F82: Bolotov Vladimir | G82: Инженер по производственному оборудованию | H82: M&U, MTC ASPC | I82: Laptop, mouse,bag | J82: Laptop IRBIS 15NBP3506 | K82: 100000003610 | L82: Наклеить | N82: СКЛАД | O82: F2715NBP35060820288 | P82: ="RUTL-" & RIGHT(O82,8) -> RUTL-60820288 | Q82: Внесены в Passwork | R82: Libre office | T82: Windows 10 Pro | U82: 8KXPN-QP9PP-GPJM9-FD82Y-43KTP | V82: ULTRAVNC / MESH | W82: No Administrator rights | X82: Кудрявцев Д. | Y82: Акт 10.03.2026
A83: =A82+1 -> #REF! | B83: 869 | C83: Журавлев Алексей Валерьевич | D83: была модернизация/upgraded | E83: Rus | F83: Zhuravlyov Alexey | G83: Инженер по деталям интерьера и экстерьера 2 категории | H83: Q&T, QT | I83: Laptop, mouse,bag | J83: Laptop Lenovo V110 | K83: 00000011073 | L83: инвентарник MOC наклеен | M83: Внесен в ITSM AST0002165 | N83: 1-09 третий этаж | O83: R90QN4XJ | P83: ="RUTL-" & RIGHT(O83,8) -> RUTL-R90QN4XJ | Q83: Внесены в Passwork | R83: Microsoft Office профессиональный плюс 2016 | T83: Windows 10 Pro | U83: 24JJN-7CJDD-7JKBC-HVGM2-76DGP | V83: ULTRAVNC / MESH | W83: No Administrator rights | Y83: - | Z83: 43368 | AA83: БЕЗ НДС 33806,78, С НДС 39892
A84: =A83+1 -> #REF! | B84: 882 | C84: Тимошин Дмитрий Иванович | D84: Модернизация не требуется/normal (no need to upgrade) | E84: Rus | F84: Timoshin Dmitriy | G84: Инженер-системный программист | H84: RDC,INFR | I84: Laptop,mouse | J84: Dell Vostro 7500 | K84: 10000001759 | L84: Наклеить | N84: 1-07 второй этаж | O84: 7DS51B3 | P84: ="RUTL-" & RIGHT(O84,8) -> RUTL-7DS51B3 | Q84: Внесены в Passwork | Y84: -
A85: =A84+1 -> #REF! | B85: 885 | C85: Соловьёв Сергей Валерьевич | D85: Модернизация не требуется/normal (no need to upgrade) | E85: Rus | F85: Solovyov Sergey | G85: Руководитель группы водоснабжения, водоотведения и очистки стоков | H85: M&U, UTL | I85: Laptop,mouse | J85: Acer Aspire Lite 15 AL15-41 | K85: поставить на учет | L85: Наклеить | N85: 1-13 крыло ютилити 2 эт | O85: UN31ZSI04F533021D80700 | P85: ="RUTL-" & RIGHT(O85,8) -> RUTL-21D80700 | Q85: Внесены в Passwork | R85: LibreOffice | T85: Windows 11 Pro | V85: ULTRAVNC / MESH | W85: No Administrator rights | X85: Кудрявцев Д. | Y85: Акт 18.11.2025 | Z85: 45975 | AA85: БЕЗ НДС 36790 с НДС -
A86: =A85+1 -> #REF! | B86: 897 | C86: Карпунин Александр Анатольевич | D86: Модернизация не требуется/normal (no need to upgrade) | E86: Rus | F86: Karpunin Aleksandr | G86: Начальник смены по качеству | H86: MD, AS | I86: Laptop,mouse | J86: Laptop IRBIS 15NBP3506 | K86: 100000003646 | L86: Наклеить | O86: F2715NBP35060821580 | P86: ="RUTL-" & RIGHT(O86,8) -> RUTL-60821580 | Q86: Внесены в Passwork | R86: LibreOffice | V86: ULTRAVNC | Y86: Акт 16.11.2024
A87: =A86+1 -> #REF! | B87: 902 | C87: Люкин Денис Анатольевич | D87: Модернизация не требуется/normal (no need to upgrade) | E87: Rus | F87: Zakharova Yulia | G87: Специалист по планированию производства | H87: MD, PM | I87: Laptop, mouse, переходник | J87: Laptop IRBIS 15NBP3508 | K87: 100000003374 | L87: Наклеить | N87: 1-09 второй этаж | O87: F2715NBP35080821350 | P87: ="RUTL-" & RIGHT(O87,8) -> RUTL-80821350 | Q87: Внесены в TeamPass | R87: Libre office | V87: ULTRAVNC / MESH | W87: No Administrator rights | X87: Климанов А. | Y87: Акт 27.02.2026
A88: =A87+1 -> #REF! | B88: 906 | C88: Дешина Екатерина Владимировна | D88: Модернизация не требуется/normal (no need to upgrade) | E88: Rus | F88: Deshina Ekaterina | G88: Казначей | H88: FD, FUND | I88: AiO, mouse, keyboard | J88: AiO Dell Inspiron 5400 | K88: 100000001675 | L88: Наклеить | N88: 1-07 третий этаж FD | O88: 8M4HDF2 | P88: ="RUTL-" & RIGHT(O88,8) -> RUTL-8M4HDF2 | Q88: Внесены в Passwork | R88: 2016 for home and business (BOX) | T88: Windows 10 Pro | U88: DYBM3-74NM3-FH3BG-PPVWK-9HJV2 | V88: ULTRAVNC | Y88: Акт 09.01.2022 | Z88: 44551 | AA88: без НДС 71 583,33 с НДС 85 900
A89: =A88+1 -> #REF! | B89: 909 | C89: Яничкина Татьяна Анатольевна | D89: Модернизация не требуется/normal (no need to upgrade) | E89: Rus | F89: Yanichkina Tatyana | G89: Руководитель группы | H89: OMD, DM | I89: Laptop, mouse,+ lan USB | J89: Laptop Dell Inspiron 15 3511 | K89: 100000001665 | L89: Наклеить | N89: 1-06 первый этаж | O89: CG50JK3 | P89: ="RUTL-" & RIGHT(O89,8) -> RUTL-CG50JK3 | Q89: Внесены в Passwork | R89: Libre office | S89: - | T89: Windows 10 Pro | V89: ULTRAVNC / MESH | W89: No Administrator rights | X89: Кудрявцев Д. | Y89: Акт от 25.03.2026 | Z89: 44551 | AA89: БЕЗ НДС 81250,00 с НДС 97500
A90: =A89+1 -> #REF! | B90: 936 | C90: Коробський Александр Александрович | D90: Модернизация не требуется/normal (no need to upgrade) | E90: Rus | F90: Korobskiy Alexander | G90: Руководитель группы по работе с рекламациями | H90: PMD, ORD | I90: Laptop, mouse,bag | J90: Laptop Lenovo V110 | K90: 00000011061 | L90: инвентарник MOC наклеен | M90: Внесен в ITSM AST0002151 | N90: 1-09 второй этаж | O90: R90QN4VU | P90: ="RUTL-" & RIGHT(O90,8) -> RUTL-R90QN4VU | Q90: Внесены в Passwork | R90: 2016 for home and business (BOX) | T90: Windows 10 Pro | V90: ULTRAVNC / MESH | W90: No Administrator rights | Y90: Акт 03.12.2020 | Z90: 43368 | AA90: БЕЗ НДС 33806,78, С НДС 39892
A91: =1+'ПК с 2 и более владельцами'!A91 -> #REF! | B91: 940 | C91: Грошев Андрей Витальевич | D91: Модернизация не требуется/normal (no need to upgrade) | E91: Rus | F91: Groshev Andrey | G91: Инженер по качеству | H91: CH Q&T, CH QA | I91: Laptop, mouse, bag | J91: Lenovo ThinkBook 16 G7 ARP 3 | K91: поставить на учет | L91: Наклеить | N91: 1-09 третий этаж (цех chassiс) | O91: PW0LW3NT | P91: ="RUTL-" & RIGHT(O91,8) -> RUTL-PW0LW3NT | Q91: Внесены в Passwork | R91: Libre Office / Only office | T91: Windows 11 Pro | U91: YD8K3-NQJQY-4TFYR-CKM7P-Q3XCT | V91: ULTRAVNC / MESH | W91: No Administrator rights | X91: Кудрявцев Д. | Y91: Акт 31.03.2026 | AA91: С НДС 64660 БЕЗ НДС 53000
A92: =#REF!+1 -> #REF! | B92: 950 | C92: Лупанов Илья Николаевич | D92: Модернизация не требуется/normal (no need to upgrade) | E92: Rus | F92: Lupanov Ilya | G92: Заместитель начальника цеха | H92: MD, STAMP | I92: Laptop, mouse,bag | J92: Laptop MSI Modern 15 F1MG-800XRU | K92: поставить на учет | L92: наклеить | N92: 1-02 офис цеха сварки 2 эт | O92: C2507N0002566 | P92: ="RUTL-" & RIGHT(O92,8) -> RUTL-N0002566 | Q92: Внесены в Passwork | R92: Libre office | T92: Windows 11 Pro | U92: JY9Y3-TNFWH-BCFHH-MP4V4-WFHCP | V92: ULTRAVNC / MESH | W92: No Administrator rights | X92: Летунов А. | Y92: Акт 20,02,2026 | Z92: 45989 | AA92: Стоимость ПК без НДС 59 160руб
A93: =A92+1 -> #REF! | B93: 951 | C93: Байко Наталия Игоревна | D93: Модернизация не требуется/normal (no need to upgrade) | E93: Rus | F93: Bayko Natalia | G93: Заместитель руководителя отдела | H93: CH, QI | I93: Laptop,mouse | J93: Laptop Acer Extensa 15 | K93: 100000003334 | L93: наклеить | N93: 1-09 третий этаж (цех chassiс) | O93: NXEGYER00H32008F053400 | P93: ="RUTL-" & RIGHT(O93,8) -> RUTL-8F053400 | Q93: Внесены в Passwork | R93: 2016 for home and business (BOX) | T93: Windows 10 Pro | U93: Q6J3H-TCQKQ-J3DYY-X9M4P-JB6PT | V93: ULTRAVNC / MESH | W93: No Administrator rights | X93: Кудрявцев Д. | Y93: Акт от 17.07.2024 | Z93: 2024 | AA93: БЕЗ НДС 60440.50
A94: =A93+1 -> #REF! | B94: 955 | C94: Семенихина Наталия Валерьевна | D94: Модернизация не требуется/normal (no need to upgrade) | E94: Rus | F94: Semenikhina Natalya | G94: Ведущий бухгалтер 1 категории | H94: FD, ACC | I94: Laptop, mouse, Monitor Xiaomi a24i SN: 54383/250100058946 | J94: Laptop MSI Modern 15 F1MG-800XRU | K94: поставить на учет | L94: Наклеить | N94: 1-07 третий этаж FD | O94: C2507N0002964 | P94: ="RUTL-" & RIGHT(O94,8) -> RUTL-N0002964 | Q94: Внесены в Passwork | R94: 2019 for home and business | T94: Windows 11 Pro | U94: 3GH8P-NQBQ6-HJVKH-7CJYT-PDK2P | V94: ULTRAVNC / MESH | W94: No Administrator rights | X94: Летунов А. | Y94: Акт 02.01.2026 | Z94: 45989 | AA94: Стоимость ПК без НДС 59 160руб
A95: =A94+1 -> #REF! | B95: 960 | C95: Острась Николай Владимирович | D95: Модернизация не требуется/normal (no need to upgrade) | E95: Rus | F95: Ostras Nikolay | G95: Диспетчер производства | H95: NOBO | I95: Laptop, mouse | J95: Laptop IRBIS 15NBP3506 | K95: 100000003614 | L95: Наклеить | N95: 1-04 офис дет. Интерьера | O95: F2715NBP35060821577 | P95: ="RUTL-" & RIGHT(O95,8) -> RUTL-60821577 | Q95: Внесены в Passwork | T95: Windows 10 Pro | V95: ULTRAVNC / MESH | W95: No Administrator rights | X95: Кудрявцев Д. | Y95: Акт 16.08.2026
A96: =A95+1 -> #REF! | B96: 991 | C96: Владимирова Кристина Александровна | D96: Модернизация не требуется/normal (no need to upgrade) | E96: Rus | F96: Vladimirova Kristina | G96: Руководитель группы | H96: M&U, PLE | I96: Laptop, mouse | J96: Acer Aspire Lite 15 AL15-41 | K96: поставить на учет | L96: Наклеить | N96: 1-09 второй этаж | O96: UN31ZSI04F533022030700 | P96: ="RUTL-" & RIGHT(O96,8) -> RUTL-22030700 | Q96: Внесены в Passwork | R96: LibreOffice | T96: Windows 11 Pro | U96: NF2QH-Q26XC-7MFCP-9RRGT-3V7J6 | V96: ULTRAVNC / MESH | W96: No Administrator rights | X96: Кудрявцев Д. | Y96: Акт 19.11.2025 | Z96: 45975 | AA96: БЕЗ НДС 36790 с НДС -
A97: =A96+1 -> #REF! | B97: 992 | C97: Михеев Илья Валентинович | D97: Модернизация не требуется/normal (no need to upgrade) | E97: Rus | F97: Mikheev Ilya | G97: Ведущий специалист по массовому подбору персонала | H97: HRD, REC, BC REC | I97: Laptop, mouse | J97: Laptop IRBIS 15NBP3508 | K97: 100000003383 | L97: Наклеить | N97: 1-07 третий этаж | O97: F2715NBP35080821821 | P97: ="RUTL-" & RIGHT(O97,8) -> RUTL-80821821 | Q97: Внесены в Passwork | R97: Microsoft Office профессиональный плюс 2019 | S97: Кто делал лицензию? добавьте ключ! | T97: Windows 10 Pro | U97: Installed Key: VK7JG-NPHTM-C97JM-9MPGT-3V66T OEM Key: CBYTG-6FNDK-4R9B7-D7C8F-HQWXC | V97: ULTRAVNC / MESH | W97: No Administrator rights | X97: Кудрявцев Д. | Y97: Акт 28.019.2026
A98: =A97+1 -> #REF! | B98: 994 | C98: Воронина Олеся Владимировна | D98: Модернизация не требуется/normal (no need to upgrade) | E98: Rus | F98: Voronina Olesya | G98: Ведущий специалист по персоналу | H98: HRD, DP, HR DATA | I98: AiO, mouse, keyboard | J98: IRBIS SMART AIO MB2389 | K98: поставить на учет | L98: наклеить | N98: 1-07 третий этаж | O98: 2408A22H124i5M2165R00474 | P98: ="RUTL-" & RIGHT(O98,8) -> RUTL-65R00474 | Q98: Внесены в Passwork | R98: Microsoft Office профессиональный плюс 2016 | T98: Windows 10 Pro | U98: 7NRB2-P743P-RC96Y-RRMCK-MG9TP | V98: ULTRAVNC / MESH | W98: No Administrator rights | X98: Мартынов Д. | Y98: Акт 21.05.2025
A99: =A98+1 -> #REF! | B99: 998 | C99: Потапов Дмитрий Николаевич | D99: была модернизация/upgraded (SSD) | E99: Rus | F99: Potapov Dmitriy | G99: Начальник смены | H99: MD, STAMP | I99: Laptop,mouse | J99: Laptop Lenovo V510 Установлен SSD kingston 240gb Взамен старому HDD, добавлена плашка ОЗУ на 8gb. | K99: 15289 | L99: инвентарник MOC наклеен | O99: LR0AVC2C | P99: ="RUTL-" & RIGHT(O99,8) -> RUTL-LR0AVC2C | Q99: Внесены в Passwork | R99: Libre office | U99: CBX6N-DD222-CRBJC-RPCX7-XD722 | V99: ULTRAVNC / MESH | W99: No Administrator rights | X99: Летунов А. | Y99: Акт 12.10.2024
A100: =A99+1 -> #REF! | B100: 1017 | C100: Шустова Ксения Игоревна | D100: Модернизация не требуется/normal (no need to upgrade) | E100: Rus | F100: Shustova Kseniya | G100: Экономист | H100: MD, STAMP | I100: AiO, mouse, keyboard | J100: AiO Lenovo V30A | K100: 10000001768 | L100: Наклеить | O100: MP1TK2Z3 | P100: ="RUTL-" & RIGHT(O100,8) -> RUTL-MP1TK2Z3 | Q100: Внесены в Passwork | R100: Libre office | V100: ULTRAVNC / MESH | X100: Климанов А. | Y100: Акт 12.05.2025
...

Sheet ПК с 2 и более владельцами
A1: № | B1: Табельный номер / Employee ID | C1: Физлицо / Owner | D1: История модернизаций, ремонтов / Modernisation, repairing history | E1: Тип домена / Domain Type | F1: Имя на английском / English name | G1: Должность / Position (Rus / Eng) | H1: Отдел / Department | I1: Комплектация / Equipment | J1: Тип и модель ПК / PC type and model | K1: Инвентарный номер / Inventory number | L1: Инвентарный номер наклеен? / Is the inventory number affixed? | M1: где хранится информация о компе | N1: Местоположение / Location | O1: Серийный номер / Serial Number | P1: Имя компьютера / PC Domain Name | Q1: TeamPass, Passwork? | R1: Тип ПО офис / Office type | S1: Ключ офиса / License key Office | T1: ОС тип / OS Type | U1: Ключ ОС / Key OS | V1: ПО удалённого управления / Remote control | W1: Админ права / Admin permissions | X1: Кто подготовил / Who installed | Y1: Дата выдачи / Issue Date | Z1: Дата покупки / Purchasing Date | AA1: Примечание / Comment
A2: 1 | B2: 6859 7841 13454 | C2: Стадольская Оксана Николаевна Долгов Ярослав Андреевич Клементьев Виталий Владимирович | D2: Модернизация не требуется/normal (no need to upgrade) | E2: Rus | F2: Stadolskaya Oksana Dolgov Yaroslav | G2: начальник участка цеха движков / Мастер 2 категории | H2: ES, ES MD, ES AS | I2: AiO, mouse, keyboard | J2: AiO Lenovo M810Z | K2: 140000062/Z000101 | L2: наклеить | N2: engine shop | O2: PC0MYXTZ | P2: ="RUTL-" & RIGHT(O2,8) -> RUTL-PC0MYXTZ | Q2: Внесены в Passwork | T2: Windows 10 Pro - 22H2/19045 | V2: ULTRAVNC / MESH | W2: No administrator rights | X2: Кудрявцев Д. / Мартынов Д. | Y2: акт 07.11.2023 / 03.09.2025 / 05.12.2025
A3: =1+A2 -> 2 | B3: 6218 10700 | C3: Дуплина Татьяна Александровна Филиппова Татьяна Денисовна | D3: Модернизация не требуется/normal (no need to upgrade) | E3: Rus | F3: Duplina Tatyana Filippova Tatyana | G3: Мастер 2 категории Оператор (промоушен на специалиста TPS) | H3: ES, ES MD, ES AS | I3: AiO, mouse, keyboard | J3: AiO Lenovo M810Z | K3: 140000172/Z000052 | L3: наклеить | N3: engine shop | O3: S4FM3331 | P3: ="RUTL-" & RIGHT(O3,8) -> RUTL-S4FM3331 | Q3: Внесены в Passwork | R3: MS Office | T3: Windows 10 Pro - 22H2/19045 | U3: R38X3-J4NJR-CRXGD-KB992-J44C2 | V3: ULTRAVNC / MESH | W3: No administrator rights | X3: Кудрявцев Д. | Y3: Акт 11.11.2025 / 19.11.2025
A4: =1+A3 -> 3 | B4: 11810 10816 | C4: Степанов Никита Алексеевич Калинин Юрий Юрьевич | D4: Модернизация не требуется/normal (no need to upgrade) | E4: Rus | F4: Stepanov Nikita Kalinin Yuri | G4: Кладовщик | H4: ES, ES PM&LS | I4: Laptop, mouse | J4: Laptop Lenovo V510 | K4: 00000011580 | L4: инвентарник MOC наклеен | N4: engine shop | O4: LR08MD5C | P4: ="RUTL-" & RIGHT(O4,8) -> RUTL-LR08MD5C | Q4: Внесены в Passwork | R4: Libre office | T4: Windows 10 Pro - 22H2/19045 | U4: GTGNK-4Y23G-TMH7C-77W3P-FX8XC | V4: ULTRAVNC / MESH | W4: No Administrator rights | X4: Кудрявцев Д. | Y4: Акт 04.06.2025 /Акт 18.06.2025
A5: =1+A4 -> 4 | B5: 7755 13475 | C5: Кадников Сергей Петрович Генг Вадим Алексеевич | D5: Модернизация не требуется/normal (no need to upgrade) | E5: Rus | F5: Kadnikov Sergey/ Geng Vadim | G5: Контролер качества/ Мастер 1 категории | H5: ES, ES Q&T, ES QTM | I5: Laptop, mouse | J5: Acer Aspire 5 A515-57-5703 | K5: поставить на учет | L5: наклеить | N5: engine shop | O5: NXKN3CD00J435010543400 | P5: ="RUTL-" & RIGHT(O5,8) -> RUTL-10543400 | Q5: Внесены в Passwork | R5: Libre office | T5: Windows 11 | U5: WBXMG-NCFQT-PB7W8-XRCXW-XW3GP | V5: ULTRAVNC / MESH | W5: No Administrator rights | X5: Мартынов Д./ Климанов А | Y5: Акт 13.08.2025/ 03.12.2025 | Z5: 45880 | AA5: БЕЗ НДС 45080, С НДС 54096
A6: =1+A5 -> 5 | B6: 12183 12098 12675 13030 13055 12905 | C6: Вышегородский Алексей Леонидович Корниенко Александр Игоревич Смирнов Дмитрий Александрович Прокопенко Сергей Юрьевич Шуев Иван Викторович | D6: была модернизация 17.04.2025/upgraded (ssd512 +8ram total 16ram | E6: Rus | F6: Vyshegorodsky Alexey Korniyenko Aleksandr Smirnov Dmitry Prokopenko Sergey Shuyev Ivan | G6: Инженер по измерениям / Инженер-технолог / Инженер-технолог / Инженер по измерениям / Инженер по измерениям | H6: ES, ES Q&T, ES QTM | I6: WorkStation,monitor(S24e-1),mouse,keyboard | J6: Компьтер Lenovo Thinkstation P520 Intel Xeon W-2104 | K6: 140000190 | L6: инвентарник ОС наклеен | N6: engine shop | O6: S4HN3450 | P6: ="RUTL-" & RIGHT(O6,8) -> RUTL-S4HN3450 | Q6: Внесены в Passwork | R6: Libre office | T6: Windows 10 Pro - 22H2/19045 | V6: ULTRAVNC / MESH | W6: No administrator rights | X6: Кудрявцев Д./ Климанов А. | Y6: Акт 12.05.2025. / 09.06.2025 / 16.09.2025/ 17.10.2025 / 06.11.2025
A7: =1+A6 -> 6 | B7: 3879 6012 6020 6076 | C7: Лялина Лилия Раисовна Балашова Ирина Анатольевна Белова Елена Бригадиренко Наталья | D7: Модернизация не требуется/normal (no need to upgrade) | E7: Rus | F7: Lyalina Lilia Balashova Irina Belova Elena Brigadirenko Natalia | G7: Диспетчеры контейнерного терминала | H7: ILD | I7: AiO, mouse, keyboard | J7: AiO Lenovo M800Z | K7: 150000023/Z000116 | L7: Наклеить | N7: 1-06 первый этаж | O7: PC0KL0L0 | P7: ="RUTL-" & RIGHT(O7,8) -> RUTL-PC0KL0L0 | Q7: Внесены в Passwork | V7: ULTRAVNC / MESH | W7: no need | X7: Кудрявцев Д. | Y7: акт 26-07-2023/акт 21-07-2023/акт 18-07-2023 Новый акт на Моторкина Д. 07.02.2025
A8: =1+A7 -> 7 | B8: 6585 6758 10645 5372 6768 6630 2659 6910 | C8: Поддубная Анна Викторовна Рыбина Наталья Владимировна Гаврильская Анастасия Алексеевна Вафина Ирина Владимировна Сушкова Ольга Владимировна Лаврищева Валерия Евгеньевна Меркулова Анастасия Александровна Сизова Ольга Валерьевна | D8: Модернизация не требуется/normal (no need to upgrade) | E8: Rus | F8: Poddubnaya Anna Viktorovna Rybina Natalya Vladimirovna Gavrilskaya Anastasia Alekseevna Vafina Irina Vladimirovna Sushkova Olga Vladimirovna Lavrishcheva Valeria Evgenievna Merkulova Anastasia Alexandrovna Sizova Olga Valerievna | G8: Специалист по складскому учету и документообороту/Warehouse and Document management specialist | H8: ILD, FPW | I8: AiO, mouse, keyboard | J8: AiO HP 200 G3 | K8: 00000021020(2) | L8: инвентарник MOC наклеен | N8: 20 сгп | O8: 8CC9164N84 | P8: ="RUTL-" & RIGHT(O8,8) -> RUTL-C9164N84 | Q8: Внесены в Passwork | R8: Microsoft Office 2007 Service Pack 3 (SP3) | T8: Windows 10 Pro - 22H2/19045 x64 | V8: ULTRAVNC | W8: ADMIN | X8: Кудрявцев Д. / Мартынов Д. | Y8: акт 15-01-2024 / / акт 29-11-2024
A9: =1+A8 -> 8 | B9: 7035 4825 10645 | C9: Жучкова Екатерина Геннадьевна Гаврильская Анастасия Медведева Татьяна | D9: модернизация прошла оперативная память добавить 8 гб | E9: Rus | F9: Zhuchkova Ekaterina / Gavrilskaya Anastasia | G9: Специалист по складскому учету и документообороту/Warehouse and Document management specialist | H9: ILD, FPW | I9: AiO, mouse, keyboard | J9: AIO HP 200 G3 | K9: 00000021020(1) | L9: инвентарник MOC наклеен | N9: 1-07_2 этаж | O9: 8CC9164N8V | P9: ="RUTL-" & RIGHT(O9,8) -> RUTL-C9164N8V | Q9: Внесены в Passwork | V9: ULTRAVNC / MESH | X9: Иванов К /Летунов А | Y9: акт 24-01-2024/21-10-2024
A10: =1+A9 -> 9 | B10: 6630 5372 2659 10645 6910 6585 6768 6758 | C10: Лаврищева Валерия Евгеньевна Вафина Ирина Владимировна Меркулова Анастасия Александровна Гаврильская Анастасия Алексеевна Сизова Ольга Валерьевна Поддубная Анна Викторовна Сушкова Ольга Владимировна Рыбина Наталья Владимировна | D10: Модернизация не требуется/normal (no need to upgrade) | E10: Rus | F10: Lavrishcheva Valeria Evgenievna Vafina Irina Vladimirovna Merkulova Anastasia Alexandrovna Gavrilskaya Anastasia Alekseevna Sizova Olga Valerievna Poddubnaya Anna Viktorovna Sushkova Olga Vladimirovna Rybina Natalya Vladimirovna | G10: Специалист по складскому учету и документообороту | H10: ILD, FPW | I10: WorkStation,monitor(S24e-1),mouse,keyboard | J10: Workstation Lenovo V530s+ отдельно монитор S24E | K10: поставить на учет | N10: 1-20 сгп новая будка | O10: YL002US0 | P10: ="RUTL-" & RIGHT(O10,8) -> RUTL-YL002US0 | Q10: Внесены в Passwork | R10: Libre office | T10: Windows 10 Pro - 22H2/19045 x64 | V10: ULTRAVNC / MESH | W10: No Administrator rights | X10: Климанов А. | Y10: Акт 19.01.2024 Акт 15.10.2025
A11: =1+A10 -> 10 | B11: 04811 2807 | C11: Белехов Николай Олегович Сьянов Антон Генадьевич | D11: была модернизация/upgraded (SSD 256) | E11: Rus | F11: Belekhov Nikolay / Syanov Anton | G11: Инженер по производственному оборудованию | H11: M&U MTC ASPC | I11: Laptop, mouse,bag | J11: Laptop Lenovo V 130 | K11: 00000019366(3) | L11: инвентарник MOC наклеен | O11: R90T947L | P11: ="RUTL-" & RIGHT(O11,8) -> RUTL-R90T947L | Q11: Внесены в Passwork | R11: Libre office | T11: Windows 10 Pro - 22H2/19045 | V11: ULTRAVNC \ MESH | W11: no need | X11: Летунов А. | Y11: акт 24-01-2025 | Z11: 43661
A12: =1+A11 -> 11 | B12: 7666 2914 2898 | C12: Савин Дмитрий Павел Стартцев Александр Агапов | D12: Модернизация не требуется/normal (no need to upgrade) | E12: Rus | F12: Pavel Startsev / Dmitry Savin / Alexander Agapov | G12: Наладчик технологического оборудования 5 категории | H12: M&U MTC ASPC | I12: Laptop, mouse,bag | J12: Laptop Lenovo T480 | K12: 140000201 | L12: инвентарник ОС наклеен | N12: 1-03 офис MU цеха окраски | O12: PF15ZDH0 | P12: ="RUTL-" & RIGHT(O12,8) -> RUTL-PF15ZDH0 | Q12: Внесены в Passwork | V12: ULTRAVNC / MESH | W12: Admin / no need | X12: Летунов А. | Y12: акт 14-03-2024
A13: =1+A12 -> 12 | B13: 9899 11269 | C13: Филатов Вячеслав Алексеевич Ким Валентин Викторович | D13: Модернизация не требуется/normal (no need to upgrade) | E13: Rus | F13: Filatov Vyacheslav / Kim Valentin | G13: Инженер по производственному оборудованию / Production Equipment Engineer | H13: M&U MTC ASPC | I13: WorkStation+monitor lenovo T24I | J13: Workstation Lenovo ThinkStation P 520 | K13: 140000188 | L13: инвентарник ОС наклеен | N13: 1-04 офис MU цеха сборки | O13: S4HN3478 | P13: ="RUTL-" & RIGHT(O13,8) -> RUTL-S4HN3478 | Q13: Внесены в Passwork | R13: 2016 for home and business (BOX) | T13: Windows 10 Pro - 22H2/19045 x64 | V13: ULTRAVNC / MESH | W13: Admin / no need | X13: Кудрявцев Д. | Y13: Акт 07.11.2024 / Акт 30.01.2025
A14: =1+A13 -> 13 | B14: 9735 738 | C14: Волкова София Александровна Ельцов Андрей | D14: Модернизация не требуется/normal (no need to upgrade) | E14: Rus | F14: Volkova Sofia | G14: Диспетчер | H14: M&U UTL | I14: AiO, mouse, keyboard | J14: AiO Lenovo M800Z | K14: 150000026/Z000001 | L14: наклеить | N14: 1-07 3 этаж | O14: PC0KDWEW | P14: ="RUTL-" & RIGHT(O14,8) -> RUTL-PC0KDWEW | Q14: Внесены в Passwork | R14: Libre office | T14: Windows 10 Pro - 22H2/19045 | V14: ULTRAVNC / MESH | W14: No Administrator rights | X14: Летунов А. / Мартынов Д. | Y14: Акт 07,12,2024
A15: =1+A14 -> 14 | B15: ??? проверить на активные уч записи | C15: Екатерина Чуванкова Казакова Анна Хусейнова Карина Анваровна | D15: требуется замена жесткого диска/need to modernisation(replacement to hard disk) | E15: Rus | F15: Chuvankova Ekaterina /Khuseynova Karina | G15: Наладчик технологического оборудования 2 категории/ Наладчик технологического 1 категории | H15: M&U, ESCP | I15: AiO, mouse, keyboard | J15: AiO Lenovo M810Z | K15: 140000168/Z000085 | L15: Наклеить | N15: У MU в цехе окраски склад МЮ 1 эт | O15: S4FM3439 | P15: ="RUTL-" & RIGHT(O15,8) -> RUTL-S4FM3439 | Q15: Внесены в Passwork | R15: 2016 for home and business (BOX) | V15: ULTRAVNC / MESH | W15: no need | X15: Климанов А./ Мартынов Д. / Летунов А. | Y15: акт 07-11-2024 / 12,12,2024/24.11..2025
A16: =1+A15 -> 15 | B16: 9454 / 5150 | C16: Пацук Евгений Викторович Денисов Олег Вячеславович | D16: Модернизация не требуется/normal (no need to upgrade) | E16: Rus | F16: Patsuk Evgeniy / Denisov Oleg | G16: Мастер-механик по ремонту специальной дорожной техники | H16: M&U, FAC | I16: Laptop, mouse | J16: Laptop Lenovo Thinkpad L580 | K16: 14000157/Z000047 | L16: Наклеить | N16: 1-13 | O16: PF12TW42 | P16: ="RUTL-" & RIGHT(O16,8) -> RUTL-PF12TW42 | Q16: Внесены в Passwork | R16: Libre office | T16: Windows 10 Pro - 22H2/19045 x64 | U16: KTNFX-XDQTR-DWXF4-CQYJQ-9766P | V16: ULTRAVNC / MESH | W16: No Administrator rights | X16: Мартынов Д. | Y16: Акт 26.11.2025 | Z16: 43236 | AA16: БЕЗ НДС 41754,78, С НДС 50920,47
A17: =1+A16 -> 16 | B17: 11353/ 2494 | C17: Сайков Максим Владимирович/ Макаров Александр Владимирович | D17: Модернизация не требуется/normal (no need to upgrade) | E17: Rus | F17: Saykov Maxim/ Makarov alexander | G17: Начальник смены технического обслуживания оборудования 1 категории | H17: M&U, MTC ES | I17: Laptop, mouse | J17: Laptop IRBIS 15NBP3507 | K17: поставить на учет | L17: Наклеить | N17: engine shop | O17: F2715NBP35070821672 | P17: ="RUTL-" & RIGHT(O17,8) -> RUTL-70821672 | Q17: Внесены в Passwork | R17: Libre office | T17: Windows 11 | V17: ULTRAVNC / MESH | W17: No Administrator rights | X17: Мартынов Д./ Климанов А | Y17: Акт 28.03.2025/ 03.12.2025
A18: =1+A17 -> 17 | B18: 11172 / 13527 | C18: Маркаров Григорий Аванесович Стуканов Дмитрий Олегович | D18: Модернизация не требуется/normal (no need to upgrade) | E18: Rus | F18: Markarov Grigory | G18: Инженер по производственному оборудованию | H18: M&U, MTC ES | I18: Laptop,mouse+Lan-USB | J18: Laptop Lenovo V15 G1+Lan-USB | K18: 100000001646 | L18: Наклеить | O18: PF2VSVTT | P18: ="RUTL-" & RIGHT(O18,8) -> RUTL-PF2VSVTT | Q18: Внесены в Passwork | R18: Libre office | T18: MS Windows 10 Prof | V18: ULTRAVNC / MESH | X18: Климанов А. | Y18: Акт 03.02.2025
A19: =1+A18 -> 18 | B19: 13532 / 14580 | C19: Баранников Михаил Юрьевич / Уткин Александр | D19: Модернизация не требуется/normal (no need to upgrade) | E19: Rus | F19: Barannikov Mikhail / Utkin Alexander | G19: Инженер-механик 1 категории | H19: M&U, MTC ES | I19: Laptop, mouse | J19: Laptop IRBIS 15NBP3506 | K19: 100000003606 | L19: наклеить | O19: F2715NBP35060821908 | P19: ="RUTL-" & RIGHT(O19,8) -> RUTL-60821908 | Q19: Внесены в Passwork | R19: Libre office | T19: Windows 10 Pro - 22H2/19045 x63 | U19: P83YN-KPWY2-WJDW6-M8W9G-722KC | V19: ULTRAVNC \ MESH | W19: No Administrator rights | X19: Климанов А / Мартынов Д. | Y19: Акт 11.12.2025 / 14.02.2026
A20: =1+A19 -> 19 | B20: 6574 13330 | C20: Чутов Иван Андреевич Тиссен Елена Николаевна | D20: Модернизация не требуется/normal (no need to upgrade) | E20: Rus | F20: Chutov Ivan Tissen Elena | G20: Начальник участка обслуживания оборудования Наладчик технологического оборудования 1 категории | H20: M&U, MTC ES / M&U, ESCP | I20: Laptop, mouse | J20: Laptop Acer Extensa 15 | K20: 100000003346 | L20: наклеить | N20: 1-03 офис окраски 2эт | O20: NXEGYER00H320086173400 | P20: ="RUTL-" & RIGHT(O20,8) -> RUTL-86173400 | Q20: Внесены в Passwork | R20: Libre office | T20: Windows 10 Pro - 22H2/19045 x64 | U20: C99VN-XGR47-JGGHW-9M8DK-Y7WGG | V20: ULTRAVNC / MESH | W20: Admin | X20: Иванов К. Кудрявцев Д. | Y20: Акт 17.05.2024 20.11.2025 | Z20: 45385 | AA20: БЕЗ НДС 60440.50
A21: =1+A20 -> 20 | B21: 629 / 7606 | C21: Карпенко Григорий Александрович / Судоргин Андрей Николаевич | D21: была модернизация/upgraded (SSD)+ram | E21: Rus | F21: Karpenko Grigoriy / Sudorgin Andrey | G21: Начальник участка / Мастер 2 категории | H21: MD, AS | I21: Laptop, mouse | J21: Laptop Lenovo V110 | K21: 00000010779 | L21: инвентарник MOC наклеен | M21: Внесен в ITSM AST0001453 | N21: 1-07 четвертый этаж | O21: R90QFPZM | P21: ="RUTL-" & RIGHT(O21,8) -> RUTL-R90QFPZM | Q21: Внесены в Passwork | R21: 2019 for home and business | T21: Windows 10 Pro - 22H2/19045 | U21: QNYK7-PG6FK-BT8DX-7T62C-FX8XC | V21: ULTRAVNC / MESH | W21: No Administrator rights | X21: Кудрявцев Д. | Y21: Акт 28.03.2025 / 25.09.2025
A22: =1+A21 -> 21 | B22: 0000000758/0000002518 | C22: Бердник Евгений Игоревич/Грушихин Денис | D22: была модернизация/upgraded (SSD 256)/ Модернизация была добавлено 4 ГБ оперативной памяти | E22: Rus | F22: Berdnik Evgeniy/Gruishikhin | G22: Начальники участка Chassis1 | H22: MD, AS | I22: Laptop, mouse | J22: Laptop Lenovo V110 | K22: 00000010781 | L22: инвентарник MOC наклеен | M22: Внесен в ITSM AST0001575 | N22: 1-04 офис цеха сборки | O22: R90QFQ06 | P22: ="RUTL-" & RIGHT(O22,8) -> RUTL-R90QFQ06 | Q22: Внесены в Passwork | R22: Libre office | T22: Windows 10 Pro - 22H2/19045 | V22: ULTRAVNC / MESH | W22: No Administrator rights | X22: Мартынов Д. | Y22: Акт 17.12.2025 | Z22: 43325 | AA22: БЕЗ НДС 30247.46 С НДС 35692.00
A23: =#REF!+1 -> #REF! | B23: - | C23: Final 2 Попов Максим Олегович , Федосова/Чирков Роман Валерьевич 3968 | D23: Подвергся вандализму | E23: Rus | F23: Chirkov Roman/Fedosova | G23: Инженер по электрике автомобиля 3 категории/Мастер 2 категории | H23: MD, AS | I23: Laptop, mouse + Keyboard | J23: Laptop Lenovo V 130 | K23: 00000019366(18) | L23: инвентарник MOC наклеен | N23: 1-04 офис цеха сборки | O23: R90T9486 | P23: ="RUTL-" & RIGHT(O23,8) -> RUTL-R90T9486 | Q23: Внесены в Passwork | V23: ULTRAVNC / MESH | W23: No Administrator rights | X23: Мартынов Д./Климанов А. | Y23: Акт 17.12.2025/19.03.2026 | Z23: 43661
A24: =1+'ПК с 2 и более владельцами'!A23 -> #REF! | B24: 594 4030 2293 1138 5494 14180 | C24: Попов Максим Владимирович Болясов Михаил Владимирович Боенков Сергей Игоревич Леонова Ирина Сергеевна Крутая Анастасия Андреевна Ерещенко Елизавета Дмитриевна | D24: была модернизация/upgraded (SSD)+ram | E24: Rus | F24: Popov Maksim Bolyasov Mikhail Boyenkov Sergey Leonova Irina Krutaya Anastasiya | G24: Начальник участка Мастер по ремонту 1 категории Мастер по ремонту 1 категории Слесарь по ремонту автомобилей 2 категории Оператор | H24: MD, AS | I24: Laptop, mouse,bag | J24: Laptop Lenovo V510 | K24: 00000015285 | L24: инвентарник MOC наклеен | N24: 1-04 (Фин.инспекция) участок СГП | O24: LR0AVC21 | P24: ="RUTL-" & RIGHT(O24,8) -> RUTL-LR0AVC21 | Q24: Внесены в Passwork | R24: Libre office | T24: Windows 10 Pro - 22H2/19045 | V24: ULTRAVNC / MESH | W24: No administrator rights | X24: Кудрявцев Д. /Летунов А. / Кудрявцев Д. / Мартынов Д / Летунов А. | Y24: Акт от 15.11.2024 /акт 15.04.2025 / 25.09.2025 / 24.10.2025 / 18.02.2026 / 19.03.2026
A25: =1+A24 -> #REF! | C25: Бирькина Анна / Лесников Егор Юрьевич | D25: была модернизация/upgraded (SSD 256)/ Модернизация была добавлено 4 ГБ оперативной памяти | E25: Rus | F25: Birkina Anna/Lesnikov Egor | G25: Мастер 2 категории линия Trim1 | H25: MD, AS | I25: Laptop, mouse,bag | J25: Laptop Lenovo V510 | K25: 00000015284 | L25: инвентарник MOC наклеен | N25: 1-04 офис цеха сборки | O25: LR0AVC25 | P25: ="RUTL-" & RIGHT(O25,8) -> RUTL-LR0AVC25 | Q25: Внесены в Passwork | V25: ULTRAVNC / MESH | W25: No Administrator rights | X25: Мартынов Д. | Y25: Акт 17.12.2025
A26: =1+A25 -> #REF! | B26: 834/809/4622/605 | C26: Романов Дмитрий Сергеевич/ Буенок Сергей Николаевич/Стародубов Кирилл Сергеевич/Коробков Андрей Евгеньевич | D26: Модернизация не требуется/normal (no need to upgrade) | E26: Rus | F26: Romanov Dmitry/ Buenok Sergey/Starodubov Kirill/Korobkov Andrey | G26: Начальник участка, Мастер по ремонту 1 категории/ Мастер по ремонту 1 категории | H26: MD, AS | I26: Laptop, mouse,bag | J26: Laptop Acer Extensa 15 | K26: 100000003342 | L26: наклеить | N26: 1-04 офис цеха сборки | O26: NXEGYER00H320089B63400 | P26: ="RUTL-" & RIGHT(O26,8) -> RUTL-89B63400 | Q26: Внесены в Passwork | R26: Libre office | T26: Windows 10 Pro - 22H2/19045 | V26: ULTRAVNC / MESH | W26: No Administrator rights | X26: Мартынов Д./Климанов А. | Y26: Акт 07.05.2025/ 19.12.2025/ 16.02.2026 | Z26: 2024 | AA26: БЕЗ НДС 60440.50
A27: =1+A26 -> #REF! | B27: 7494 | C27: Петрищев Василий Викторович Жданов Александр Сергеевич ( не пришел за учеткой) | D27: Модернизация не требуется/normal (no need to upgrade) | E27: Rus | F27: Petrishchev Vasily / Zhdanov Alexander | G27: Инженер-технолог 1 категории / Мастер 1 категории | H27: MD, AS | I27: Laptop, mouse | J27: Laptop Acer Extensa 15 | K27: 100000003351 | L27: наклеить | O27: NXEGYER00H32008ABE3400 | P27: ="RUTL-" & RIGHT(O27,8) -> RUTL-8ABE3400 | Q27: Внесены в Passwork | V27: ULTRAVNC | X27: Летунов А. / Мартынов Д. | Y27: Акт 31.05.2024 / 09.07.2025 | Z27: 2024 | AA27: БЕЗ НДС 60440.50
A28: =1+A27 -> #REF! | B28: 1656 3162 | C28: Поляков Евгений Вадимович Дубровин Сергей Валерьевич | D28: Модернизация не требуется/normal (no need to upgrade) | E28: Rus | F28: Polyakov Evgeniy / Dubrovin Sergey | G28: Технолог 3 категории / Оператор | H28: MD, AS | I28: Laptop, mouse | J28: Acer Aspire Lite 15 AL15-41 | K28: поставить на учет | L28: Наклеить | N28: 1-04 офис цеха сборки | O28: UN31ZSI04F533024740700 | P28: ="RUTL-" & RIGHT(O28,8) -> RUTL-24740700 | Q28: Внесены в Passwork | T28: Windows 11 | V28: ULTRAVNC / MESH | W28: No Administrator rights | X28: Климанов А. | Y28: Акт 05.12.2025/05.12.2025 | Z28: 45975 | AA28: БЕЗ НДС 36790 с НДС -
A29: =1+A28 -> #REF! | B29: 340 1595 | C29: Рольгейзер Николай Николаевич Собаченков Михаил Геннадьевич | D29: Модернизация не требуется/normal (no need to upgrade) | E29: Rus | F29: Rolgeyzer Nikolay/Sobachenkov Mikhail | G29: Инженер-технолог 1 категории | H29: MD, AS | I29: Laptop, mouse | J29: Acer Aspire Lite 15 AL15-41 | K29: поставить на учет | L29: Наклеить | N29: 1-04 офис цеха сборки | O29: UN31ZSI04F533024CD0700 | P29: ="RUTL-" & RIGHT(O29,8) -> RUTL-24CD0700 | Q29: Внесены в Passwork | R29: Libre office | T29: Windows 11 Pro | U29: VK7JG-NPHTM-C97JM-9MPGT-3V66T | V29: ULTRAVNC / MESH | W29: No Administrator rights | X29: Кудрявцев Д./ Климанов А. | Y29: Акт 10.12.2025/11.12.2025 | Z29: 45975 | AA29: БЕЗ НДС 36790 с НДС -
A30: =1+A29 -> #REF! | B30: 1420 1355 6433 2236 7414 | C30: Трифонов Иван Михайлович Хуснутдинов Рустам Викторович Васюнин Денис Владимирович Хабибулин Дмитрий Тахирович Горин Иван Андреевич | D30: была модернизация/upgraded (SSD 256)/ Модернизация была добавлено 4 ГБ оперативной памяти | E30: Rus | F30: Trifonov Ivan Khusnutdinov Rustam Gorin Ivan | G30: Начальники участка Door Line Мастер 2 категории Мастер 2 категории | H30: MD, AS | I30: Laptop, mouse | J30: Laptop Lenovo V510 | K30: 00000016134 | L30: инвентарник MOC наклеен | N30: 1-04 офис цеха сборки | O30: LR0AVC2H | P30: ="RUTL-" & RIGHT(O30,8) -> RUTL-LR0AVC2H | Q30: Внесены в Passwork | R30: Libre office | T30: Windows 10 Pro - 22H2/19045 | V30: ULTRAVNC / MESH | W30: No Administrator rights | X30: Мартынов Д | Y30: Акт 17.12.2025 / 18.02.2026 / 24.02.2026
A31: =1+A30 -> #REF! | C31: Викторов Иван /Фирсов Валерий | D31: была модернизация/upgraded/была добавлено 8 ГБ оперативной памяти | E31: Rus | G31: Начальники участка Engine | H31: MD, AS | I31: Laptop, mouse | J31: Laptop Lenovo L340 | K31: 00000022303(7) | L31: инвентарник МОС наклеен | N31: 1-04 офис цеха сборки | O31: PF14SQHW | P31: ="RUTL-" & RIGHT(O31,8) -> RUTL-PF14SQHW | Q31: Внесены в Passwork | U31: По свински | Y31: Акт 10.02.2020
A32: =1+A31 -> #REF! | B32: 11821/ 10171 | C32: Шведов Даниил Игоревич Подгорнев Александр Владиславович | D32: Модернизация не требуется/normal (no need to upgrade) | E32: Rus | F32: Shvedov Daniil/ Podgornev Alexander | G32: Начальник участка / Мастер 2 категории | H32: MD, AS | I32: Laptop, mouse | J32: Laptop Dell Latitude 3450(C2) | K32: 140000012/Z000139 | L32: инвентарник ОС наклеен | M32: Внесен в ITSM AST0001705 | N32: 1-04 офис цеха сборки | O32: 2QNPG22 | P32: ="RUTL-" & RIGHT(O32,8) -> RUTL-2QNPG22 | Q32: Внесены в Passwork | R32: Libre office | T32: Windows 10 Pro - 22H2/19045 | U32: XNRBW-3Q2VH-VGFH2-TCBFV-G6MD2 | V32: ULTRAVNC / MESH | W32: No Administrator rights | X32: Кудрявцев Д./ Климанов А | Y32: Акт 13.03.2025/ 25.12.2025 | Z32: 42438
A33: =1+A32 -> #REF! | C33: Попов Павел 0000002187/ Петров 0000001837 | D33: Модернизация не требуется/normal (no need to upgrade) | E33: Rus | H33: MD, AS | I33: Laptop, mouse | J33: Laptop Lenovo ThinkPad EDGE E560(C2) | K33: 140000040/Z000019 | L33: Наклеить | N33: 1-04 офис цеха сборки | O33: PF0L9GF3 | P33: ="RUTL-" & RIGHT(O33,8) -> RUTL-PF0L9GF3 | Q33: Внесены в Passwork | R33: Libre office | T33: Windows 10 Pro - 22H2/19045 | U33: Installed Key: VK7JG-NPHTM-C97JM-9MPGT-3V66T OEM Key: B2WJH-PNYTH-RQHYP-22YK8-F3K2P | V33: ULTRAVNC / MESH | W33: No administrator rights | X33: Кудрявцев Д. | Y33: Акт от 03.04.2025
A34: =1+A33 -> #REF! | B34: 2024 6389 | C34: Муллоева Анастасия Алексеевна Бабкин Евгений Сергеевич | D34: Модернизация не требуется/normal (no need to upgrade) | E34: Rus | F34: Mulloeva Anastasia Babkin Evgeny | G34: Специалист TPS Инженер-технолог 1 категории | H34: MD, AS | I34: Laptop, mouse | J34: Laptop Acer Extensa 15 | K34: 100000003336 | L34: Наклеить | N34: 1-04 офис цеха сборки | O34: NXEGYER00H320089263400 | P34: ="RUTL-" & RIGHT(O34,8) -> RUTL-89263400 | Q34: Внесены в Passwork | T34: Windows 10 Pro - 22H2/19045 | U34: 2P9NF-YQJKV-CH6KD-HTXVC-J44C2 | V34: ULTRAVNC / MESH | W34: No Administrator rights | X34: Кудрявцев Д. | Y34: Акт 05.07.2024 Акт 30.01.2026 | Z34: 2024 | AA34: БЕЗ НДС 60440.50
A35: =1+A34 -> #REF! | C35: Прохоров Максим /Горлачев Антон | D35: была модернизация/upgraded (SSD 256) | E35: Rus | G35: Начальники участка Final 1 | H35: MD, AS | I35: Laptop, mouse,bag | J35: Laptop Lenovo V110 | K35: 00000011058 | L35: инвентарник MOC наклеен | N35: 1-07 третий этаж | O35: R90QN4VW | P35: ="RUTL-" & RIGHT(O35,8) -> RUTL-R90QN4VW | Q35: Внесены в Passwork | U35: 4XHTB-VNXWT-QCF3R-M4D89-DYH22 | V35: ULTRAVNC / MESH | W35: No Administrator rights | X35: Мартынов Д. | Y35: Акт 18.12.2025 | Z35: 43368 | AA35: БЕЗ НДС 33806,78, С НДС 39892
A36: =1+A35 -> #REF! | B36: 774/7997/7535/841 | C36: Сысоев Станислав Викторович/ Блок Александр Александрович/Баранюк Руслан Иванович/ Васильев Василий Сергеевич | D36: Модернизация не требуется/normal (no need to upgrade) | E36: Rus | F36: Sysoev Stanislav/ Blok Alexander/ Baranyuk Rusla/ Vasilyev Vasily | G36: Начальник участка/ мастер 1 категории/Мастер 1 категории/ Начальник участка | H36: MD, AS | I36: Laptop,mouse+Lan-USB | J36: Laptop Lenovo V15 G1+Lan-USB | K36: 100000001625 | L36: Наклеить | M36: Внесен в ITSM AST0000875 | N36: 1-04 линия двигателей | O36: PF2TM25W | P36: ="RUTL-" & RIGHT(O36,8) -> RUTL-PF2TM25W | Q36: Внесены в Passwork | V36: ULTRAVNC | X36: Климанов А. | Y36: Акт 19.07.2022/ 25.09.25/ 23.12.25/ 24.12.25
A37: =1+A36 -> #REF! | B37: 13491/14582 | C37: Шуршиков Роман Сергеевич/ Анашкина Алина Витальевна | D37: Модернизация не требуется/normal (no need to upgrade) | E37: Rus | F37: Shurshikov Roman/ Anashkina Alina | G37: Технолог 1 категории | H37: MD, AS | I37: Laptop, mouse | J37: Laptop IRBIS 15NBP3507 | K37: поставить на учет | L37: Наклеить | N37: 1-04 офис цеха сборки | O37: F2715NBP35070820586 | P37: ="RUTL-" & RIGHT(O37,8) -> RUTL-70820586 | Q37: Внесены в Passwork | R37: Libre office | T37: Windows 10 Pro - 22H2/19045 | V37: ULTRAVNC / MESH | W37: No Administrator rights | X37: Кудрявцев Д. | Y37: Акт 27.03.2025 Акт 25.09.2025 Акт 11.12.2025
A38: =1+'ПК с 1 владельцем'!A687 -> #REF! | B38: 11265 13513 | C38: Костикова Ирина Александровна Попова Анастасия Андреевна | D38: Модернизация не требуется/normal (no need to upgrade) | E38: Rus | F38: kostikova irina / Popova Anastasia | G38: Специалист по качеству Оператор | H38: MD, AS | I38: Laptop, mouse | J38: Laptop Lenovo L340 | K38: 10000001780 | L38: Наклеить | N38: 45748 | O38: PF1SL81M | P38: ="RUTL-" & RIGHT(O38,8) -> RUTL-PF1SL81M | Q38: Внесены в Passwork | R38: Libre office | T38: Windows 10 Pro - 22H2/19045 | V38: ULTRAVNC / MESH | X38: Климанов А. / Мартынов Д. | Y38: Акт 01.09.2025 / 27.02.2026
A39: =1+A38 -> #REF! | B39: 4407 / 14856 | C39: Рязанов Максим Александрович / Фатюшин Александр Владимирович | D39: Модернизация не требуется/normal (no need to upgrade) ОЗУ 12 SSD 256 | E39: Rus | F39: Ryazanov Maxim / Fatyushin Alexander | G39: Начальник участка | H39: MD, AS | I39: Laptop, mouse | J39: Laptop Lenovo V110 | K39: 00000011070 | L39: инвентарник MOC наклеен | M39: Внесен в ITSM AST0002160 | O39: R90QN4VJ | P39: ="RUTL-" & RIGHT(O39,8) -> RUTL-R90QN4VJ | Q39: Внесены в Passwork | T39: Windows 10 Pro | U39: HK7WV-VN4Q8-RH7GX-XDR27-GCQGP | V39: ULTRAVNC / MESH | W39: No Administrator rights | X39: Летунов А. / Мартынов Д. | Y39: Акт 10.03.2026 | Z39: 43368 | AA39: БЕЗ НДС 33806,78, С НДС 39892
A40: ='ПК с 1 владельцем'!A625+1 -> 13 | B40: - | C40: Векшина Анастасия Красюк Елена Викторовна 11248 | D40: Модернизация не требуется/normal (no need to upgrade) | E40: Rus | F40: Vekshina Anastasia/ Krasyuk Elena | G40: Диспетчер производства | H40: MD, AS | I40: AiO, mouse, keyboard | J40: AiO Lenovo S400Z | K40: 150000011/Z000010 | L40: Наклеить | N40: 1-04 офис цеха сборки | O40: P901FSLH | P40: ="RUTL-" & RIGHT(O40,8) -> RUTL-P901FSLH | Q40: Внесены в Passwork | R40: 2016 for home and business (BOX) | V40: ULTRAVNC / MESH | W40: no need | X40: Летунов А./Климанов А. | Y40: акт 15.11.2024/Акт от 13.03.2026
A41: =1+A40 -> 14 | B41: 2414 3636 1069 1202 121212 7569 | C41: Сурков Евгений Долгорученко Виталий Семёнов Павел Адамович Сергей Фролова Виктория Олеговна Рыжков Михаил Дмитриевич | D41: Модернизация не требуется/normal (no need to upgrade) | E41: Rus | F41: Surkov Evgeniy Semenov Pavel Adamovich Sergey Frolova Victoria Ryzhkov Mikhail | G41: Мастер/ Оператор | H41: MD, COMP | I41: Laptop | J41: Laptop Lenovo V110 | K41: 00000011076 | L41: инвентарник MOC наклеен | M41: Внесен в ITSM AST0002168 | N41: 1-04 офис компонентов | O41: R90QN4VM | P41: ="RUTL-" & RIGHT(O41,8) -> RUTL-R90QN4VM | Q41: Внесены в Passwork | R41: Libre office | T41: Windows 10 Pro - 22H2/19045 | V41: ULTRAVNC / MESH | W41: No Administrator rights | X41: Мартынов Д./ Климанов А. | Y41: Акт 14.05.2025/ 25.09.25 | Z41: 43368 | AA41: БЕЗ НДС 33806,78, С НДС 39892
A42: =1+'ПК с 1 владельцем'!A733 -> 16 | B42: 915 / 7010 | C42: Романова (Тросиненко) Екатерина Анатольевна /Воркунов Андрей Александрович | D42: Модернизация не требуется/normal (no need to upgrade) | E42: Rus | F42: Trosinenko Ekaterina / Vorkunov Andrey | G42: Мастер 3 категории / Мастер 1 категории | H42: MD, COMP | I42: Laptop, mouse | J42: Laptop Lenovo L340 | K42: 00000022303(8) | L42: инвентарник MOC наклеен | N42: 1-04 офис дет. Интерьера | O42: PF14SUQE | P42: ="RUTL-" & RIGHT(O42,8) -> RUTL-PF14SUQE | Q42: Внесены в Passwork | R42: Microsoft Office профессиональный плюс 2016 | T42: MS Windows 10 Prof | U42: NF6JK-H9R6P-GGM2Y-DB6BP-27JXC | V42: ULTRAVNC / MESH | W42: No Administrator rights | X42: Кудрявцев Д. | Y42: Акт 15.01.2020 / 23.09.2025
A43: =1+A42 -> 17 | B43: 1250 / 9664 | C43: Фролов Дмитрий Сергеевич / Павлов Егор Евгениевич | D43: была модернизация/upgraded(RAM+16) | E43: Rus | F43: Frolov Dmitriy | G43: Слесарь-инструментальщик/ Оператор | H43: MD, COMP | I43: WorkStation,mouse,keyboard,monitor lenovo T24I | J43: Workstation Lenovo ThinkStation P 520 | K43: 140000189 | L43: инвентарник ОС наклеен | N43: 1-04 офис дет. Интерьера | O43: S4HN3462 | P43: ="RUTL-" & RIGHT(O43,8) -> RUTL-S4HN3462 | Q43: Внесены в Passwork | V43: ULTRAVNC | X43: Климанов А | Y43: Акт 19.07.2023/ 26.11.2025
A44: =1+A43 -> 18 | B44: 3307 326 | C44: Кушнарев Илья Сергеевич Ланкин Павел | D44: Модернизация не требуется/normal (no need to upgrade) | E44: Rus | F44: Kushnarev Ilya Lankin Pavel | G44: Начальник смены | H44: MD, PAINT | I44: Laptop, mouse | J44: Acer Aspire 5 A515-57-506D | K44: поставить на учет | L44: наклеить | N44: 45717 | O44: NXKN3CD001452022993400 | P44: ="RUTL-" & RIGHT(O44,8) -> RUTL-22993400 | Q44: Внесены в Passwork | R44: Libre office | T44: Windows 11 | V44: ULTRAVNC / MESH | W44: No Administrator rights | X44: Мартынов Д. | Y44: Акт 22.10.2025 | AA44: БЕЗ НДС 50360, С НДС 60432
A45: =1+A44 -> 19 | B45: 4149 2208 | C45: Савосин Андрей Анатольевич Дёмчева Светлана Викторовна | D45: Модернизация не требуется/normal (no need to upgrade) | E45: Rus | G45: Начальник участка в цеху окраски | H45: MD, PAINT | I45: AiO, mouse, keyboard | J45: AiO Lenovo M810Z | K45: 140000155/Z000072 | L45: Наклеить | N45: 1-03 камера окраски | O45: S4FM3303 | P45: ="RUTL-" & RIGHT(O45,8) -> RUTL-S4FM3303 | Q45: Внесены в Passwork | R45: Libre office | T45: Windows 10 Pro - 22H2/19045 | V45: ULTRAVNC / MESH | W45: No Administrator rights | X45: Кудрявцев Д. | Y45: Акт 28.02.2026
A46: =1+A45 -> 20 | B46: 4908 /1531/4852/4509 | C46: Петрунин Павел Александрович / Диденко Алексей Александрович /Гусельникова Светлана Александровна | D46: Модернизация не требуется/normal (no need to upgrade) | E46: Rus | F46: Petrunin Pavel / Didenko Alexey / Guselnikova Svetlana | G46: Мастер 2 категории / Начальник участка | H46: MD, S&W | I46: Laptop, mouse | J46: Laptop Lenovo Thinkpad L580 | K46: 14000155/Z000060 | L46: Наклеить | N46: 1-02 цех сварки | O46: PF12TWZN | P46: ="RUTL-" & RIGHT(O46,8) -> RUTL-PF12TWZN | Q46: Внесены в Passwork | R46: Libre office | T46: MS Windows 10 Prof | V46: ULTRAVNC / MESH | X46: Мартынов Д./ Летунов А/Климанов А. | Y46: акт 11.12.1024 / 10.03.2025/ 20.01.2026 | Z46: 43236 | AA46: БЕЗ НДС 41754,78, С НДС 50920,47
A47: =1+A46 -> 21 | B47: - | C47: Борисов Сергей/ Каширкин Алексей Владимирович | D47: need to check | E47: Rus | F47: Borisov Sergey/Kashirkin Alexey | G47: начальники участка цеха сварки штамповки/ welding and stamping shops Group leaders | H47: MD, S&W | I47: Laptop, mouse | J47: Laptop Lenovo ThinkPad EDGE E560(C2) | K47: 150000020/Z000004 | L47: Наклеить | N47: 1-02 цех сварки | O47: PF0LC4J4 | P47: ="RUTL-" & RIGHT(O47,8) -> RUTL-PF0LC4J4 | Q47: Внесены в Passwork | V47: ULTRAVNC / MESH | X47: Кудрявцев Д. Климанов А. | Y47: 08/10/2024/ 07.11.2024 / 31.10.2025/ 20.01.2026
A48: =1+A47 -> 22 | B48: 1207/ 2609 | C48: Кутузов Сергей Владимирович/ Кочетов Михаил | D48: Модернизация не требуется/normal (no need to upgrade) | E48: Rus | F48: Kutuzov Sergey | G48: Начальник участка/ Мастер 2 категории | H48: MD, S&W | I48: Laptop, mouse | J48: Laptop Lenovo L340 | K48: 00000022303(9) | L48: Наклеить | N48: 1-02 офис цеха сварки 2 эт | O48: PF14T1VM | P48: ="RUTL-" & RIGHT(O48,8) -> RUTL-PF14T1VM | Q48: Внесены в Passwork | V48: MESH | X48: Климанов А. | Y48: акт 11-08-2021 /акт 17-12-2024
A49: =1+A48 -> 23 | B49: 1288 / 1047 | C49: Кот Андрей Сергеевич / Глаголев Александр Николаевич / Гарифзянов Евгений | D49: Модернизация не требуется/normal (no need to upgrade) | E49: Rus | F49: kot andrey/ Glagolev Aleksandr | G49: Начальник смены | H49: MD, S&W | I49: Laptop, mouse | J49: Laptop IRBIS 15NBP3506 | K49: 100000003593 | L49: Наклеить | O49: F2715NBP35060821062 | P49: ="RUTL-" & RIGHT(O49,8) -> RUTL-60821062 | Q49: Внесены в Passwork | R49: Libre office | T49: MS Windows 10 Prof | V49: ULTRAVNC / MESH | X49: Климанов А. / Летунов А. | Y49: акт 30.11.2024 / 21.02.2025/ АКТ 10.03.2025
A50: =1+A49 -> 24 | B50: 1197/4668/8162/3801 | C50: Поляков Дмитрий Генадьевич Коротнев Юрий Генадьевич Гранкин роман анатольевич Шолох Евгений Мурадович | D50: Модернизация не требуется/normal (no need to upgrade) | E50: Rus | F50: Polyakov dmitriy / Korotnev Yuriy / Grankin Roman / Sholokh Evgeniy | G50: Начальник участка / Мастер штамповой оснастки | H50: MD, S&W | I50: Laptop, mouse | J50: Laptop HP 250 G7 | K50: 100000001608 | L50: наклеить | M50: Внесен в ITSM AST0000865 | N50: 1-02 Офис сварки штамповки 2-ой этаж | O50: CND12505QN | P50: ="RUTL-" & RIGHT(O50,10) -> RUTL-CND12505QN | Q50: Внесены в Passwork | R50: 2016 for home and business (BOX) | T50: Windows 10 Pro - 22H2/19045 | U50: BYNTV-DRJ9G-7HCDP-7PPB8-33WXG | V50: ULTRAVNC / MESH | W50: No Administrator rights | X50: Кудрявцев Д./ Летунов А. | Y50: Акт от 27.03.2025 / Акт от 16.09.2025 | Z50: 43236
A51: =1+A50 -> 25 | B51: 1993 3655 1994 7274 | C51: Гудков Александр Гордиенко Владимир Алексеевич Бармин Дмитрий Щербаченко Георгий Игоревич | D51: Модернизация не требуется/normal (no need to upgrade) | E51: Rus | F51: Chernogortsev Roman Gudkov Alexander. Gordienko Vladimir Barmin Dmitry Shcherbachenko Georgy | G51: начальники участка цеха сварки штамповки/ welding and stamping shops Group leaders | H51: MD, S&W | I51: Laptop,mouse+Lan-USB | J51: Laptop Lenovo V15 G1+Lan-USB | K51: 100000001648 | L51: Наклеить | N51: 1-02 цех сварки | O51: PF2TM25Q | P51: ="RUTL-" & RIGHT(O51,8) -> RUTL-PF2TM25Q | Q51: Внесены в Passwork | R51: 2019 for home and business | S51: YNPF9-8Y39J-TTFHK-MF3YF-4X976 | V51: ULTRAVNC / MESH | X51: Климанов А.К/ Летунов А./ Климанов А. | Y51: акт 01-12-2022/22-01-2024/ 02.11.2024 / 08.11.2024 / 14,01,2025/ 19.01.26/ 17.02.2026
A52: =1+A51 -> 26 | B52: 2860/1088/3813/ 10630 | C52: Зимин Валерий/ Черноусов Роман/ Поляков Петр | D52: была модернизация/upgraded Добавление 4GB Оперативы | E52: Rus | F52: Molodtsov Anton/Zimin Valeriy/ Chernousov Roman/Polyakov Petr | G52: Начальник участка/Начальник участка/Мастер 2 категории | H52: MD, STAMP | I52: Laptop, mouse,bag | J52: Laptop Lenovo V110 | K52: 16132 | L52: инвентарник MOC наклеен | N52: 1-02 офис цеха сварки 2 эт | O52: LR0AVC24 | P52: ="RUTL-" & RIGHT(O52,8) -> RUTL-LR0AVC24 | Q52: Внесены в Passwork | R52: Libre office | V52: ULTRAVNC\mesh | W52: no need | X52: Климанов А. | Y52: акт 29.11.2024
A53: =1+A52 -> 27 | B53: 10996 7011 | C53: Плюснин Станислав Игоревич Кутузов Антон Владимирович | D53: была модернизация/upgraded Добавление 4GB Оперативы | E53: Rus | F53: Plyusnin Stanislav | G53: Начальник участка / Мастер 2 категории | H53: MD, STAMP | I53: Laptop, mouse,bag | J53: Laptop Lenovo V110 | K53: 00000011068 | L53: инвентарник MOC наклеен | M53: Внесен в ITSM AST0002158 | N53: 1-02 офис цеха сварки 2 эт | O53: R90QN4XC | P53: ="RUTL-" & RIGHT(O53,8) -> RUTL-R90QN4XC | Q53: Внесены в Passwork | R53: Libre office | V53: ULTRAVNC / MESH | W53: No Administrator rights | X53: Климанов А. / Летунов А. / Мартынов Д. | Y53: акт 29.11.2024 / 02.10.2025 / 10.12.2025 | Z53: 43368 | AA53: БЕЗ НДС 33806,78, С НДС 39892
A54: =1+A53 -> 28 | B54: 1088/4121 | C54: Зимин Валерий Владимирович/ Караваев Антон Олегович | D54: Модернизация не требуется/normal (no need to upgrade) | E54: Rus | F54: Zimin Valeriy/ Karavaev Anton. | G54: Начальник участка/ Мастер 2 категории | H54: MD, STAMP | I54: Laptop, mouse,bag | J54: Laptop IRBIS 15NBP3506 | K54: 100000003627 | L54: Наклеить | N54: 1-02 офис цеха сварки 2 эт | O54: F2715NBP35060821801 | P54: ="RUTL-" & RIGHT(O54,8) -> RUTL-60821801 | Q54: Внесены в Passwork | R54: Libre office | T54: Windows 10 Pro - 22H2/19048 | U54: 6W38N-TD78B-YH896-B64W6-683GP | V54: ULTRAVNC / MESH | W54: No Administrator rights | X54: Кудрявцев Д./ Климанов А. | Y54: Акт от 13.11.2025 / 24.11.25
A55: =1+A54 -> 29 | B55: 9506 / 1972 / 2358 | C55: Бабкина Екатерина Алексеевна / Наумкина Светлана Михайлова / Жичкин Дмитрий Владимирович | D55: Модернизация не требуется/normal (no need to upgrade) | E55: Rus | F55: Babkina Ekaterina / Naumkina Svetlana / Zhichkin Dmitry | G55: Мастер 1 категории / Мастер 2 категории | H55: MD, STAMP | I55: Laptop, mouse | J55: Laptop Lenovo V510 | K55: 00000014313 | L55: инвентарник MOC наклеен | N55: 1-02 цех штамповки 2-ой этаж | O55: LR0AVC2E | P55: ="RUTL-" & RIGHT(O55,8) -> RUTL-LR0AVC2E | Q55: Внесены в Passwork | R55: Libre office | T55: Windows 10 Pro - 22H2/19045 | U55: NTKPR-KTGG7-H9RXJ-RTQ7W-CPQGP | V55: ULTRAVNC / MESH | W55: No Administrator rights | X55: Кудрявцев Д. / Летунов А. | Y55: Акт 06.06.2025 / Акт 18.09.2025
A56: =1+A55 -> 30 | B56: 646/ 1088 | C56: Шайхизаманов Ринат Фанизович / Зимин Валерий | D56: Модернизация не требуется/normal (no need to upgrade) SSD 512 ОЗУ 8гб. | E56: Rus | F56: Shakhizamanov Rinat/ Zimin Valeriy | G56: Начальник участка | H56: MD, STAMP | I56: Laptop,mouse+Lan-USB | J56: Laptop Lenovo V 130 | K56: 00000019367(2) | L56: инвентарник MOC наклеен | N56: 1-02 офис цеха сварки 2 эт | O56: R90SRSG6 | P56: ="RUTL-" & RIGHT(O56,8) -> RUTL-R90SRSG6 | Q56: Внесены в Passwork | R56: Libre office | T56: Windows 10 Pro - 22H2/19045 | U56: Installed Key: YF42W-2KNPG-G6YW6-42D4Q-GF4C2 OEM Key: YF42W-2KNPG-G6YW6-42D4Q-GF4C2 | V56: ULTRAVNC / MESH | W56: No Administrator rights | X56: Кудрявцев Д./ Климанов А. | Y56: Акт от 30.11.2024/ 29.09.2025 | Z56: 43661
A57: =1+A56 -> 31 | B57: 7487 3563 | C57: Карагулов Кантемир Заурович Абдуллаев Эльдар Элшанович | D57: была модернизация/upgraded (SSD 256) | E57: Rus | F57: Karagulov Kantemir Abdullaev Eldar | G57: Мастер 1 категории Начальник участка | H57: MD, STAMP | I57: Laptop, mouse | J57: Laptop HP 250 G7 | K57: 100000001602 | L57: наклеить | M57: Внесен в ITSM AST0000859 | N57: 1-07 Второй этаж | O57: CND12505XP | P57: RUTL-CND12505XP | Q57: Внесены в Passwork | R57: 2016 for home and business (BOX) | S57: WJN26-MB989-2T3FD-6TDGD-3PFD9 | T57: Windows 10 Pro | U57: 9HNX7-28CB7-VYV34-GX3R7-R9CKC | V57: ULTRAVNC / MESH | W57: No Administrator rights | X57: Кудрявцев Д. | Y57: Акт 05.03.2026 | Z57: 44551 | AA57: без НДС 39916,67 с НДС 47900
A58: =1+A57 -> 32 | B58: 7986 / 3860 / | C58: Блажко Виолетта Витальевна/ Антонова Юлия | D58: Модернизация не требуется/normal (no need to upgrade) | E58: Rus | F58: Blazhko Violetta/ Antonova Yulia | G58: Экономист/ Офис-ассистент/ | H58: MD, WELD | I58: AiO, mouse, keyboard | J58: AiO Lenovo M810Z | K58: 140000152/Z000068 | L58: (Забаланс) Инвентарник наклеен | N58: 1-02 Офис сварки штамповки 2-ой этаж | O58: S4FM3362 | P58: ="RUTL-" & RIGHT(O58,8) -> RUTL-S4FM3362 | Q58: Внесены в Passwork | R58: Libre office | T58: Windows 10 Pro - 22H2/19045 | U58: VN372-P26F6-Q8FD7-V8GGR-WFG6P | V58: ULTRAVNC / MESH | W58: No Administrator rights | X58: Климанов А. | Y58: Акт 01.08.2025/ 08.08.2025
A59: =1+A58 -> 33 | B59: 419/ 7545 | C59: Завитаев Антон Владимирович / Кантауров Данил Валентинович | D59: требуется замена жесткого диска/ need to replacement hard disk | E59: Rus | F59: Zavitaev Anton / Kantaurov Danil | G59: СММ инспектор / Техник по геометрии 2 категории | H59: MD, WELD | I59: Laptop | J59: Laptop Lenovo V110 | K59: 00000010786 | L59: инвентарник MOC наклеен | M59: Внесен в ITSM AST0001580 | N59: 1-02 камера 3д измерений | O59: R90QFPYQ | P59: ="RUTL-" & RIGHT(O59,8) -> RUTL-R90QFPYQ | Q59: Внесены в Passwork | R59: Microsoft Office профессиональный плюс 2016 | T59: MS Windows 10 Prof | V59: ULTRAVNC \ MESH | X59: Климанов А. | Y59: Акт 12-11-2018/27-09-2022 / 18.02.2025
A60: =1+A59 -> 34 | B60: 6237 /0458 | C60: Бабурин Петр/Курицын Александр | D60: Модернизация не требуется/normal (no need to upgrade) | E60: Rus | F60: Baburin Petr/Kuritsyn Aleksandr | G60: Инженер по геометрии автомобиля 3 категории / Инженер по геометрии автомобиля 2 категории | H60: MD, WELD | I60: Laptop, mouse | J60: Laptop Acer Extensa 15 | K60: 100000003373 | L60: Наклеить | N60: 1-02 цех сварки | O60: NXEGYER00H32008A093400 | P60: ="RUTL-" & RIGHT(O60,8) -> RUTL-8A093400 | Q60: Внесены в Passwork | R60: Libre office | T60: MS Windows 10 Prof | U60: PQ73C-49G7J-YYHG8-6TQRV-WK8XC | V60: ULTRAVNC / MESH | W60: no need | X60: Климанов А. | Y60: акт 02.11.2024 | Z60: 2024 | AA60: БЕЗ НДС 60440.50
A61: =1+A60 -> 35 | B61: 2574 / 13834 | C61: Брежнев Дмитрий Вячеславович / Манохин Александр Сергеевич | D61: была модернизация/upgraded (SSD 240 (SSD) | E61: Rus | F61: Brezhnev Dmitry | G61: Техник по геометрии 1 категории | H61: MD, WELD | I61: Laptop, mouse | J61: Lenovo THINKPAD L450 | K61: 140000006 | L61: Наклеить | M61: Внесен в ITSM AST0000786 | N61: 1-02 офис цеха сварки 2 эт | O61: PF07168K | P61: ="RUTL-" & RIGHT(O61,8) -> RUTL-PF07168K | Q61: Внесены в Passwork | R61: Libre office | T61: Windows 10 Pro - 22H2/19045 | U61: Installed Key: NF6HC-QH89W-F8WYV-WWXV4-WFG6P OEM Key: 9NG3V-WFGG9-PXVD9-2YFH7-VT8MC | V61: ULTRAVNC / MESH | W61: No Administrator rights | X61: Климанов А. / Мартынов Д. | Y61: Акт 20.12.2025 / 26.01.2026
A62: =1+A61 -> 36 | B62: 5839 / 5098 | C62: Белов Денис Александрович / Бойцов Степан Игоревич | D62: была модернизация/upgraded (SSD 256 (SSD) | E62: Rus | F62: Belov Denis | G62: начальник участка цеха сварки штамповки/head of the section of the welding and stamping shop | H62: MD, WELD | I62: Laptop, mouse | J62: Laptop Lenovo V110 | K62: 00000011074 | L62: инвентарник MOC наклеен | M62: Внесен в ITSM AST0002166 | N62: 1-02 цех сварки | O62: R90QFPZT | P62: ="RUTL-" & RIGHT(O62,8) -> RUTL-R90QFPZT | Q62: Внесены в Passwork | V62: ULTRAVNC / MESH | W62: No Administrator rights | X62: Мартынов Д. | Y62: Акт 30.01.2026 | Z62: 43368 | AA62: БЕЗ НДС 33806,78, С НДС 39892
A63: =1+#REF! -> #REF! | B63: - | C63: Бакай Иван/Саакян Максим/Илюшкин Илья Юрьевич | D63: Модернизирован SSD samsung 500гб ОЗУ 12гб | E63: Rus | F63: Bakai Ivan/Saakyan Maksim / Ilyushkin Ilya | G63: начальник участка цеха сварки штамповки | H63: MD, WELD | I63: Laptop, mouse,bag | J63: Laptop Lenovo V110 | K63: 00000011069 | L63: инвентарник MOC наклеен | M63: Внесен в ITSM AST0002159 | N63: 1-04 офис цеха сборки | O63: R90QN4VV | P63: ="RUTL-" & RIGHT(O63,8) -> RUTL-R90QN4VV | Q63: Внесены в Passwork | R63: Libre office | T63: Windows 10 Pro - 22H2/19045 | V63: ULTRAVNC / MESH | W63: No Administrator rights | X63: Климанов А. / Летунов А. / Кудрявцев Д./ Климанов А. | Y63: Акт 01.10.2024 / Акт 05.11.2024 / Акт 04.09.2025/ 13.10.2025/ 03.03.2026 | Z63: 43368 | AA63: БЕЗ НДС 33806,78, С НДС 39892
A64: =1+A63 -> #REF! | B64: - | C64: Толчева Милена Сергеевна14765 Журавлева Ольга Владимировна | D64: Модернизация не требуется/normal (no need to upgrade) | E64: Rus | F64: Zhuravleva Olga/ Tolcheva Milena | G64: Оператор ( ИО специалист по производственной безопасности)/Специалист по COGI | H64: MD, WELD | I64: Laptop, mouse | J64: Laptop Lenovo V 130 | K64: 00000019366(7) | L64: инвентарник MOC наклеен | N64: 1-02 офис цеха сварки 2 эт | O64: R90T947M | P64: ="RUTL-" & RIGHT(O64,8) -> RUTL-R90T947M | Q64: Внесены в Passwork | R64: 2019 for home and business | S64: Y9QCX-JN9X2-JTV8D-H7GMK-TF6MT | T64: Windows 10 Pro | V64: ULTRAVNC / MESH | W64: No Administrator rights | X64: Кудрявцев Д./Климанов А. | Y64: Акт 28.02.2026/16.03.20226 | Z64: 43661
A65: =1+A64 -> #REF! | B65: 14414 / 14413 | C65: Сабра Джехад /Дабабне Исса | D65: Модернизация не требуется/normal (no need to upgrade) | E65: Rus | F65: Sabra Jehad / Dababne Issa | G65: Инженер-технолог 1 категории | H65: MD,WELD | I65: Laptop, mouse | J65: Laptop IRBIS 15NBP3507 | K65: поставить на учет | L65: Наклеить | O65: F2715NBP35070822047 | P65: ="RUTL-" & RIGHT(O65,8) -> RUTL-70822047 | Q65: Внесены в Passwork | R65: Libre office | T65: Windows 10 Pro | U65: N49FW-W4B2V-MDXHQ-GTJDQ-WQKTP | V65: ULTRAVNC / MESH | W65: No Administrator rights | X65: Климанов А. / Мартынов Д. | Y65: Акт 10.02.2026 / 06.03.2026
A66: =1+A65 -> #REF! | B66: 835/1173/5960/642 | C66: Ершова Анастасия Юрьевна/ Колков Александр Александрович /Дормидонтов Владимир Владимирович | D66: требуется модернизация/ЗАМЕНА сдох жесткий | E66: Rus | F66: Anastasiya Ershova /Kolkov Alexander/Dormidontov Vladimir | G66: Начальники участка/group leaders of Paint | H66: MD(Paint) | I66: AiO, mouse, keyboard | J66: AiO Lenovo M810Z | K66: 140000167/Z000084 | L66: Наклеить | N66: 1-03 первый этаж цех | O66: S4FM3406 | P66: ="RUTL-" & RIGHT(O66,8) -> RUTL-S4FM3406 | Q66: Внесены в Passwork | V66: ULTRAVNC / MESH | X66: Климанов А. | Y66: акт 10-08-2023/10.02.2026
A67: =1+#REF! -> #REF! | B67: 3955 1486 | C67: Журавлев Антон Вячеславович Свиридова Алёна Константиновна | D67: была модернизация/upgraded (SSD 256 +r am) | E67: Rus | F67: Zhuravlev Anton Sviridova Alena | G67: Начальник участка Мастер 1 категории | H67: PLD, DL | I67: Laptop, mouse,bag | J67: Laptop Lenovo V110 | K67: 00000011062 | L67: инвентарник MOC наклеен | M67: Внесен в ITSM AST0002152 | N67: 1-04 апендикс логистики | O67: R90QN4Y2 | P67: ="RUTL-" & RIGHT(O67,8) -> RUTL-R90QN4Y2 | Q67: Внесены в Passwork | R67: Libre office | T67: MS Windows 10 Prof | U67: RRPT3-F3N4C-T9882-7YT6K-TF4C2 | V67: ULTRAVNC / MESH | W67: No Administrator rights | X67: Летунов А. Кудрявцев Д. | Y67: Акт 14.08.2025 Акт 05.12.2025 | Z67: 43368 | AA67: БЕЗ НДС 33806,78, С НДС 39892
A68: =1+A67 -> #REF! | B68: 10588 4744 | C68: Карпушкина Анжела Геннадьевна Фалина Елена | D68: Модернизация не требуется/normal (no need to upgrade) | E68: Rus | F68: karpushkina angela / Falina Elena | G68: Специалист по вводу данных/ Специалист по вводу данных | H68: PLD, DL | I68: Laptop, mouse | J68: Laptop IRBIS 15NBP3506 | K68: 100000003598 | L68: Наклеить | N68: 1-04 комната 123 (вроде) | O68: F2715NBP35060820709 | P68: ="RUTL-" & RIGHT(O68,8) -> RUTL-60820709 | Q68: Внесены в Passwork | R68: Professional Plus 2019 | V68: ULTRAVNC\mesh | X68: Климанов А. | Y68: акт 06.12.2024
A69: =1+A68 -> #REF! | B69: 8379 | C69: Ерохина Анжела Юрьевна/Острась Илья | D69: Модернизация не требуется/normal (no need to upgrade) | E69: Rus | F69: Ostras Ilya | G69: Начальник участка | H69: PLD, DL | I69: Laptop, mouse | J69: Laptop IRBIS 15NBP3512 | K69: ОТЖАТЬ /ВЫДАН НЕВЕРНО | L69: наклеить | O69: F2715NBP3512_G2084140 | P69: ="RUTL-" & RIGHT(O69,8) -> RUTL-G2084140 | Q69: Внесены в Passwork | R69: Libre office | U69: MXFK4-67NGM-WJQQ8-RWHYC-KW3GP | V69: ULTRAVNC / MESH | X69: Мартынов Д. | Y69: Акт 03.12.2024 / 21.01.2026
A70: =1+A69 -> #REF! | B70: 892 / 844 | C70: Лось Алексей Анатольевич / Коняев Владимир Сергеевич | D70: была модернизация/upgraded (SSD)+ram | E70: Rus | F70: Los Alexey / Konyaev Vladimir | G70: Начальник участка | H70: PLD, DL | I70: Laptop, mouse,bag | J70: Laptop Lenovo V110 | K70: 00000011055 | L70: инвентарник MOC наклеен | M70: Внесен в ITSM AST0002169 | N70: 1-04 апендикс логистики | O70: R90QN4WH | P70: ="RUTL-" & RIGHT(O70,8) -> RUTL-R90QN4WH | Q70: Внесены в Passwork | R70: Libre office | T70: Windows 10 Pro - 22H2/19045 | U70: FKKNH-CYFXT-MWD86-Q3PTY-6VJXC | V70: ULTRAVNC / MESH | W70: No Administrator rights | X70: Кудрявцев Д. | Y70: акт 02.04.2025 | Z70: 43368 | AA70: БЕЗ НДС 33806,78, С НДС 39892
A71: =1+'ПК с 1 владельцем'!A697 -> 1 | B71: 687/1443 | C71: Абдель Латиф Аль Раи Анвар Махмуд/Бочаров Владислав Евгеньевич | D71: need to check | E71: Rus | F71: Al Rai Abdel Latif/ Bocharov Vladislav | G71: Начальник участка | H71: PLD, DL | I71: Laptop, mouse,bag | J71: Laptop Lenovo V510 | K71: 00000016123 | L71: инвентарник MOC наклеен | N71: 1-06 первый этаж | O71: LR0AVC0V | P71: ="RUTL-" & RIGHT(O71,8) -> RUTL-LR0AVC0V | Q71: Внесены в Passwork | R71: Libre office | V71: ULTRAVNC | W71: No Administrator rights | X71: Летунов А. / Мартынов Д. | Y71: 22.01.2025/06.03.2026
A72: =1+'ПК с 1 владельцем'!A662 -> #REF! | B72: 539 3925 | C72: Ковалев Александр Павлович Болотин Геннадий Николаевич | D72: Стоит SSD 240 ОЗУ 8GB | E72: Rus | F72: Kovalev Aleksandr Bolotin Gennady | G72: Начальник участка Начальник участка | H72: PLD, WL | I72: Laptop, mouse,bag | J72: Laptop Lenovo ThinkPad EDGE E570(C2) | K72: 140000056/Z000105 | L72: Наклеить | N72: 1-06 первый этаж | O72: PF10YR5K | P72: ="RUTL-" & RIGHT(O72,8) -> RUTL-PF10YR5K | Q72: Внесены в Passwork | R72: Libre office | T72: Windows 10 Pro - 22H2/19045 | V72: ULTRAVNC \ MESH | W72: no need | X72: /Летунов А. | Y72: / Акт 25-01-2023 / Акт 20.05.2025
A73: =1+A72 -> #REF! | B73: 3245 6762 8324 11045 5302 | C73: Федин Антон Александрович Зададаева Анастасия Игоревна Перескокова Юлия Сухачева Олеся Васильевна Власова Эльвира | D73: Модернизация не требуется/normal (no need to upgrade) | E73: Rus | F73: Fedin Anton Zadadaeva Anastasiya Pereskokova Julia Sukhacheva Olesya | G73: специалист по вводу данных/Data maintenance specialist | H73: PLD, WL | I73: WorkStation,mouse,keyboard,monitor lenovo T24I | J73: Workstation Lenovo V530s+ отдельно монитор Т24I | K73: 100000001596 | L73: Наклеить | N73: 1-06 первый этаж | O73: YL00SV07 | P73: ="RUTL-" & RIGHT(O73,8) -> RUTL-YL00SV07 | Q73: Внесены в Passwork | R73: Microsoft Office профессиональный плюс 2016 | T73: Windows 10 Pro - 22H2/19045 x64 | V73: ULTRAVNC | W73: no need | X73: / Кудрявцев Д. | Y73: акт 24-09-2021/16-11-2023/01-02-2024/26-08-2024 / 13.01.2025
A74: =1+A73 -> #REF! | B74: 6428/10031 | C74: Рогатина Елизавета Георгиевна/ Шестаков Игорь Витальевич | D74: была модернизация/upgraded(SSD 256 +RAM +8) | E74: Rus | F74: Rohatina Elizaveta/Shestakov Igor | G74: Аудитор логистических процессов | H74: PLD,DL | I74: Laptop, mouse | J74: Laptop Lenovo V110 | K74: 00000010776 | L74: инвентарник MOC наклеен | M74: Внесен в ITSM AST0001569 | N74: 1-06 первый этаж | O74: R90QFPYJ | P74: ="RUTL-" & RIGHT(O74,8) -> RUTL-R90QFPYJ | Q74: Внесены в Passwork | R74: 2019 for home and business | S74: 3H8XT-PN3WH-GVQR6-MMGJQ-63CYT | T74: Win 10 Pro 64 | U74: QTXVN-JJXK6-PXBHH-FC38J-PKCKC | V74: ULTRAVNC | X74: Климанов А. | Y74: Акт 18.02.2027
A75: =1+A74 -> #REF! | B75: 10241 / 8452 / 3641 | C75: Потапова Надежда Николаевна / Шишиморова Елена Александровна | D75: была модернизация/upgraded (SSD) | E75: Rus | F75: Potapova Nadezhda / Shishimorova Elena | G75: Специалисты по складскому учету и документообороту/warehouse specialists | H75: PMD, WS | I75: AiO, mouse, keyboard | J75: AiO Lenovo M810Z | K75: 140000162/Z000080 | L75: Наклеить | N75: 1-04 склад цеха сборки | O75: S4FM3311 | P75: ="RUTL-" & RIGHT(O75,8) -> RUTL-S4FM3311 | Q75: Внесены в Passwork | R75: Libre office | T75: Windows 10 Pro - 22H2/19045 | U75: Installed Key: VK7JG-NPHTM-C97JM-9MPGT-3V66T OEM Key: 6NM94-Y34GJ-9RKDD-V7B4B-B4G6P | V75: ULTRAVNC / MESH | W75: no need | X75: Кудрявцев Д. | Y75: акт 14.11.2024
A76: =1+A75 -> #REF! | B76: 3102 4738 | C76: Струкова(Глашкина) Кристина Сергеевна Фрост Елена Владимировна | D76: Модернизация не требуется/normal (no need to upgrade) | E76: Rus | F76: Glashkina Kristina / Frost Elena | G76: Кладовщик | H76: PMD, WS | I76: AiO, mouse, keyboard | J76: AiO Lenovo M810Z | K76: 140000170/Z000087 | L76: Наклеить | N76: 1-03 офис окраски 1эт(склад) | O76: S4FM3412 | P76: ="RUTL-" & RIGHT(O76,8) -> RUTL-S4FM3412 | Q76: Внесены в Passwork | R76: Libre office | V76: ULTRAVNC / MESH | X76: Климанов А. / Мартынов Д. | Y76: Акт 01.10.2024 / 13.01.2025
A77: =1+A76 -> #REF! | B77: 3942 4738 6503 10689 | C77: Горюнова Светлана Викторовна Башурина Анастасия Алексеевна | D77: была модернизация/upgraded (SSD) | E77: Rus | F77: Goryunova Svetlana Bashurina Anastasiya Mertehina Olga | G77: Специалисты по складскому учету и документообороту/warehouse specialists | H77: PMD, WS | I77: AiO, mouse, keyboard | J77: AiO Lenovo S400Z | K77: 140000036 | L77: инвентарник ОС наклеен | N77: 1-02 склад сварки штамповки | O77: P901FSR7 | P77: ="RUTL-" & RIGHT(O77,8) -> RUTL-P901FSR7 | Q77: Внесены в Passwork | T77: Windows 10 Pro - 22H2/19045 | U77: K4XYM-FGNH6-H7YMT-72WF6-Y986C | V77: ULTRAVNC / MESH | W77: no need | X77: Кудрявцев Д. | Y77: акт 26.11.2024 / 18.06.2025
A78: =1+A77 -> #REF! | B78: 718/2915/ 5696 | C78: Филина Светлана Владимировна / Шайхизаманова(Салова) Анна Игоревна / Александрова Любовь | D78: Модернизация не требуется/normal (no need to upgrade) | E78: Rus | F78: Filina Svetlana / Alexandrova Lyubov Shaikhizamanova Anna | G78: Мастера проверки качества (линии интерьера и экстерьера)/Masters of quality control (interior and exterior lines) | H78: Q&T, QI | I78: Laptop, mouse | J78: Laptop Acer Extensa 15 | K78: 100000003367 | L78: Наклеить | O78: NXEGYER00H32008AB43400 | P78: ="RUTL-" & RIGHT(O78,8) -> RUTL-8AB43400 | Q78: Внесены в Passwork | V78: ULTRAVNC | X78: Летунов А. \ Климанов А. | Y78: акт 30-07-2024 / акт 06-11-2024 | Z78: 2024 | AA78: БЕЗ НДС 60440.50
A79: =1+'Технические ПК'!A54 -> 51 | B79: 718 2848 2079 | C79: Филина Светлана Владимировна Самбурова Елена Якушева Олеся | D79: Модернизация не требуется/normal (no need to upgrade) | E79: Rus | F79: Filina Svetlana / Samburova Ekaterina / Yakusheva Olesya | G79: Мастер 2 категории / Мастер 1 категории | H79: Q&T, QI | I79: Laptop, mouse | J79: Laptop Lenovo V510 | K79: 00000016129 | L79: инвентарник MOC наклеен | O79: LR0AVC0E | P79: ="RUTL-" & RIGHT(O79,8) -> RUTL-LR0AVC0E | Q79: Внесены в Passwork | R79: Libre office | T79: Windows 10 Pro - 22H2/19045 | U79: TG4FJ-M3N83-PPJP2-V8BM7-WK8XC | V79: ULTRAVNC / MESH | W79: No Administrator rights | X79: Кудрявцев Д. / Мартынов Д. | Y79: Акт 13.05.2025 / 16.09.2025
A80: =1+A79 -> 52 | B80: 1608 / 3286/ 4756 | C80: Шумейко Андрей Витальевич /Линяев Иван Александрович | D80: Модернизация не требуется/normal (no need to upgrade) | E80: Rus | F80: Shumeiko Andrei / Linyaev Ivan. | G80: Начальник участка / Контролер качества/Мастер 1 категории | H80: Q&T, QI | I80: Laptop, mouse | J80: Laptop IRBIS 15NBP3508 | K80: 100000003375 | L80: Наклеить | O80: F2715NBP35080821781 | P80: ="RUTL-" & RIGHT(O80,8) -> RUTL-80821781 | Q80: Внесены в Passwork | V80: ULTRAVNC | X80: Климанов А.\Летунов А.\ Климанов А. | Y80: акт 09-08-2024/29,10,2024/ 17.07.2025
A81: =1+A80 -> 53 | B81: 1721 / 5796 / 6388 | C81: Матюшин Михаил Александрович / Тетерин Дмитрий Сергеевич/ Рожков Дмитрий Юрьевич | D81: была модернизация/upgraded (SSD) | E81: Rus | F81: Matyushin Mikhail / Teterin Dmitry / Rozhkov Dmitry | G81: Начальник участка/Мастер / Мастер 2 категории | H81: Q&T, QI | I81: Laptop, mouse | J81: Laptop Lenovo V510 | K81: 00000016128 | L81: инвентарник MOC наклеен | N81: 1-04 напротив светового тонеля | O81: LR0AVC1U | P81: ="RUTL-" & RIGHT(O81,8) -> RUTL-LR0AVC1U | Q81: Внесены в Passwork | R81: Libre office | T81: Windows 10 Pro - 22H2/19045 | U81: 2GFV2-N8Y44-TQBMM-M6M37-4C2KC | V81: ULTRAVNC | W81: No administrator rights | X81: Кудрявцев Д. / Мартынов Д./ Климанов А. | Y81: Акт 21.05.2024 / 13.05.2025 / 24.07.2025 | Z81: 43482
A82: =1+A81 -> 54 | B82: 4086\0341 | C82: Лаврищева Оксана Сергеевна / Солопов Сергей Александрович | D82: Модернизация не требуется/normal (no need to upgrade) | E82: Rus | F82: Lavrisheva Oksana/ Solopov Sergey | G82: Техник по деталям интерьера и экстерьера/Interior and exterior detail Technician | H82: Q&T, QI | I82: WorkStation,mouse,keyboard,monitor lenovo T24I | J82: Компьтер Thinkstation P520 Intel Xeon W-2104 | K82: 140000192 | L82: инвентарник ОС наклеен | N82: 1-09 второй этаж | O82: S4HN3484 | P82: ="RUTL-" & RIGHT(O82,8) -> RUTL-S4HN3484 | Q82: Внесены в Passwork | V82: ULTRAVNC | Y82: Акт 27-06-2023/15-05-2024
A83: =1+A82 -> 55 | B83: 10689 / 5369 | C83: Мертехина Ольга Константиновна Заверухина Елена Юрьевна | D83: Модернизация не требуется/normal (no need to upgrade) | E83: Rus | F83: Mertekhina Olga / Zaverukhina Elena | G83: Кладовщик | H83: R&D, PMD, PS | I83: AiO, mouse, keyboard | J83: LENOVO V30a-22IML | K83: 100000001323 | L83: Наклеить | N83: 1-07 четвертый этаж | O83: MP1Z7VHF | P83: ="RUTL-" & RIGHT(O83,8) -> RUTL-MP1Z7VHF | Q83: Внесены в Passwork | T83: MS Windows 10 Prof | V83: ULTRAVNC | W83: No Administrator rights | X83: Летунов А. | Y83: Акт 27.02.2026
A84: =1+A83 -> 56 | B84: 11796 12819 | C84: Лыгина Наталья Олеговна Проскоков Алексей Олегович | D84: Модернизация не требуется/normal (no need to upgrade) Был заменён аккумулятор 03.03.2026 Мартыновым Ethernet порт расшатан сильно, выдали адаптер USB - LAN Тачпад не работает | E84: Rus | F84: Lygina Natalya/Proskokov Alexey | G84: Специалист по технической оценке производственных процессов | H84: R&D, Q&T, PQM | I84: Laptop,mouse+Lan-USB | J84: Laptop IRBIS 15NBP3506 | K84: поставить на учет | L84: наклеить | N84: 1-09 второй этаж | O84: F2715NBP35060820006 | P84: ="RUTL-" & RIGHT(O84,8) -> RUTL-60820006 | Q84: Внесены в Passwork | R84: Libre office | T84: Windows 10 Pro - 22H2/19045 | U84: TNBVX-T7BTQ-63FBM-JWMW8-2GYP2 | V84: ULTRAVNC / MESH | W84: No Administrator rights | X84: Мартынов Д./ Летунов А./ Климанов А. | Y84: Акт 15.01.2024 Акт 11.03.2025 / 26.09.2025
A85: =1+A84 -> 57 | B85: 6591/11447/ 12600 | C85: Соловьев Денис Юрьевич/ Захарова Кристина Александровна | D85: Модернизация не требуется/normal (no need to upgrade) | E85: Rus | F85: Solovyov Denis/Kuznetsova Natalia/Zakharova Kristina | G85: Специалист по качеству | H85: R&D, Q&T, PQM | I85: Laptop, mouse,bag | J85: Laptop IRBIS 15NBP3506 | K85: 100000003638 | L85: Наклеить | N85: 1-09 второй этаж | O85: F2715NBP35060820719 | P85: ="RUTL-" & RIGHT(O85,8) -> RUTL-60820719 | Q85: Внесены в Passwork | R85: Libre office | T85: Windows 10 Pro - 22H2/19045 x64 | U85: TFJPT-XNPQC-7RKQR-8JPKY-R6YP2 | V85: ULTRAVNC | W85: No Administrator rights | X85: Кудрявцев Д./ Климанов А. | Y85: Акт 23.11.2024/29.09.25/29.09.25
A86: =1+A85 -> 58 | B86: 11465/ 10747 | C86: Козлова Анастасия Сергеевна/Янтикова Алёна Владимировна | D86: Модернизация не требуется/normal (no need to upgrade) | E86: Rus | F86: Kozlova Anastasia/Yantikova Alena | G86: Специалист по качеству | H86: R&D, Q&T, PQM | I86: Laptop, mouse | J86: Laptop Lenovo V110 | K86: 00000010771 | L86: инвентарник MOC наклеен | M86: Внесен в ITSM AST0001572 | O86: R90QFPYZ | P86: ="RUTL-" & RIGHT(O86,8) -> RUTL-R90QFPYZ | Q86: Внесены в Passwork | R86: Libre office | T86: Windows 10 Pro - 22H2/19045 | U86: 68JRX-NVXKF-RDKRG-G2PGP-27JXC | V86: Windows 10 Pro - 22H2 | W86: No Administrator rights | X86: Летунов А./ Климанов А. | Y86: Акт 04.06.2025/ 26.09.25
A87: =1+'ПК с 1 владельцем'!A1295 -> 1 | B87: - | C87: Матюхин Александр Александрович Макаров Григорий Вячеславович | D87: Модернизация не требуется/normal (no need to upgrade) | E87: Rus | F87: Matyukhin Aleksandr Chernogortsev Roman / Makarov Grigory | G87: Начальник участка Начальник участка | H87: MD, WELD | I87: Laptop, mouse,bag | J87: Laptop Lenovo V510 | K87: 00000016126 | L87: инвентарник MOC наклеен | N87: 1-02 цех штамповки 2-ой этаж | O87: LR0AVC1J | P87: ="RUTL-" & RIGHT(O87,8) -> RUTL-LR0AVC1J | Q87: Внесены в Passwork | R87: 2019 for home and business | S87: MRJVN-7H2TD-7TH8K-2WWX8-BWTMT | T87: Windows 10 Pro - 22H2/19045 x65 | U87: N3MB8-7J8M8-QFR2P-FXR8Q-WQKTP | V87: ULTRAVNC / MESH | W87: No Administrator rights | X87: Кудрявцев Д./ Климанов А. | Y87: Акт 03.03.2026 / 06.03.2026
A88: =1+'ПК с 1 владельцем'!A699 -> 5 | B88: 1265 14868 | C88: Гайдуков Сергей Эдуардович Поляков Александр Анатольевич | D88: Модернизация не требуется/normal (no need to upgrade) | E88: Rus | F88: Gaidukov Sergey Polyakov Alexander | G88: Мастер 3 категории | H88: TM | I88: Laptop, mouse | J88: Laptop Lenovo V110 | K88: 00000010775 | L88: инвентарник MOC наклеен | M88: Внесен в ITSM AST0001446 | O88: R90QFPYH | P88: ="RUTL-" & RIGHT(O88,8) -> RUTL-R90QFPYH | Q88: Внесены в Passwork | R88: Libre Office / Only office | T88: Windows 10 Pro | U88: T3QQN-263W4-YTYRY-HK8BG-MKMP2 | V88: ULTRAVNC / MESH | W88: No Administrator rights | X88: Климанов А. | Y88: Акт 11.03.2026
A89: ='ПК с 2 и более владельцами'!A62+1 -> 37 | B89: gw07008154 | C89: Егоров Дмитрий Николаевич Жбанов Максим Витальевич ( 8154 ) | D89: Модернизация не требуется/normal (no need to upgrade) | E89: Rus | F89: Egorov Dmitry Zhbanov Maxim | G89: Инженер-технолог 3 категории Инженер-технолог 1 категории | H89: MD, WELD | I89: Laptop, mouse,bag | J89: Laptop Acer Extensa 15 | K89: 100000003335 | L89: наклеить | O89: NXEGYER00H32008A7A3400 | P89: ="RUTL-" & RIGHT(O89,8) -> RUTL-8A7A3400 | Q89: Внесены в Passwork | T89: Windows 10 Pro | U89: CPX29-JKNFG-DPMP3-PT3D6-RRHJ6 | V89: ULTRAVNC / MESH | W89: No Administrator rights | X89: Кудрявцев Д. | Y89: Акт 17.08.2026 | Z89: 2024 | AA89: БЕЗ НДС 60440.50
A90: ='ПК с 1 владельцем'!A646+1 -> #REF! | B90: - | C90: Ершов Максим Михайлович ( 272 ) Корнеев Владимир Аркадьевич ( 7791 ) | D90: Модернизация не требуется/normal (no need to upgrade) | E90: Rus | F90: Ershov Maksim Korneev Vladimir | G90: Инженер-механик 1 категории Инженер по производственному оборудованию | H90: M&U, MTC ASPC | I90: Laptop, mouse | J90: Laptop Acer Aspire 5 A515-54G | K90: поставить на учет | N90: 1-04 офис MU цеха сборка | O90: NXHN0ER005011109767600 | P90: ="RUTL-" & RIGHT(O90,8) -> RUTL-09767600 | Q90: Внесены в Passwork | R90: Microsoft Office профессиональный плюс 2019 | T90: Windows 10 Pro | U90: QDC3Q-QNRRD-Q7HQG-R36BD-7T9QQ | V90: ULTRAVNC / MESH | W90: No Administrator rights | X90: Кудрявцев Д. Кудрявцев Д. | Y90: Акт 23.03.2026 Акт 23.03.2026
A91: =1+'ПК с 1 владельцем'!A656 -> #REF! | B91: - | C91: Оспищев Роман Николаевиx (12526) Зафарзода Зарирджон (4471) | D91: Модернизация не требуется/normal (no need to upgrade) | E91: Rus | F91: Ospischev Roman Zafarzoda Zarirjon | G91: Мастер 2 категории | H91: MD, WELD | I91: Laptop, mouse | J91: Laptop Lenovo Thinkpad L580 | K91: 14000149/Z000042 | L91: Наклеить | M91: Внесен в ITSM AST0001704 | O91: PF12TV9F | P91: ="RUTL-" & RIGHT(O91,8) -> RUTL-PF12TV9F | Q91: Внесены в Passwork | R91: SoftMaker FreeOffice 2021 | T91: Windows 10 Pro | V91: ULTRAVNC / MESH | W91: No Administrator rights | X91: Мартынов Д. | Y91: Акт от 30.03.2026 | Z91: 43236 | AA91: БЕЗ НДС 41754,78, С НДС 50920,47
A92: =A110+1 -> 1 | B92: 3642 \ 15181 | C92: Бакай Юлия Витальевна (3642) Сычев Тимофей Романович (15181) | D92: Модернизация не требуется/normal (no need to upgrade) | E92: Rus | F92: Bakai Yulia Timofey Sychev | G92: Специалист по технологической оценке производственного процесса | H92: R&D, Q&T, PQM | I92: Laptop, mouse | J92: Lenovo ThinkBook 16 G7 ARP 3 | K92: поставить на учет | L92: Наклеить | O92: PW0LW3SH | P92: ="RUTL-" & RIGHT(O92,8) -> RUTL-PW0LW3SH | Q92: Внесены в Passwork | R92: Libre Office / Only office | T92: Windows 11 Pro | U92: BN2WX-GH4QF-YHJ2F-M362V-BDXCT | V92: ULTRAVNC / MESH | W92: No Administrator rights | X92: Протопопов А. | Y92: Акт 03.04.2026 | Z92: 46108 | AA92: С НДС 64660 БЕЗ НДС 53000
A93: 12 | B93: 13503 \ 15315 | C93: Курмелев И.В. (13503) Лышов Д.Н. (15315) | D93: Модернизация не требуется/normal (no need to upgrade) | E93: Rus | F93: Igor Kurmelev Dmitry Lyshov | G93: СММ Инспектор / инженер по геометрии | H93: MD, WELD | I93: Laptop,mouse+Lan-USB | J93: Laptop IRBIS 15NBP3506 | K93: 100000003595 | L93: наклеить | N93: 1-09 третий этаж | O93: F2715NBP35060821715 | P93: ="RUTL-" & RIGHT(O93,8) -> RUTL-60821715 | Q93: Внесены в Passwork | R93: Libre Office / Only office | T93: Windows 10 Pro | U93: VK7JG-NPHTM-C97JM-9MPGT-3V66T | V93: ULTRAVNC / MESH | W93: No Administrator rights | X93: Протопопов А. | Y93: Акт 06.04.2026

Sheet Технические ПК
A1: # | B1: Technical_PC
B2: Табельный номер / Employee ID | C2: Физлицо / Owner | D2: История модернизаций, ремонтов / Modernisation, repairing history | E2: Тип домена / Domain Type | F2: Имя на английском / English name | G2: Должность / Position (Rus / Eng) | H2: Отдел / Department | I2: Комплектация / Equipment | J2: Тип и модель ПК / PC type and model | K2: Инвентарный номер / Inventory number | L2: Инвентарный номер наклеен? / Is the inventory number affixed? | M2: где хранится информация о компе | N2: Местоположение / Location | O2: Серийный номер / Serial Number | P2: Имя компьютера / PC Domain Name | Q2: TeamPass, Passwork? | R2: Тип ПО офис / Office type | S2: Ключ офиса / License key Office | T2: ОС тип / OS Type | U2: Ключ ОС / Key OS | V2: ПО удалённого управления / Remote control | W2: Админ права / Admin permissions | X2: Кто подготовил / Who installed | Y2: Дата выдачи / Issue Date | Z2: Дата покупки / Purchasing Date | AA2: Примечание / Comment
A3: 1 | C3: Весовая Акт Казазаев 19-09-2025 | D3: была модернизация/upgraded (SSD 480 +RAM8) | E3: Rus | H3: GA_для весового контроля | I3: AiO, -мышь свою оставил (личная), keyboard | J3: AiO Lenovo S400Z | K3: 150000006/Z000012 | L3: Наклеить | N3: СКЛАД | O3: P901FSPN | P3: ="RUTL-" & RIGHT(O3,8) -> RUTL-P901FSPN | X3: Летунов А. | Y3: Акт 18,09,2025 | AA3: Норм
A4: 2 | C4: Куан Хэн акт 08-02-2019 | D4: очень старый /old(2015-2017 г) | E4: Rus | H4: GA_для комендантов общежития | I4: Workstation, Monitor(Lenovo 19" LT 1952p Black/240000014-0002)mouse, keyboard | J4: WorkStation Lenovo ThinkCenter M73(24000014) | K4: 00000000315 | L4: Наклеить | N4: local acc Dormitory.105-106 | O4: PC017TGV | P4: ="RUTL-" & RIGHT(O4,8) -> RUTL-PC017TGV
A5: 3 | C5: Мамед Г акт 07-08-2024 | D5: очень старый /old(2015-2017 г) | E5: Rus | H5: GA_для комендантов общежития | I5: WorkStation,monitor(20994),mouse,keyboard | J5: WorkStation Lenovo M93p | K5: 100000001343(0000009138(1)) | L5: Наклеить | N5: local acc Dormitory.105-106 | O5: PBP3W0G | P5: ="RUTL-" & RIGHT(O5,8) -> RUTL-PBP3W0G
A6: 4 | C6: Sec_КПП Огаревка( акт 13-02-2024 Ильин Д) | D6: требуется модернизация/ need to modernisation | H6: GD, SEC, SG | I6: Laptop,mouse | J6: Laptop Lenovo x240 | K6: поставить на учет | L6: MOSCOW | N6: 1-02 офис MU цеха сварки | O6: PF0095LY | P6: ="RUTL-" & RIGHT(O6,8) -> RUTL-PF0095LY | X6: Летунов А. | Y6: Акт 13-02-24 | Z6: 2013
A7: 5 | C7: технический компьютер с кпп | D7: Модернизация не требуется/normal (no need to upgrade) | H7: GD, SEC, SG | I7: WorkStation,monitor,mouse,keyboard | J7: Workstation Lenovo V530s+ отдельно монитор | K7: не на балансе | L7: Наклеить | N7: КПП | O7: YL002WQK | P7: ="RUTL-" & RIGHT(O7,8) -> RUTL-YL002WQK | U7: VMRJN-B8RC7-QBJMM-GVM8D-QRR9C | V7: ULTRAVNC
A8: 6 | C8: для электронных птс СОБОЛЬ (Болясова) СГП ЭПТС EPTS | D8: need check | G8: Специалист по выпуску электронного паспорта | H8: GD,FPW (соболь) | I8: WorkStation,monitor,mouse,keyboard | J8: Workstation Lenovo V530+ отдельно монитор Т24м | K8: 140000214 | L8: инвентарник ОС наклеен | N8: 45839 | O8: YL002URP | P8: ="RUTL-" & RIGHT(O8,8) -> RUTL-YL002URP
A9: 7 | C9: для электронных птс СОБОЛЬ (Акт на Аверьянову 12-08-2024) СГП EPTS ЭПТС | D9: need check | G9: Специалист по выпуску электронного паспорта | H9: GD,FPW (соболь) | I9: WorkStation,monitor,mouse,keyboard | J9: Workstation Lenovo V530s+ отдельно монитор S24E | K9: поставить на учет | L9: - | N9: 45839 | O9: YL002US3 | P9: ="RUTL-" & RIGHT(O9,8) -> RUTL-YL002US3
A10: 8 | C10: для электронных птс СОБОЛЬ (Акт Рязанцев К. 12-01-2022 г) Петрова СГП EPTS ЭПТС | D10: need check | G10: Специалист по выпуску электронного паспорта | H10: GD,FPW (соболь) | I10: WorkStation,monitor,mouse,keyboard | J10: Workstation Lenovo V530+ отдельно монитор Т24м | K10: 140000213 | L10: инвентарник ОС наклеен | N10: 45839 | O10: YL003MHN | P10: ="RUTL-" & RIGHT(O10,8) -> RUTL-YL003MHN
A11: 9 | C11: для электронных птс СОБОЛЬ Корнева Светлана Евгеньевна СГП EPTS ЭПТС | D11: need check | G11: Специалист по выпуску электронного паспорта | H11: GD,FPW (соболь) | I11: WorkStation,monitor,mouse,keyboard | J11: Workstation Lenovo V530s+ отдельно монитор Т24I | K11: 100000001345 | L11: Наклеить | N11: 1-06 первый этаж | O11: YL00STYS | P11: ="RUTL-" & RIGHT(O11,8) -> RUTL-YL00STYS | Q11: Внесены в Passwork | R11: Microsoft Office профессиональный плюс 2016 | T11: Windows 10 Pro - 22H2/19048 | V11: ULTRAVNC / MESH | W11: No Administrator rights | X11: Климанов А. | Y11: Акт 07.02.2026
A12: 10 | C12: HR_Training_PC | D12: need check | H12: HR Training | I12: Laptop | J12: Ноутбук Lenovo V130 | K12: 00000022357 | L12: инвентарник MOC наклеен | N12: HR_Room 303 | O12: R90TY3EF | P12: ="RUTL-" & RIGHT(O12,8) -> RUTL-R90TY3EF
A13: 10 | C13: HR_Training_PC | D13: need check | H13: HR Training | I13: Laptop,mouse | J13: Laptop Lenovo V110 | K13: 00000011057 | L13: инвентарник MOC наклеен | N13: HR_Room 303 | O13: R90QN4WF | P13: ="RUTL-" & RIGHT(O13,8) -> RUTL-R90QN4WF | Q13: Внесены в Passwork | R13: 2019 for home and business | S13: RGBN3-7RY3T-236WV-8MQGK-H6FRG | T13: Windows 10 Pro | U13: TWVTN-Y6PFT-WHX9Q-R3FJ9-TF4C2 | V13: ULTRAVNC / MESH | W13: No Administrator rights | X13: Лктунов А. | Y13: Акт 03.04.2026 | Z13: 43368 | AA13: БЕЗ НДС 33806,78, С НДС 39892
A14: 12 | C14: HSE_Training_PC (Акт на Волкову К.) | D14: Модернизация не требуется/normal (no need to upgrade) SSD 256 озу 8 | H14: hse_Training | I14: Laptop,mouse | J14: Laptop Lenovo V110 | K14: 00000010768 | L14: Наклеить | N14: hse обучение | O14: R90QFPY7 | P14: ="RUTL-" & RIGHT(O14,8) -> RUTL-R90QFPY7 | U14: RPDWY-7NXM3-PFC7K-FGDXQ-Y4G6P
A15: 11 | C15: Шустова Полина Сергеевна (Используется для атестации) | D15: была модернизация/upgraded (SSD 480 +RAM8) | H15: hse_Training ( для атестации) | I15: AiO, mouse, keyboard | J15: AiO Lenovo M810Z | K15: 140000174/Z000054 | L15: Инвентарник наклеен | N15: 1-09 второй этаж HSE | O15: S4FM3374 | P15: ="RUTL-" & RIGHT(O15,8) -> RUTL-S4FM3374 | V15: ULTRAVNC | Y15: Акт 07.03.2023
A16: 13 | B16: - | C16: склад MU движки | D16: need check | E16: Rus | F16: локальная учетка как у mu asse | H16: M&U, PLE | I16: Workstation, Monitor(Lenovo 19" LT 1952p Black/240000010-0002)mouse, keyboard | J16: Lenovo ThinkCenter M73((24000010)) | K16: 00000000214 | L16: инвентарник MOC наклеен | N16: СКЛАД | O16: PC017THP | P16: ="RUTL-" & RIGHT(O16,8) -> RUTL-PC017THP | Q16: Внесены в Passwork | R16: Libre office | T16: Windows 10 Pro - 22H2/19045 | U16: VK7JG-NPHTM-C97JM-9MPGT-3V66T | V16: ULTRAVNC / MESH | W16: No Administrator rights | X16: Кудрявцев Д. | Y16: Акт 20.03.2025
A17: 14 | C17: шоркин | D17: НОВЫЙ/New(no need to upgrade) | H17: M&U(MTC) | I17: WorkStation,monitor,mouse,keyboard | J17: workStation Dell D15s OptiPlex7080 SFF | K17: 10000002172 | L17: Наклеить | N17: 1-04 офис MU цеха сборки | O17: 4HBW783 | P17: ="RUTL-" & RIGHT(O17,8) -> RUTL-4HBW783
A18: 15 | C18: Доп. учётка КАРАУЛОВ акт 17.07.2024 | D18: Модернизация не требуется/normal (no need to upgrade) | H18: M&U(MTC) | I18: WorkStation,monitor,mouse,keyboard | J18: Workstation Lenovo V530s+ отдельно монитор | K18: поставить на учет | L18: Наклеить | O18: YL002URE | P18: ="RUTL-" & RIGHT(O18,8) -> RUTL-YL002URE
A19: 16 | C19: Основная и единственная учётка ГЕРАСИМОВ с правами локального администратора акт 03.09.2024 | D19: Модернизация не требуется/normal (no need to upgrade) | H19: M&U(MTC) | I19: WorkStation,monitor,mouse,keyboard | J19: Workstation Lenovo V530s+ отдельно монитор | K19: поставить на учет | L19: Наклеить | O19: YL002US1 | P19: ="RUTL-" & RIGHT(O19,8) -> RUTL-YL002US1
A20: 17 | C20: UTILITY (Щербаков Д АКТ 30-09-2020) | D20: need check | H20: M&U(MTC) (У MU в 1-13 для наладчиков) | I20: Laptop,mouse | J20: Laptop Lenovo Thinkpad L580 (C1) | K20: 14000154/Z000046 | L20: Наклеить | N20: У MU в 1-13(для наладчиков) | O20: PF12TWY1 | P20: ="RUTL-" & RIGHT(O20,8) -> RUTL-PF12TWY1 | Y20: Акт 30-09-20 | Z20: 43236 | AA20: БЕЗ НДС 41754,78, С НДС 50920,47
A21: 18 | C21: 07-10-21 принимал Корень А "Акт оформлен на Шпирный А. 07-10-2021" | D21: очень старый /old(2015-2017 г) | H21: M&U(MTC) У MU в цехе окраски 1 эт. | I21: Workstation, Monitor(Lenovo ThinkVision V9-PPHD5)mouse, keyboard | J21: Lenovo ThinkCenter M720Q | K21: поставить на учет | L21: MOSCOW | N21: У MU в цехе окраски 1 эт. | O21: PC10TT9N | P21: ="RUTL-" & RIGHT(O21,8) -> RUTL-PC10TT9N
A22: 19 | C22: Onufriev акт 12-02-2019 .\Naladchik.MU | D22: need check | H22: M&U(MTC) У MU в цехе штамповки и сварки | I22: Laptop,mouse | J22: Laptop Lenovo V510 | K22: 00000011585 | L22: инвентарник MOC наклеен | N22: У MU в цехе штамповки и сварки | O22: LR08MDC3 | P22: ="RUTL-" & RIGHT(O22,8) -> RUTL-LR08MDC3
A23: 20 | C23: технический | D23: Модернизация не требуется/normal (no need to upgrade) | H23: M&U(MTC) цеха сборки(1-04 офис MU) | I23: WorkStation,monitor,mouse,keyboard | J23: Workstation Lenovo ThinkStation P 520c | K23: 140000175/Z000059 | L23: Наклеить | N23: 1-04 офис MU цеха сборки | O23: S4FT0578 | P23: ="RUTL-" & RIGHT(O23,8) -> RUTL-S4FT0578
A24: 21 | C24: Общий, акт подписал Ершов 06-08-2024 | D24: Модернизация не требуется/normal (no need to upgrade) | H24: M&U(Utility) | I24: Laptop,mouse | J24: Laptop Lenovo V320 | K24: 140000180/Z000035 | L24: Наклеить | N24: 1-13,диспетчерская | O24: PF10LM6F | P24: ="RUTL-" & RIGHT(O24,8) -> RUTL-PF10LM6F
A25: 22 | C25: Glonass_system | D25: Модернизация не требуется/normal (no need to upgrade) | H25: MD, глонасс | I25: WorkStation,monitor Lenovo 19" LT 1952p Black/240000013-0002 | J25: PC HP 110-305nr J5M98EA/240000004 | K25: 0000000009 | L25: инвентарник MOC наклеен | N25: в цехе сборки глонасс | O25: 4CH42602VD | P25: ="RUTL-" & RIGHT(O25,10) -> RUTL-4CH42602VD
A26: 23 | C26: Технический- под Engine акт от 26,02,2025 | D26: Модернизация не требуется/normal (no need to upgrade) | H26: MD, Engine MU | I26: WorkStation,monitor(Хiaomi A22FAB-RAGL 21'9 s/n 48341/107100042303),mouse,keyboard | J26: Workstation Регард К01369/1 | K26: поставить на учет | L26: Наклеить | O26: К01369/1 | P26: ="RUTL-" & RIGHT(O26,8) -> RUTL-К01369/1
A27: 25 | C27: Ответственная Лейко Д.А. акт от 10.12.2024 на неё / PaintShiftLeaders (Настроена общая учётка) | D27: Модернизация не требуется/normal (no need to upgrade) | H27: MD, PAINT | I27: AiO, mouse, keyboard | J27: AiO Lenovo M810Z | K27: 140000157 | L27: инвентарник MOC наклеен | N27: 1-03 офис окраски 2эт | O27: S4FM3319 | P27: ="RUTL-" & RIGHT(O27,8) -> RUTL-S4FM3319
A28: 25 | C28: у PAINT в лаборатории акт на Чеснокова Елена Николаевна 14.04.2025 | D28: Модернизация не требуется/normal (no need to upgrade) ОЗУ 8 SSD 256 | H28: MD, PAINT (лаборатория окраки) | I28: Laptop,mouse | J28: Laptop Dell Latitude 3450 | K28: 140000019/Z000141 | L28: инвентарник ОС наклеен | N28: 1-03 лаборатория окраски 1 эт | O28: 99GPG22 | P28: ="RUTL-" & RIGHT(O28,8) -> RUTL-99GPG22
A29: 27 | C29: Paint_Mix_room | D29: Модернизация не требуется/normal (no need to upgrade) ОЗУ 8 SSD 256 | F29: Paint_Mix_room | H29: MD, PAINT микс рум цех окраски | I29: AiO, mouse, keyboard | J29: AiO Lenovo M810Z | K29: 140000156/Z000073 | L29: Наклеить | N29: микс рум цех окраски 1 эт | O29: S4FM3379 | P29: ="RUTL-" & RIGHT(O29,8) -> RUTL-S4FM3379
A30: 28 | C30: Ответственная Тимченко Юлия Алексеевна акт от 07.12.2024 на неё / QC.Paint (Настроена общая учётка) | D30: Модернизация не требуется/normal (no need to upgrade) | H30: MD, PAINT QT | I30: Laptop | J30: Laptop Lenovo V110 | K30: 00000011072 | L30: инвентарник MOC наклеен | M30: Внесен в ITSM AST0002164 | N30: 1-03 офис окраски 2эт | O30: R90QN4WB | P30: ="RUTL-" & RIGHT(O30,8) -> RUTL-R90QN4WB | U30: Installed Key:9Q9NM-K27Y3-D8BYW-4B997-3J3GP OEM Key:9Q9NM-K27Y3-D8BYW-4B997-3J3GP | Z30: 43368 | AA30: БЕЗ НДС 33806,78, С НДС 39892
A31: 29 | C31: акт на лейко(07-08-2023) | D31: требуется модернизация/ need to modernisation | H31: MD, PAINT QT | I31: Laptop, mouse,bag | J31: Laptop Lenovo V510 | K31: 00000015287 | L31: инвентарник MOC наклеен | N31: 1-03 офис окраски 2 эт | O31: LR0AVC2R | P31: ="RUTL-" & RIGHT(O31,8) -> RUTL-LR0AVC2R | U31: 9H9FT-NQ7VW-Q637K-V62BQ-PYT6P
A32: 30 | C32: Расписывался Ушаков Денис для общей учётки QT_SW | D32: Модернизация не требуется/normal (no need to upgrade) | E32: Rus | H32: MD, WELD | I32: Laptop, mouse,bag | J32: Laptop Lenovo V510 | K32: 00000011591 | L32: инвентарник MOC наклеен | N32: 1-02 офис цеха сварки 2 эт | O32: LR08MDC1 | P32: ="RUTL-" & RIGHT(O32,8) -> RUTL-LR08MDC1
A33: 31 | C33: акт 10-11-2022 Ушаков Денис для общей учётки QT_SW | D33: Модернизация не требуется/normal (no need to upgrade) | E33: Rus | H33: MD, WELD | I33: Laptop,mouse | J33: Laptop Lenovo Thinkpad L580 (C1) | K33: 14000142/Z000061 | L33: Наклеить | N33: 1-02 цех сварки | O33: PF12TV8F | P33: ="RUTL-" & RIGHT(O33,8) -> RUTL-PF12TV8F | Z33: 43236 | AA33: БЕЗ НДС 41754,78, С НДС 50920,47
A34: 32 | B34: 278 | C34: Сурин Сергей Валериевич/Локальная учетка Haval (расписался Чабан М) | D34: Модернизация не требуется/normal (no need to upgrade) На борту уже установлено 2 nvme+ установили ОЗУ 32 GB | E34: Rus | F34: Surin Sergey | G34: СММ инспектор | H34: MD, WELD | I34: Laptop,mouse | J34: Lenovo ThinkPad X1 | K34: 140000212 | L34: инвентарник ОС наклеен | M34: Внесен в ITSM AST0000628 | N34: 1-02 камера 3д измерений | O34: R90RVMF6 | P34: ="RUTL-" & RIGHT(O34,8) -> RUTL-R90RVMF6 | R34: Microsoft Office профессиональный плюс 2016 | T34: MS Windows 10 Prof | V34: ULTRAVNC / MESH | W34: No Administrator rights | X34: Летунов А. | Y34: Акт 05.12.2025
A35: 32 | B35: 278 | C35: Сурин Сергей Валериевич/Локальная учетка СММ | D35: Модернизация не требуется/normal (no need to upgrade) На борту уже установлено 2 nvme+ установили ОЗУ 32 GB | E35: Rus | F35: Surin Sergey | G35: СММ инспектор | H35: MD, WELD | I35: Laptop,mouse | J35: MSI Modern 15 F1MG-800XRU | K35: поставить на учет | L35: Наклеить | O35: C2507N0002622 | P35: ="RUTL-" & RIGHT(O35,8) -> RUTL-N0002622 | R35: Libre Office/ Only Office | T35: MS Windows 11 Prof | U35: GVR9N-KKY87-2XF9T-2KBJY-BBH22 | V35: ULTRAVNC / MESH | W35: Admin | X35: Летунов А. | Y35: Акт 03.04.2026 | Z35: Тендер 28.11.2025
A36: 33 | B36: 9003 | C36: Ермолаева Майя Андреевна / Общая учётная запись storekepers | D36: была модернизация/upgraded | E36: Rus | G36: Кладовщик | H36: PLD, WL складская логистика (Storekeepers) | I36: AiO, mouse, keyboard | J36: AiO Lenovo M810Z | K36: 140000154/Z000071 | L36: Наклеить | N36: 1-06 комната кладовщиков | O36: S4FM3305 | P36: ="RUTL-" & RIGHT(O36,8) -> RUTL-S4FM3305 | Q36: Внесены в Passwork | U36: NPM9X-GF7DT-4QFX6-BWQ6Y-2PQGP | V36: ULTRAVNC | X36: Климанов А.
A37: 34 | B37: 12918 12926 | C37: логистика акт 03-06-2021 Выдан акт Ворониной Наталье 12.11.2024/ Быцкевич Оксана Викторовна Хороших Наталья Викторовна Бородкина Лидия Дмитриевна акт 27.02.2026 Лапина Каролина Евгеньевна акт 27.02.2026 | D37: no need to upgrade | E37: Rus | H37: PLD, WL складская логистика (Storekeepers) | I37: Workstation,keyboard,monitor | J37: Workstation Lenovo V50T+ отдельно монитор Samsung S24F | K37: 100000001588 | L37: Наклеить | N37: 1-06 первый этаж | O37: PC1SQYHA | P37: ="RUTL-" & RIGHT(O37,8) -> RUTL-PC1SQYHA | Q37: Внесены в Passwork | R37: 2019 for home and business | S37: NV8DJ-DRFMJ-DD4QY-RHR69-QV8FG | T37: Windows 10 Pro - 22H2/19045 | V37: ULTRAVNC / MESH | W37: No Administrator rights | X37: Летунов А. Кудрявцев Д. | Y37: Акт 28,11,2025 Акт 27.02.2026
A38: 35 | C38: логистика акт 03-06-2021 | D38: no need to upgrade | E38: Rus | H38: PLD, WL складская логистика (Storekeepers) | I38: Workstation,keyboard,monitor | J38: Workstation Lenovo V50T+ отдельно монитор Samsung S24F | K38: 100000001589 | L38: Наклеить | N38: 1-06 первый этаж | O38: PC1SQYHK | P38: ="RUTL-" & RIGHT(O38,8) -> RUTL-PC1SQYHK | R38: 2019 for home and business | S38: B3R9N-TXWQ2-XGHCW-XX96F-F62YT | T38: Windows 10 Pro - 22H2/19045
A39: 36 | C39: логистика акт 03-06-2021 | D39: no need to upgrade | E39: Rus | H39: PLD, WL складская логистика (Storekeepers) | I39: Workstation,keyboard,monitor | J39: Workstation Lenovo V50T+ отдельно монитор Samsung S24F | K39: 100000001591 | L39: Наклеить | N39: 1-06 первый этаж | O39: PC1SQYHN | P39: ="RUTL-" & RIGHT(O39,8) -> RUTL-PC1SQYHN | R39: 2019 for home and business | S39: TNPMT-6RQ9V-QVQGV-YFWHP-6JHH6 | T39: Windows 10 Pro - 22H2/19045
A40: 37 | C40: логистика акт 03-06-2021 | D40: no need to upgrade | E40: Rus | H40: PLD, WL складская логистика (Storekeepers) | I40: Workstation,keyboard,monitor | J40: Workstation Lenovo V50T+ отдельно монитор Samsung S24F | K40: 100000001590 | L40: Наклеить | N40: 1-06 первый этаж | O40: PC1SQYHQ | P40: ="RUTL-" & RIGHT(O40,8) -> RUTL-PC1SQYHQ | R40: 2019 for home and business | S40: DKM9N-KBGMM-RPWF8-6T4T2-3YKBT | T40: Windows 10 Pro - 22H2/19045
A41: 38 | C41: логистика акт 03-06-2021 (Рязанцев К.С.) | D41: no need to upgrade | E41: Rus | H41: PLD, WL складская логистика (Storekeepers) | I41: Workstation,keyboard,monitor | J41: Workstation Lenovo V50T+ отдельно монитор Samsung S24F | K41: 100000001585 | L41: Наклеить | N41: 1-06 первый этаж | O41: PC1SQYHV | P41: ="RUTL-" & RIGHT(O41,8) -> RUTL-PC1SQYHV | R41: 2019 for home and business | S41: Y9QCX-JN9X2-JTV8D-H7GMK-TF6MT | T41: Windows 10 Pro - 22H2/19045
A42: 39 | C42: логистика акт 03-06-2021 (Рязанцев К.С.)/ Подселен Воробьева Елена Николаевна Кладовщик | D42: no need to upgrade | E42: Rus | H42: PLD, WL складская логистика (Storekeepers) | I42: Workstation,keyboard,monitor | J42: Workstation Lenovo V50T+ отдельно монитор Samsung S24F | K42: 100000001587 | L42: Наклеить | N42: 1-06 первый этаж | O42: PC1SQYJR | P42: ="RUTL-" & RIGHT(O42,8) -> RUTL-PC1SQYJR | R42: 2019 for home and business | S42: NBJBH-8YTHB-6DJ34-Q64J4-BY7H6 | T42: Windows 10 Pro - 22H2/19045 | V42: ULTRAVNC / MESH | W42: No Administrator rights | X42: Летунов А. | Y42: Акт 28,11,2025
A43: 40 | C43: логистика акт 03-06-2021 (Рязанцев К.С.) | D43: no need to upgrade | E43: Rus | H43: PLD, WL складская логистика (Storekeepers) | I43: Workstation,keyboard,monitor | J43: Workstation Lenovo V50T+ отдельно монитор Samsung S24F | K43: 100000001584 | L43: Наклеить | N43: 1-06 первый этаж | O43: PC1SQYJW | P43: ="RUTL-" & RIGHT(O43,8) -> RUTL-PC1SQYJW | R43: 2019 for home and business | S43: MRJVN-7H2TD-7TH8K-2WWX8-BWTMT | T43: Windows 10 Pro - 22H2/19045
A44: 41 | C44: логистика акт 03-06-2021 (Рязанцев К.С.), использует Савленков В. | D44: no need to upgrade | E44: Rus | H44: PLD, WL складская логистика (Storekeepers) | I44: Workstation,keyboard,monitor | J44: Workstation Lenovo V50T+ отдельно монитор Samsung S24F | K44: 100000001586 | L44: Наклеить | N44: 1-06 первый этаж | O44: PC1SQYJX | P44: ="RUTL-" & RIGHT(O44,8) -> RUTL-PC1SQYJX | R44: 2019 for home and business | S44: TY829-NWGQF-82FJG-BVBW6-RRJFG | T44: Windows 10 Pro - 22H2/19045
A45: 42 | C45: логистика акт 03-06-2021 | D45: no need to upgrade | E45: Rus | H45: PLD, WL складская логистика (Storekeepers) | I45: Workstation,keyboard,monitor | J45: Workstation Lenovo V50T+ отдельно монитор Samsung S24F | K45: 100000001592 | L45: Наклеить | N45: 1-06 первый этаж | O45: PC1SQYK7 | P45: ="RUTL-" & RIGHT(O45,8) -> RUTL-PC1SQYK7 | R45: 2016 for home and business | S45: XGWNH-DFD9K-7JJFC-QT26M-43M4G | T45: Windows 10 Pro - 22H2/19045
A46: 43 | C46: логистика акт 03-06-2021 | D46: no need to upgrade | E46: Rus | H46: PLD, WL складская логистика (Storekeepers) | I46: Workstation,keyboard,monitor | J46: Workstation Lenovo V50T+ отдельно монитор Samsung S24F | K46: 100000001593 | L46: инвентарник MOC наклеен | N46: 1-06 первый этаж | O46: PC1SQYHH | P46: ="RUTL-" & RIGHT(O46,8) -> RUTL-PC1SQYHH | R46: 2019 for home and business | S46: NGQTG-PTWKP-CMG84-G99HC-P9Y4G | T46: Windows 10 Pro - 22H2/19045 | V46: ULTRAVNC | Y46: Акт 07.10.2021
A47: 44 | C47: Для Storkeepers (акт на Воронину Н.) | D47: no need to upgrade | E47: Rus | G47: общий технический | H47: PLD, WL складская логистика (Storekeepers) | I47: AiO, mouse, keyboard | J47: AiO Lenovo S400Z | K47: 140000047/Z000124 | L47: Наклеить | N47: СКЛАД | O47: P901FSPC | P47: ="RUTL-" & RIGHT(O47,8) -> RUTL-P901FSPC | Q47: Внесены в Passwork | T47: Windows 10 Pro - 22H2/19048 | V47: ULTRAVNC / MESH | W47: No Administrator rights | X47: Мартынов Д. | Y47: Акт 11.02.2026
A48: 46 | C48: Для Storkeepers (акт на Воронину Н.) | D48: Модернизация не требуется/normal (no need to upgrade) | E48: Rus | G48: Storekeepers | H48: PLD, WL складская логистика (Storekeepers) | I48: AiO, mouse, keyboard | J48: AiO Lenovo S400Z | K48: 150000021/Z000003 | L48: Наклеить | N48: 1-09 второй этаж | O48: P901FSLQ | P48: ="RUTL-" & RIGHT(O48,8) -> RUTL-P901FSLQ | Q48: Внесены в Passwork | U48: HVNTR-6PK7H-3H3HQ-DG9TV-VT92P | V48: ULTRAVNC / MESH | X48: Климанов А. | Y48: Акт 17.02.2026
A49: 45 | C49: Monitoring QI (512 ГБ и 12 ГБ ) Акты на Геворкян Максим и Иванов Дмитрий | D49: Модернизация не требуется/normal (no need to upgrade) | E49: Rus | H49: R&D, Q&T, QI | I49: Laptop, mouse,bag + usb keyboard | J49: Laptop Lenovo V 130 | K49: 00000019367(5) | L49: инвентарник MOC наклеен | N49: 1-04 напротив светового тонеля | O49: R90T947V | P49: ="RUTL-" & RIGHT(O49,8) -> RUTL-R90T947V | U49: KVNRK-GYTQD-8YH44-BYKM4-R3KTP
A50: 46 | C50: Для Storkeepers (акт на Кочеткову М.) | D50: Модернизация не требуется/normal (no need to upgrade) | E50: Rus | G50: Storekeepers | H50: PLD, WL складская логистика (Storekeepers) | I50: AiO, mouse, keyboard | J50: AiO Lenovo M810Z | K50: 140000139/Z000051 | L50: Инвентарник наклеен | N50: 1-07 четвертый этаж | O50: S4FM3370 | P50: ="RUTL-" & RIGHT(O50,8) -> RUTL-S4FM3370 | Q50: Внесены в Passwork | R50: Professional Plus 2019 | S50: ND9DW-GMRDT-Q2KP9-F3PRF-6Q9GG | T50: Windows 10 Pro | U50: Y9N99-HD2J4-T2XMY-C9WJB-CWF9C | V50: ULTRAVNC / MESH | W50: No Administrator rights | X50: Мартынов Д. | Y50: Акт 13.03.2026
A51: 47 | C51: Для Storkeepers (акт на Кочеткову М.) | D51: Модернизация не требуется/normal (no need to upgrade) | E51: Rus | G51: Storekeepers | H51: PLD, WL складская логистика (Storekeepers) | I51: AiO, mouse, keyboard | J51: AiO Lenovo M810Z | K51: 140000147/Z000093 | L51: Наклеить | N51: 1-03 склад цех окраски 1 этаж | O51: S4FM3405 | P51: ="RUTL-" & RIGHT(O51,8) -> RUTL-S4FM3405 | Q51: Внесены в Passwork | T51: Windows 10 Pro | V51: ULTRAVNC / MESH | W51: No Administrator rights | X51: Мартынов Д. | Y51: Акт 13.03.2026
A52: 48 | C52: после Трегубова Яна | D52: Модернизация не требуется/normal (no need to upgrade) | E52: Rus | F52: Tregubova Yana | G52: Технический для FD | H52: FD, ACC | I52: AiO, mouse, keyboard | J52: AiO Dell Inspiron 5400 | K52: 100000001674 | L52: Наклеить | N52: 1-07 третий этаж FD | O52: 7M4HDF2 | P52: ="RUTL-" & RIGHT(O52,8) -> RUTL-7M4HDF2 | Q52: Внесены в Passwork | R52: 2016 for home and business (BOX) | T52: Windows 10 Pro | U52: 9NDHD-XH4XJ-J2TJ2-M88GC-KW3FC | V52: ULTRAVNC / MESH | W52: No Administrator rights | X52: Летунов А. | Y52: Акт 12.03.2026 | Z52: 44551 | AA52: без НДС 71 583,33 с НДС 85 900
A53: 49 | C53: HMMR_Construction_site (акт на Зорина С) | D53: Модернизация не требуется/normal (no need to upgrade) | E53: Rus | F53: HMMR_Construction_site | G53: Для работы с чертежами в строй городке | H53: GD, CONSTR | I53: Workstation, Монитор ThinkVision T2454p | J53: Workstation Lenovo ThinkStation P310 | K53: 150000013/Z000117 | L53: Наклеить | N53: строительный городок | O53: S4AA3128 | P53: ="RUTL-" & RIGHT(O53,8) -> RUTL-S4AA3128 | Q53: Внесены в Passwork | R53: Professional Plus 2019 | S53: PJYRN-89X82-BXK73-YGRVQ-DV8J6 | T53: Windows 10 Pro | U53: GV6KN-VKH9H-BBHG2-4J27T-23782 | V53: ULTRAVNC / MESH | W53: No Administrator rights | X53: Кудрявцев Д. | Y53: Акт 16.03.2026 на Зорина Сергея
A54: 50 | C54: Технический- под Engine акт от 17,03,2026 на фатина c | D54: Модернизация не требуется/normal (no need to upgrade) | E54: Rus | H54: ES, ES Q&T, ES QTM | I54: WorkStation,monitor,mouse,keyboard | J54: Workstation,monitor Xiaomi a24i SN: 54383/250100058479 | O54: K01274/34 | P54: ="RUTL-" & RIGHT(O54,8) -> RUTL-01274/34 | V54: ULTRAVNC / MESH | W54: No Administrator rights | X54: Мартынов Д. | Y54: Акт 17.03.2026

Sheet Склад, ремонт, ожидающие
A1: 0 | G1: На складе
A2: № | B2: Табельный номер / Employee ID | C2: Физлицо / Owner | D2: История модернизаций, ремонтов / Modernisation, repairing history | E2: Тип домена / Domain Type | F2: Имя на английском / English name | G2: Должность / Position (Rus / Eng) | H2: Отдел / Department | I2: Комплектация / Equipment | J2: Тип и модель ПК / PC type and model | K2: Инвентарный номер / Inventory number | L2: Инвентарный номер наклеен? / Is the inventory number affixed? | M2: где хранится информация о компе | N2: Местоположение / Location | O2: Серийный номер / Serial Number | P2: Имя компьютера / PC Domain Name | Q2: TeamPass, Passwork? | R2: Тип ПО офис / Office type | S2: Ключ офиса / License key Office | T2: ОС тип / OS Type | U2: Ключ ОС / Key OS | V2: ПО удалённого управления / Remote control | W2: Админ права / Admin permissions | X2: Кто подготовил / Who installed | Y2: Дата выдачи / Issue Date | Z2: Дата покупки / Purchasing Date | AA2: Примечание / Comment
A3: 1 | C3: по тендеру RDD новые без офиса | D3: Модернизация не требуется/normal (no need to upgrade) | E3: Rus | I3: Laptop | J3: Laptop MSI Modern 15 F1MG-800XRU | K3: поставить на учет | L3: Наклеить | N3: СКЛАД BSS | O3: C2507N0002756 | P3: ="RUTL-" & RIGHT(O3,8) -> RUTL-N0002756 | W3: No Administrator rights | X3: Летунов А. | Z3: 45987 | AA3: Стоимость ПК без НДС 59 160руб
A4: =A3+1 -> 2 | C4: по тендеру RDD новые без офиса | D4: Модернизация не требуется/normal (no need to upgrade) | E4: Rus | I4: Laptop | J4: Laptop MSI Modern 15 F1MG-800XRU | K4: поставить на учет | L4: Наклеить | N4: СКЛАД BSS | O4: C2507N0002947 | P4: ="RUTL-" & RIGHT(O4,8) -> RUTL-N0002947 | AA4: Стоимость ПК без НДС 59 160руб
A5: =A4+1 -> 3 | C5: по тендеру RDD новые без офиса | D5: Модернизация не требуется/normal (no need to upgrade) | E5: Rus | I5: Laptop | J5: Laptop MSI Modern 15 F1MG-800XRU | K5: поставить на учет | L5: Наклеить | N5: СКЛАД BSS | O5: C2507N0002757 | P5: ="RUTL-" & RIGHT(O5,8) -> RUTL-N0002757 | AA5: Стоимость ПК без НДС 59 160руб
A6: =A5+1 -> 4 | C6: по тендеру RDD новые без офиса | D6: Модернизация не требуется/normal (no need to upgrade) | E6: Rus | I6: Laptop | J6: Laptop MSI Modern 15 F1MG-800XRU | K6: поставить на учет | L6: Наклеить | N6: СКЛАД BSS | O6: C2507N0002820 | P6: ="RUTL-" & RIGHT(O6,8) -> RUTL-N0002820 | AA6: Стоимость ПК без НДС 59 160руб
A7: =A6+1 -> 5 | C7: по тендеру RDD новые без офиса | D7: Модернизация не требуется/normal (no need to upgrade) | E7: Rus | I7: Laptop | J7: Laptop MSI Modern 15 F1MG-800XRU | K7: поставить на учет | L7: Наклеить | N7: СКЛАД BSS | O7: C2507N0002775 | P7: ="RUTL-" & RIGHT(O7,8) -> RUTL-N0002775 | AA7: Стоимость ПК без НДС 59 160руб
A8: =A7+1 -> 6 | C8: по тендеру RDD новые без офиса | D8: Модернизация не требуется/normal (no need to upgrade) | E8: Rus | I8: Laptop | J8: Laptop MSI Modern 15 F1MG-800XRU | K8: поставить на учет | L8: Наклеить | N8: СКЛАД BSS | O8: C2507N0002749 | P8: ="RUTL-" & RIGHT(O8,8) -> RUTL-N0002749 | AA8: Стоимость ПК без НДС 59 160руб
A9: =A8+1 -> 7 | C9: по тендеру RDD новые без офиса | D9: Модернизация не требуется/normal (no need to upgrade) | E9: Rus | I9: Laptop | J9: Laptop MSI Modern 15 F1MG-800XRU | K9: поставить на учет | L9: Наклеить | N9: СКЛАД BSS | O9: C2507N0002774 | P9: ="RUTL-" & RIGHT(O9,8) -> RUTL-N0002774 | AA9: Стоимость ПК без НДС 59 160руб
A10: =A9+1 -> 8 | C10: по тендеру RDD новые без офиса | D10: Модернизация не требуется/normal (no need to upgrade) | E10: Rus | I10: Laptop | J10: Laptop MSI Modern 15 F1MG-800XRU | K10: поставить на учет | L10: Наклеить | N10: СКЛАД BSS | O10: C2507N0002598 | P10: ="RUTL-" & RIGHT(O10,8) -> RUTL-N0002598 | AA10: Стоимость ПК без НДС 59 160руб
A11: =A10+1 -> 9 | C11: по тендеру RDD новые без офиса | D11: Модернизация не требуется/normal (no need to upgrade) | E11: Rus | I11: Laptop | J11: Laptop MSI Modern 15 F1MG-800XRU | K11: поставить на учет | L11: Наклеить | N11: СКЛАД BSS | O11: C2507N0002850 | P11: ="RUTL-" & RIGHT(O11,8) -> RUTL-N0002850 | AA11: Стоимость ПК без НДС 59 160руб
A12: 1 | C12: по тендеру RDD новые с офисом ( проверить по реестру поставок) | D12: Модернизация не требуется/normal (no need to upgrade) | E12: Rus | I12: Laptop | J12: Laptop MSI Modern 15 F1MG-800XRU | K12: поставить на учет | L12: Наклеить | N12: СКЛАД BSS | O12: C2509N0008343 | P12: ="RUTL-" & RIGHT(O12,8) -> RUTL-N0008343 | AA12: Стоимость ПК без НДС 59 160руб
A13: 2 | C13: по тендеру RDD новые с офисом ( проверить по реестру поставок) | D13: Модернизация не требуется/normal (no need to upgrade) | E13: Rus | I13: Laptop | J13: Laptop MSI Modern 15 F1MG-800XRU | K13: поставить на учет | L13: Наклеить | N13: СКЛАД BSS | O13: C2507N0002908 | P13: ="RUTL-" & RIGHT(O13,8) -> RUTL-N0002908 | AA13: Стоимость ПК без НДС 59 160руб
A14: =A13+1 -> 3 | C14: по тендеру RDD новые с офисом ( проверить по реестру поставок) | D14: Модернизация не требуется/normal (no need to upgrade) | E14: Rus | I14: Laptop | J14: Laptop MSI Modern 15 F1MG-800XRU | K14: поставить на учет | L14: Наклеить | N14: СКЛАД BSS | O14: C2507N0002550 | P14: ="RUTL-" & RIGHT(O14,8) -> RUTL-N0002550 | AA14: Стоимость ПК без НДС 59 160руб
A15: =A14+1 -> 4 | C15: по тендеру RDD новые с офисом ( проверить по реестру поставок) | D15: Модернизация не требуется/normal (no need to upgrade) | E15: Rus | I15: Laptop | J15: Laptop MSI Modern 15 F1MG-800XRU | K15: поставить на учет | L15: Наклеить | N15: СКЛАД BSS | O15: C2509N0008367 | P15: ="RUTL-" & RIGHT(O15,8) -> RUTL-N0008367 | AA15: Стоимость ПК без НДС 59 160руб
A16: =A15+1 -> 5 | C16: по тендеру RDD новые с офисом ( проверить по реестру поставок) | D16: Модернизация не требуется/normal (no need to upgrade) | E16: Rus | I16: Laptop | J16: Laptop MSI Modern 15 F1MG-800XRU | K16: поставить на учет | L16: Наклеить | N16: СКЛАД BSS | O16: C2509N0008349 | P16: ="RUTL-" & RIGHT(O16,8) -> RUTL-N0008349 | AA16: Стоимость ПК без НДС 59 160руб
A17: =A16+1 -> 6 | C17: по тендеру RDD новые с офисом ( проверить по реестру поставок) | D17: Модернизация не требуется/normal (no need to upgrade) | E17: Rus | I17: Laptop | J17: Laptop MSI Modern 15 F1MG-800XRU | K17: поставить на учет | L17: Наклеить | N17: СКЛАД BSS | O17: C2509N0008364 | P17: ="RUTL-" & RIGHT(O17,8) -> RUTL-N0008364 | AA17: Стоимость ПК без НДС 59 160руб
A18: =A17+1 -> 7 | C18: по тендеру RDD новые с офисом ( проверить по реестру поставок) | D18: Модернизация не требуется/normal (no need to upgrade) | E18: Rus | I18: Laptop | J18: Laptop MSI Modern 15 F1MG-800XRU | K18: поставить на учет | L18: Наклеить | N18: СКЛАД BSS | O18: C2507N0002866 | P18: ="RUTL-" & RIGHT(O18,8) -> RUTL-N0002866 | AA18: Стоимость ПК без НДС 59 160руб
A19: =A18+1 -> 8 | C19: по тендеру RDD новые с офисом ( проверить по реестру поставок) | D19: Модернизация не требуется/normal (no need to upgrade) | E19: Rus | I19: Laptop | J19: Laptop MSI Modern 15 F1MG-800XRU | K19: поставить на учет | L19: Наклеить | N19: СКЛАД BSS | O19: C2509N0008359 | P19: ="RUTL-" & RIGHT(O19,8) -> RUTL-N0008359 | AA19: Стоимость ПК без НДС 59 160руб
A20: =A19+1 -> 9 | C20: по тендеру RDD новые с офисом ( проверить по реестру поставок) | D20: Модернизация не требуется/normal (no need to upgrade) | E20: Rus | I20: Laptop | J20: Laptop MSI Modern 15 F1MG-800XRU | K20: поставить на учет | L20: Наклеить | N20: СКЛАД BSS | O20: C2509N0008337 | P20: ="RUTL-" & RIGHT(O20,8) -> RUTL-N0008337 | AA20: Стоимость ПК без НДС 59 160руб
A21: 1 | C21: РЕЗЕРВ SEC ПОД СПЕЦИАЛИСТА SEC (бронь за подразделением) | D21: Модернизация не требуется/normal (no need to upgrade) | E21: Rus | H21: GD, SEC, ISG | I21: WorkStation,monitor,mouse,keyboard | J21: Workstation Lenovo Legion R5 | K21: 10000001761 | L21: Наклеить | N21: СКЛАД | O21: S1019GMA | P21: ="RUTL-" & RIGHT(O21,8) -> RUTL-S1019GMA | V21: ULTRAVNC | Y21: Акт 31.12.2020
A22: 2 | B22: Окраска Резерв | C22: резерв за окраской | D22: была модернизация/upgraded (SSD 480, 8 ОЗУ) | E22: Rus | F22: Zaderenko Victoria | H22: MD, PAINT | I22: Laptop,mouse | J22: Laptop Lenovo t440p | K22: поставить на учет | L22: МОСКВА | N22: 1-07 четвертый этаж | O22: PC00V9QJ | P22: ="RUTL-" & RIGHT(O22,8) -> RUTL-PC00V9QJ | R22: 2019 for home and business | S22: KTQN4-9FGT2-RRWJ6-8PWRY-MY7H6 | T22: Windows 10 Pro | U22: VK7JG-NPHTM-C97JM-9MPGT-3V66T | V22: ULTRAVNC / MESH | W22: No Administrator rights | X22: Летунов А. | Y22: Акт 14.02.2026
A23: 7 | B23: - | C23: для студентов | D23: Модернизация не требуется/normal (no need to upgrade) | E23: Rus | H23: NOBO_1 | I23: Laptop, mouse | J23: laptop HP ProBook455/240000003 | K23: 0000000469 | L23: инвентарник MOC наклеен | N23: 1-07 третий этаж | O23: CND4434S0B | P23: ="RUTL-" & RIGHT(O23,8) -> RUTL-D4434S0B | Q23: Внесены в Passwork | R23: 2019 for home and business | S23: XQC3V-D7NHY-DHBY2-YDBYK-XKY4G | T23: Windows 10 Pro | U23: QH947-TJN7R-K46Y8-DC7VW-6MRYC | V23: ULTRAVNC / MESH | W23: No Administrator rights | X23: Кудрявцев Д. | Y23: Акт 22.01.2026
A24: 3 | B24: РЕЗЕРВ ИТ | C24: РЕЗЕРВ ИТ | D24: Модернизация не требуется/normal (no need to upgrade) | E24: Rus | I24: Laptop, mouse, bag | J24: Laptop Lenovo ThinkBook 15 G4 IAP | K24: 100000003384 | N24: СКЛАД | O24: MP2HBY6H | P24: ="RUTL-" & RIGHT(O24,8) -> RUTL-MP2HBY6H | V24: ULTRAVNC | W24: admin?? | X24: иванов к | Y24: Акт 26.04.2024
A25: 4 | B25: РЕЗЕРВ ИТ | C25: РЕЗЕРВ ИТ | D25: Модернизация не требуется/normal (no need to upgrade) | E25: Rus | F25: Faizullin Marat | G25: Руководитель отдела | H25: FD(OMD, INVEST) | I25: Laptop, mouse, bag | J25: Laptop Lenovo ThinkBook 15 G4 IAP | K25: 100000003388 | L25: Наклеить | N25: 1-07 третий этаж | O25: MP2HBY5J | P25: ="RUTL-" & RIGHT(O25,8) -> RUTL-MP2HBY5J | Q25: Внесены в Passwork | R25: Libre Office / Only office | T25: Windows 10 Pro | V25: ULTRAVNC / MESH | X25: Летунов А. | Y25: Акт 29.11.2025
A26: 5 | B26: РЕЗЕРВ ИТ | C26: РЕЗЕРВ на перераспределение общежития | D26: Модернизация не требуется/normal (no need to upgrade) | E26: Rus | H26: GD, GA, | I26: AiO, mouse, keyboard | J26: AIO Lenovo ThinkCentre M73z | K26: 140000038/Z000020 | L26: Наклеить | N26: СКЛАД | O26: S1H03BRZ | P26: ="RUTL-" & RIGHT(O26,8) -> RUTL-S1H03BRZ | Q26: Внесены в Passwork | V26: ULTRAVNC / MESH | X26: Климанов А. | Y26: Акт 15.12.2025 | AA26: Норм
A27: 6 | B27: РЕЗЕРВ ИТ | C27: РЕЗЕРВ на перераспределение общежития | D27: поставить оперативную память | E27: Rus | H27: GD, GA, | I27: AiO, mouse, keyboard | J27: AIO Lenovo ThinkCentre M73z | K27: 140000045/Z000016 | L27: Наклеить | N27: СКЛАД | O27: S1H03BQD | P27: ="RUTL-" & RIGHT(O27,8) -> RUTL-S1H03BQD | AA27: Норм
A28: 8 | B28: ДЛЯ НАСТРОЙКИ | C28: отдать на перераспределение или в новые цех | D28: Модернизация не требуется/normal (no need to upgrade) | E28: Rus | H28: RDC | I28: Workstation+monitor | J28: Компьтер Thinkstation P520 Intel Xeon W-2104 | K28: 140000191 | L28: инвентарник ОС наклеен | N28: 1-07 второй этаж | O28: S4HP0649 | P28: ="RUTL-" & RIGHT(O28,8) -> RUTL-S4HP0649 | Q28: Внесены в Passwork
A29: 9 | B29: ДЛЯ НАСТРОЙКИ | C29: отдать на перераспределение в новые цех (ГОТОВ пользователю) | D29: Модернизация не требуется/normal (no need to upgrade) | E29: Rus | I29: WorkStation,monitor s24e,mouse,keyboard | J29: Workstation LENOVO ThinkStation P330 | K29: 140000240 | L29: инвентарник ОС наклеен | N29: СКЛАД | O29: PC0ZVQPT | P29: ="RUTL-" & RIGHT(O29,8) -> RUTL-PC0ZVQPT | Q29: Внесены в Passwork | R29: Libre office | V29: ULTRAVNC / MESH | W29: ADMIN | X29: - /Летунов А. | Y29: Акт 25.11.2024 / Акт 30.10.2025
A30: 10 | B30: ДЛЯ НАСТРОЙКИ | C30: после Яничкина Татьяна Анатольевна | D30: Модернизация не требуется/normal (no need to upgrade) | E30: Rus | F30: Yanichkina Tatyana | G30: Руководитель группы | H30: OMD, DM | I30: WorkStation,monitor,mouse,keyboard | J30: Workstation Lenovo ThinkStation P 320 | K30: 140000244 | L30: инвентарник ОС наклеен | N30: 1-06 первый этаж | O30: PC10AS8Z | P30: ="RUTL-" & RIGHT(O30,8) -> RUTL-PC10AS8Z | Q30: Внесены в Passwork | T30: Windows 10 Pro | U30: 9GN83-C9YWQ-MR4YG-VD8F4-369TP | V30: ULTRAVNC
A31: 19 | C31: Канунникова Юлия Олеговна (БЫЛ ирбис на ремонт по гарантии 13-02-2026, отказ в ремонта, прислана замена CBR AIO) ЗАПОЛНИТЬ! | D31: Отправили на ремонт по гарантии 13-02-2026, отказ Прислали замену 06.04.2026 МОНОБЛОК CBR | E31: Rus | F31: Kanunnikova Yulia | G31: Специалист по персоналу | H31: HRD, DP, HR DATA | I31: AiO, mouse, keyboard | J31: AiO БЫЛ Irbis Smart MB2389 СТАЛ CBR | K31: поставить на учет | L31: Наклеить | N31: 1-07 третий этаж | O31: БЫЛ 2408A22H124i5M2165R00347 СТАЛ | P31: БЫЛ RUTL-65R00347 СТАЛ | Q31: Внесены в Passwork | R31: Professional Plus 2019 | V31: ULTRAVNC / MESH | X31: Летунов А. | Y31: Акт 07.05.2025
A32: 14 | B32: должны вернуть | C32: Котова Яна Игоревна ( 14881 ) | D32: Модернизация не требуется/normal (no need to upgrade) | E32: Rus | F32: Kotova Yana | G32: Специалист по оборудованию | H32: NOBO, MTC | I32: Laptop,mouse | J32: Laptop Acer Extensa 15 | K32: 100000003367 | L32: Наклеить | N32: 1-02 офис MU цеха сварки | O32: NXEGYER00H320088FC3400 | P32: ="RUTL-" & RIGHT(O32,8) -> RUTL-88FC3400 | Q32: Внесены в Passwork | R32: Professional Plus 2019 | S32: 6HR2P-NR9K3-69WT8-7BKPW-9TQ21 | T32: Windows 10 Pro | U32: HJTRQ-N2HV4-DPRQ3-Y32WR-PPQGP | V32: ULTRAVNC / MESH | W32: No Administrator rights | X32: Климанов А. | Y32: Акт 12.03.2026 | Z32: 2024 | AA32: БЕЗ НДС 60440.50
A33: ='ПК с 1 владельцем'!A251+1 -> #REF! | B33: 5075 | C33: Никитин Евгений | D33: Модернизация не требуется/normal (no need to upgrade) | E33: Rus | F33: Nikitin Evgeniy | G33: Начальник участка | H33: CH | I33: Laptop, mouse,bag | J33: Laptop Lenovo V 130 | K33: 00000019366(16) | L33: инвентарник MOC наклеен | N33: 1-07 третий этаж | O33: R90SRSGR | P33: ="RUTL-" & RIGHT(O33,8) -> RUTL-R90SRSGR | Q33: Внесены в Passwork | T33: Windows 10 Pro | U33: JNTQY-V8V9C-DTBKY-K4K3X-C7JXC | V33: ULTRAVNC / MESH | X33: Мелёшкин С. | Y33: Акт 19.03.2026 | Z33: 43661
A34: 15 | B34: Леша Л | C34: ЛЕША после Иванова Анна Викторовна ( Юдиной Ю на замену) | D34: Модернизация не требуется/normal (no need to upgrade) | E34: Rus | G34: Бухгалтер 3 категории | H34: FD, ACC | I34: AiO, mouse, keyboard | J34: AiO Dell Inspiron 5400 | K34: 100000001688 | L34: Наклеить | N34: 1-07 третий этаж FD | O34: 7K4HDF2 | P34: ="RUTL-" & RIGHT(O34,8) -> RUTL-7K4HDF2 | Q34: Внесены в Passwork | R34: 2016 for home and business (BOX) | U34: Q6Q74-FGNWF-2BGQG-6TXCW-2GYMP | V34: ULTRAVNC | Y34: Акт 02.03.2022 | Z34: 44551 | AA34: без НДС 71 583,33 с НДС 85 900
A35: 16 | B35: Леша Л | C35: после Ветчинкина Лариса Владимировна на Михалева Елена Владимировна | D35: Модернизация не требуется/normal (no need to upgrade) | E35: Rus | I35: Laptop, mouse, bag, переходник DIGMA | J35: Laptop IRBIS 17NBP4502 | K35: поставить на учет | L35: Наклеить | N35: 1-09 второй этаж | O35: F2717NBP4502103177 | P35: ="RUTL-" & RIGHT(O35,8) -> RUTL-02103177 | Q35: Внесены в Passwork | R35: MS Office Home & Business 2019 MASSGRAVE | T35: Windows 10 Pro | U35: X868N-JCM72-9PGYT-Q3JQW-4VV22 | V35: ULTRAVNC / MESH | X35: Мартынов Д. | Y35: Акт 06.02.2025
A36: 21 | C36: Светличная Алина Сергеевна | D36: Модернизация не требуется/normal (no need to upgrade) | E36: Rus | F36: Svetlichnaya Alina | G36: Специалист по подбору персонала | H36: HRD, REC, WC REC | I36: Laptop,mouse | J36: Laptop IRBIS 15NBP3506 | K36: 100000003613 | L36: Наклеить | N36: 1-07 третий этаж HR | O36: F2715NBP35060820616 | P36: ="RUTL-" & RIGHT(O36,8) -> RUTL-60820616 | Q36: Внесены в Passwork | R36: Libre office | T36: Windows 10 Pro | V36: ULTRAVNC / MESH | W36: No Administrator rights | X36: Климанов А. | Y36: Акт 04.08.2025
A37: ='ПК с 1 владельцем'!A3+1 -> #REF! | B37: ЛЕША П | C37: после Онуфриев Сергей Юрьевич на Старостину Екатерину | D37: Модернизация не требуется/normal (no need to upgrade) | E37: Rus | F37: Onufriev Sergey | G37: Директор департамента | H37: M&U | I37: Laptop, mouse | J37: Acer Aspire Lite 15 AL15-41 | K37: поставить на учет | L37: Наклеить | N37: 1-09 второй этаж | O37: UN31ZSI04F533023D90700 | P37: ="RUTL-" & RIGHT(O37,8) -> RUTL-23D90700 | Q37: Внесены в Passwork | R37: 2019 for home and business | T37: Windows 11 Pro | V37: ULTRAVNC / MESH | W37: No administrator rights | X37: Летунов А. | Y37: Акт 19.11.2025 | Z37: 45975 | AA37: БЕЗ НДС 36790 с НДС -
A38: ='ПК с 1 владельцем'!A594+1 -> #REF! | B38: ЛЕША П | C38: после Ногин Михаил Валерьевич сделать модернизацию / поставить на склад | D38: Модернизация не требуется/normal (no need to upgrade) | E38: Rus | F38: Nogin Mikhail | G38: Координатор по транспорту | H38: GD, GA, RMG | I38: AiO, mouse, keyboard | J38: AiO Lenovo M810Z | K38: 140000144/Z000090 | L38: Наклеить | N38: 1-07 третий этаж | O38: PC0QUZBZ | P38: ="RUTL-" & RIGHT(O38,8) -> RUTL-PC0QUZBZ | Q38: Внесены в Passwork | T38: Windows 10 Pro | U38: MYJ3N-2JVF2-3Q4V8-QJM4X-QV66P | V38: ULTRAVNC / MESH | W38: No Administrator rights | X38: Кудрявцев Д. | Y38: Акт 24.12.2025
A39: 20 | B39: ЛЕША П | C39: после Якушевская Юлия Владимировна сделать модернизацию / поставить на склад | D39: Модернизация не требуется/normal (no need to upgrade) | E39: Rus | F39: Yakushevskaya Yulia | G39: Специалист по работе с рекламациями 2 категории | H39: PMD, ORD | I39: AiO, mouse, keyboard | J39: AiO Lenovo M800Z | K39: 140000050/Z000112 | L39: Наклеить | N39: 1-07 четвертый этаж | O39: PC0KL0MA | P39: ="RUTL-" & RIGHT(O39,8) -> RUTL-PC0KL0MA | Q39: Внесены в Passwork | R39: Microsoft Office профессиональный плюс 2016 | U39: 44DNT-94KRT-33CWT-PDKXT-VCFC2 | V39: ULTRAVNC | Y39: Акт 05.08.2024
A40: =A38+1 -> #REF! | B40: СЕРЁЖА | C40: Ширяев А | D40: Модернизация не требуется/normal (no need to upgrade) | E40: Rus | I40: Laptop,mouse | J40: Lenovo ThinkBook 16 G7 ARP 3 | K40: поставить на учет | L40: Наклеить | O40: PW0LW3Q9 | P40: ="RUTL-" & RIGHT(O40,8) -> RUTL-PW0LW3Q9 | Q40: Внесены в Passwork | R40: Libre office | T40: Windows 11 Pro | U40: 68CNW-GHXPM-H6DBM-RCQPD-977J6 | V40: ULTRAVNC / MESH | W40: No Administrator rights | X40: Мелёшкин С. | AA40: С НДС 64660 БЕЗ НДС 53000
A41: =A40+1 -> #REF! | B41: СЕРЁЖА | C41: Плехов Илья | D41: Модернизация не требуется/normal (no need to upgrade) | E41: Rus | H41: AC | I41: Laptop,mouse | J41: Lenovo ThinkBook 16 G7 ARP 3 | K41: поставить на учет | L41: Наклеить | O41: PW0LW3NJ | P41: ="RUTL-" & RIGHT(O41,8) -> RUTL-PW0LW3NJ | Q41: Внесены в Passwork | R41: Libre office | T41: Windows 11 Pro | U41: KF77M-7XNFW-JWQD4-W6M6M-88GPT | V41: ULTRAVNC / MESH | W41: No Administrator rights | X41: Мелёшкин С. | AA41: С НДС 64660 БЕЗ НДС 53000
A42: =A41+1 -> #REF! | B42: СЕРЁЖА | C42: Кучин А А | D42: Модернизация не требуется/normal (no need to upgrade) | E42: Rus | H42: AC | I42: Laptop,mouse | J42: Lenovo ThinkBook 16 G7 ARP 3 | K42: поставить на учет | L42: Наклеить | O42: PW0LW3QP | P42: ="RUTL-" & RIGHT(O42,8) -> RUTL-PW0LW3QP | Q42: Внесены в Passwork | R42: Libre office | T42: Windows 11 Pro | U42: KHQ4N-DP93V-6KPPK-F86TF-QGP2T | V42: ULTRAVNC / MESH | W42: No Administrator rights | X42: Мелёшкин С. | AA42: С НДС 64660 БЕЗ НДС 53000
A43: 1 | B43: должны вернуть | C43: Живов Сергей Викторович | D43: очень старый/old (2017 г) | E43: Rus | F43: Zhivov Sergey Viktorovich | G43: Заместитель генерального директора по производству | H43: MD | I43: Laptop, mouse,bag | J43: Laptop Lenovo ThinkPad EDGE E570 | K43: 150000027/Z000115 | L43: Наклеить | M43: Внесен в ITSM AST0000603 | N43: 1-09 третий этаж | O43: PF0NG272 | P43: ="RUTL-" & RIGHT(O43,8) -> RUTL-PF0NG272 | U43: J4V9V-N7QVM-3THKD-W67R4-8B49C | V43: ULTRAVNC / MESH | W43: Уточнить | Y43: 2017 | AA43: все проверено /внесено в итсм/нет акта выдачи/выдано давно
A44: ='ПК с 1 владельцем'!A35+1 -> #REF! | B44: должны вернуть | C44: Тамбовцева Екатерина Юрьевна (MSI+o) | D44: была модернизация/upgraded(SSD 480+RAM 8 from RDC reserve) | E44: Rus | F44: Tambovtseva Ekaterina | G44: Заместитель руководителя отдела | H44: HRD, DP, HR DATA | I44: AiO, mouse, keyboard | J44: HP All-in-One - 22-c0018ur | K44: 0000021019 | L44: инвентарник MOC наклеен | N44: 1-07 третий этаж | O44: 8CC9114K7V | P44: ="RUTL-" & RIGHT(O44,8) -> RUTL-C9114K7V | Q44: Внесены в Passwork | T44: Windows 10 Pro | V44: ULTRAVNC | W44: No Administrator rights | Y44: Акт 07.11.2019
A53: РЕЗЕРВ_СТОЯТ В ПОДРАЗДЕЛЕНИЯХ
A55: ='ПК с 1 владельцем'!A675+1 -> #REF! | B55: - | C55: Тишунин Сергей Анатольевич(3679) | D55: Модернизация не требуется/normal (no need to upgrade) | E55: Rus | F55: Tishunin Sergey | G55: Руководитель группы | H55: RDC, ISS | I55: laptop,mouse+Monitor Lenovo | J55: Dell Vostro 7500 | K55: 10000001758 | L55: инвентарник ОС наклеен | N55: 1-07 второй этаж | O55: 1GS51B3 | P55: ="RUTL-" & RIGHT(O55,8) -> RUTL-1GS51B3 | Q55: Внесены в Passwork | T55: Windows 10 Pro | U55: RV4P9-9RNBG-V923C-F3YMD-XHJXC | V55: ULTRAVNC | Y55: Акт 26.10.2023
A56: 2 | B56: - | C56: Каприца Светлана Олеговна(учетку не затирать) | D56: Модернизация не требуется/normal (no need to upgrade) | E56: Rus | F56: Kapritsa Svetlana | G56: Ведущий бухгалтер 1 категории | H56: FD, ACC | I56: AiO, mouse, keyboard | J56: AiO Dell Inspiron 5400 | K56: 100000001683 | L56: Наклеить | N56: 1-07 третий этаж FD | O56: 8VCFG92 | P56: ="RUTL-" & RIGHT(O56,8) -> RUTL-8VCFG92 | Q56: Внесены в Passwork | T56: Windows 10 Pro | U56: XBW3N-9TRV8-RPRXT-WR2FJ-HMHYP | V56: ULTRAVNC | W56: No Administrator rights | X56: Кудрявцев Д. | Y56: Акт 10.01.2024 | Z56: 44551 | AA56: без НДС 71 583,33 с НДС 85 900
A57: 3 | B57: - | C57: Стоит в закупках | D57: Модернизация не требуется/normal (no need to upgrade) | E57: Rus | G57: Специалист по закупкам | H57: PMD, PS | I57: AiO, mouse, keyboard | J57: AIO Acer Aspire C24-1800 | K57: 100000003396 | O57: DQBKMCD002336012DC3000 | P57: ="RUTL-" & RIGHT(O57,8) -> RUTL-12DC3000 | T57: Windows 10 Pro | V57: ULTRAVNC / MESH | X57: Климанов А. | Y57: акт 09.06.2025
A58: 🛠️ На ремонт 🛠️
A59: =A58+1 -> #VALUE! | B59: 2986 | C59: Корнилова Дарья Сергеевна (Дмитрий включил. Предполагаю что аккум ушел в глубокий разряд и не включаляся, но полежав сутки ему хватило емкости что бы подхватить зарядку) родная коробка найдена подписана на ремонт | D59: перестал включаться ЗАПАКОВАТЬ ДЛЯ ГАРАНТИЙНОГО РЕМОНТА | E59: Rus | F59: Kornilova Daria | G59: Ведущий бухгалтер 1 категории | H59: FD, ACC | I59: Laptop,mouse, monitor Xiaomi a24i SN: 54383/250100058939 | J59: Laptop MSI Modern 15 F1MG-800XRU | K59: поставить на учет | L59: Наклеить | N59: 1-07 третий этаж FD | O59: C2509N0008433 | P59: ="RUTL-" & RIGHT(O59,8) -> RUTL-N0008433 | Q59: Внесены в Passwork | R59: 2019 for home and business | T59: Windows 11 Pro | U59: YMTDN-JHTJK-6CMCJ-9DMR9-C7J6C | V59: ULTRAVNC / MESH | W59: No Administrator rights | X59: Летунов А. | Y59: Акт 03.01.2026 | Z59: 45989 | AA59: Стоимость ПК без НДС 59 160руб
A60: =A31+1 -> 20 | C60: Злобина Елена Викторовна ( РЕМОНТ ПО ГАРАНТИИ) | D60: Модернизация не требуется/normal (no need to upgrade) В РЕГАРДЕ НА РЕМОНТЕ | E60: Rus | F60: Zlobina Elena | G60: Специалист по производственной безопасности | H60: MD, AS | I60: Laptop,mouse | J60: Acer Aspire Lite 15 AL15-41 | K60: поставить на учет | L60: Наклеить | O60: UN31ZSI04F5330252D0700 | P60: ="RUTL-" & RIGHT(O60,8) -> RUTL-252D0700 | Q60: Внесены в Passwork | R60: Libre office | T60: Windows 11 | U60: K926X-N466P-FRCM3-WY6CC-8XC2T | V60: ULTRAVNC / MESH | W60: No Administrator rights | X60: Климанов А. | Y60: Акт 09.02.2026 | Z60: 45975 | AA60: БЕЗ НДС 36790 с НДС -
A61: =A60+1 -> 21 | B61: СФОРМИРОВАТЬ ЗАЯВКУ НА РЕМОНТ | C61: Глаголев Александр Николаевич/ Абдуллаев Эльдар / Зафарзода Зарирджон | D61: Необходима замена кулера и клавиатуры Требуется ремонт | E61: Rus | F61: Glagolev Aleksandr Eldar Abdullaev /Zafarzoda Zarirjon | G61: начальники участка цеха сварки штамповки/ welding and stamping shops Group leaders | H61: MD, S&W | I61: Laptop,mouse+Lan-USB | J61: Laptop Lenovo V15 G1+Lan-USB | K61: 100000001651 | L61: Наклеить | N61: 1-04 световой тоннель | O61: PF2TXV6E | P61: ="RUTL-" & RIGHT(O61,8) -> RUTL-PF2TXV6E | Q61: Внесены в Passwork | R61: 2019 for home and business | V61: ULTRAVNC | X61: Климанов А.К | Y61: акт 01-11-2024
A62: =A61+1 -> 22 | B62: СФОРМИРОВАТЬ ЗАЯВКУ НА РЕМОНТ | C62: Стрельникова Наталья Анатольевна (После блокировки экрана, через 5-10 мин. Постоянные перезагрузки,может даже во время работы) | D62: Модернизация не требуется/normal (no need to upgrade) | E62: Rus | F62: Strelnikova Nataliya | G62: Бухгалтер по расчету заработной платы | H62: HRD, DP, PAY | I62: AiO, mouse, keyboard | J62: AIO HP200G G4 22 | K62: 100000001757 | L62: Наклеить | M62: Внесен в ITSM AST0000652 | N62: 1-07 третий этаж | O62: 8CC1373GZW | P62: ="RUTL-" & RIGHT(O62,10) -> RUTL-8CC1373GZW | R62: Microsoft Office профессиональный плюс 2016 | V62: ULTRAVNC | Z62: 44551 | AA62: БЕЗ НДС с НДС 61000
A63: =A62+1 -> 23 | B63: СФОРМИРОВАТЬ ЗАЯВКУ НА РЕМОНТ | C63: Куликова Лидия СИНИЕ ЭКРАНЫ СМЕРТИ И НЕ ПОЛУЧАЕТСЯ ВКЛЮЧИТЬ ДО ОБЕСТОЧИВАНИЯ И ВРЕМЕНИ БЕЗ ПИТАНИЯ | D63: Постоянные зависания/синий экран | E63: Rus | F63: Kulikova Lidiya | G63: Бухгалтер | H63: FD, ACC | I63: AiO, mouse, keyboard | J63: AiO Dell Inspiron 5400 | K63: 100000001678 | L63: Наклеить | N63: 1-07 третий этаж FD | O63: HJRHDF2 | P63: RUTL-HJRHDF2 | Q63: Внесены в Passwork | R63: 2019 for home and business | T63: Windows 10 Pro | V63: ULTRAVNC / MESH | W63: No Administrator rights | X63: Летунов А. | Y63: Акт 22.09.2025
A64: =A63+1 -> 24 | B64: СФОРМИРОВАТЬ ЗАЯВКУ НА РЕМОНТ | C64: Тютина Майя Алексеевна | D64: МодернПЕРЕСТАЛ ВИДЕТЬ НАКОПИТЕЛЬ/ повреждение матрицы | E64: Rus | F64: Tutina Maya | G64: Ведущий специалист | H64: R&D, PMD, PS | I64: AiO, mouse, keyboard | J64: IRBIS SMART AIO MB2389 | K64: поставить на учет | L64: наклеить | O64: 2408A22H124i5M2165R00487 | P64: ="RUTL-" & RIGHT(O64,8) -> RUTL-65R00487 | Q64: Внесены в Passwork | R64: Libre office | T64: Windows 10 Pro | U64: MHHDN-CRHTG-TQKQX-R39YY-6VJXC | V64: ULTRAVNC / MESH | X64: Климанов А. | Y64: Акт 21.05.2025
A65: =A64+1 -> 25 | B65: СФОРМИРОВАТЬ ЗАЯВКУ НА РЕМОНТ | C65: Москаленко Ольга Леонидовна | D65: ОЗУ 2 плашки по 4гб всего 8 гб. SSD Micron MTFDDAK256TDL 240 гб. Не включается совсем. На матплате видны прогары (ооочень маленькие) | E65: Rus | F65: Moskalenko Olga | G65: Специалист по стандартизации документооборота | H65: QMD, QA | I65: Laptop, mouse | J65: Laptop Lenovo L340 | K65: 10000001797 | L65: инвентарник ОС наклеен | N65: 1-09 второй этаж | O65: PF1SLH49 | P65: ="RUTL-" & RIGHT(O65,8) -> RUTL-PF1SLH49 | R65: Microsoft Office профессиональный плюс 2016 | T65: Windows 10 Pro | U65: D27N6-DQRCV-D3J93-JX9DG-J2QGT | V65: ULTRAVNC | W65: No Administrator rights | X65: Кудрявцев Д. | Y65: Акт 22.08.2024
A66: =A65+1 -> 26 | B66: Стоит ли ремонтировать? | C66: Самопроизвольные перезагрузки после синего экрана, осматривал его но так и не нашел решение из-за чего это может быть, менял и ОЗУ и SSD на только что установленой ОС возникают ошибки | D66: Модернизация не требуется | E66: Rus | F66: Maslova Zhanna | G66: Специалист по затратам | H66: TM, GA | I66: Laptop,mouse | J66: Laptop Lenovo L340 | K66: 10000001793 | L66: инвентарник ОС наклеен | N66: СКЛАД | O66: PF1ALKU1 | P66: ="RUTL-" & RIGHT(O66,8) -> RUTL-PF1ALKU1 | Q66: Внесены в Passwork | R66: 2016 for home and business (BOX) | S66: CNM3K-WT96W-W4VDJ-P24KT-BP2MK | T66: Windows 10 Pro | V66: ULTRAVNC / MESH | W66: No Administrator rights | X66: Кудрявцев Д. | Y66: Акт 11.03.2026
A67: =A66+1 -> 27 | B67: СФОРМИРОВАТЬ ЗАЯВКУ НА РЕМОНТ | C67: РЕЗЕРВ IT из под Фоменков Владимир Александрович | D67: Модернизация не требуется/normal (no need to upgrade) | E67: Rus | F67: Fomenkov Vladimir | G67: Руководитель группы | H67: РЕМОНТ/REPAIR | I67: Laptop,mouse+Lan-USB | J67: Dell Vostro 7500 | K67: 10000001757 | L67: инвентарник ОС наклеен | N67: 1-07 второй этаж | O67: JFS51B3 | P67: ="RUTL-" & RIGHT(O67,8) -> RUTL-JFS51B3 | R67: W9V86-NMY7Q-7HVMW-68MTH-T3BP2 | Y67: . | AA67: лежит на ремонт
A68: =A77+1 -> 29 | B68: СФОРМИРОВАТЬ ЗАЯВКУ НА РЕМОНТ | C68: Чуйкина Эльвира | E68: Rus | F68: Chuikina Elvira | G68: Специалист по управлению эффективностью | H68: РЕМОНТ/REPAIR | I68: Laptop,mouse | J68: Laptop Lenovo V510 | K68: 00000011597 | L68: инвентарник MOC наклеен | N68: 1-07 2 этаж | O68: LR08MD81 | P68: ="RUTL-" & RIGHT(O68,8) -> RUTL-LR08MD81 | Q68: Внесены в Passwork | R68: Libre office | T68: Windows 10 Pro - 22H2/19045 x64 | U68: RC84X-P9NB9-89XXY-PJWWV-7QWXC | V68: ULTRAVNC / MESH | W68: No Administrator rights | X68: Мартынов Д. | Y68: Акт 30.07.2025
A69: =A68+1 -> 30 | B69: СФОРМИРОВАТЬ ЗАЯВКУ НА РЕМОНТ | C69: Старостина Екатерина Валерьевна | D69: НЕ КРУТИТ КУЛЕР ОХЛАЖДЕНИЯ, ОПАСНО С ПЕРЕГРЕВОМ | E69: Rus | F69: Starostina Ekaterina | G69: Начальник смены технического обслуживания оборудования 1 категории | H69: РЕМОНТ/REPAIR | I69: Laptop, mouse,bag | J69: Laptop HP 250 G7 | K69: 100000001597 | L69: Наклеить | M69: Внесен в ITSM AST0000852 | N69: 1-02 склад MU | O69: CND12506BY | P69: ="RUTL-" & RIGHT(O69,8) -> RUTL-D12506BY | Q69: Внесены в Passwork | R69: 2019 for home and business | T69: Windows 10 Pro | V69: ULTRAVNC | Y69: Акт 17.01.2022 | Z69: 44551 | AA69: без НДС 39916,67 с НДС 47900
A70: =A69+1 -> 31 | B70: СФОРМИРОВАТЬ ЗАЯВКУ НА РЕМОНТ | C70: повтор проблемы | E70: Rus | G70: - | H70: РЕМОНТ/REPAIR | I70: Workstation | J70: ПК Lenovo ThinkStation P 330 | K70: 140000249 | L70: инвентарник ОС наклеен | N70: СКЛАД | O70: PC0ZVQPP | P70: ="RUTL-" & RIGHT(O70,8) -> RUTL-PC0ZVQPP | Q70: NOT STABLE( проблема с цепью питания??) | AA70: лежит на ремонт
J71: ⛪︎ | K71: ✟ | L71: СПИСАНИЕ/need to dismiss | M71: ✟ | N71: ⛪︎
A72: 38 | B72: Заключение О нецелесообразности дальнейшего использования ИТ активов № RDC-BSS-11-2025-001 От 14-11-2025 г. | C72: Амелин Максим Геннадьевич (СЛОМАЛСЯ, ДИСПЛЕЙ НИЧЕГО НЕ ОТОБРАЖАЕТ, ЗАГРУЗКА НЕ ПРОХОДИТ, КЛАВА НЕ РЕАГИРУЕТ НА КАПСЛОК, ВЫТАЩИЛИ МЫ ССД И ОПЕРУ) | D72: Модернизация не требуется/normal (no need to upgrade) | H72: can’t repair (need to dismiss) | I72: Laptop | J72: Laptop Lenovo T480 | K72: 140000197 | L72: инвентарник ОС наклеен | N72: СКЛАД | O72: PF17Y7T2 | P72: ="RUTL-" & RIGHT(O72,8) -> RUTL-PF17Y7T2 | Q72: Внесены в Passwork | AA72: лежит на ремонт
A73: 6 | B73: документы на списание в процессе ( для FD) | C73: очень старый /old(2014-2017 г) | H73: can’t repair (need to dismiss) | I73: wORKST/Desktop,monitor | J73: Lenovo ThinkCentre M73z | K73: 100000001324/23468 | L73: инвентарник MOC наклеен | M73: очень старый /old(2014-2017 г) | N73: СКЛАД | O73: PC017TC2 | P73: ="RUTL-" & RIGHT(O73,8) -> RUTL-PC017TC2 | Q73: 💩 | AA73: В коробке на списание
A74: 7 | B74: документы на списание в процессе ( для FD) | C74: очень старый /old(2014-2017 г) | H74: can’t repair (need to dismiss) | I74: Workst,monitor+monitor(000000329) | J74: Lenovo ThinkCentre M93p | K74: 100000001344(0000009138(2) | L74: инвентарник MOC наклеен | M74: очень старый /old(2014-2017 г) | N74: СКЛАД | O74: S4G32596 | P74: ="RUTL-" & RIGHT(O74,8) -> RUTL-S4G32596 | Q74: 💩 | AA74: Норм
A75: 39 | B75: Не подлежит ремонту, можно использовать как донора. | C75: Кузнецов Михаил Сергеевич на тесте у секюрити | D75: шлейф экрана | E75: Rus | H75: can’t repair (need to dismiss) | I75: Laptop | J75: Laptop Lenovo V510 | K75: 00000016127 | L75: инвентарник MOC наклеен | N75: 1-09 второй этаж | O75: LR0AVC1Y | P75: ="RUTL-" & RIGHT(O75,8) -> RUTL-LR0AVC1Y | U75: GN8G8-XPHQY-6H9M9-QVGVB-DPFC2 | V75: ULTRAVNC | Y75: Акт 28.01.2019
A76: =1+'ПК с 1 владельцем'!A610 -> #REF! | B76: Не подлежит ремонту, можно использовать как донора. | C76: Кимаев Артем Александрович ( 7849 ) на тесте у секюрити | D76: Модернизация не требуется/normal (no need to upgrade) 8 ОЗУ +SSD | E76: Rus | F76: Kimaev Artem | G76: Специалист TPS | H76: NOBO | I76: Laptop, mouse | J76: Laptop Lenovo V 130 | K76: 00000019366(9) | L76: инвентарник MOC наклеен | N76: engine shop | O76: R90T948L | P76: ="RUTL-" & RIGHT(O76,8) -> RUTL-R90T948L | Q76: Внесены в Passwork | R76: Microsoft Office профессиональный плюс 2016 | U76: 2YWGK-NXRFQ-M3M66-CJMDR-PPQGP | V76: ULTRAVNC / MESH | W76: No Administrator rights | X76: Кудрявцев Д. | Y76: Акт 19.03.2026 | Z76: 43661
A77: =A67+1 -> 28 | B77: СФОРМИРОВАТЬ ЗАЯВКУ НА РЕМОНТ | C77: не работает клава и акум на тесте сек | D77: Клавиатура не работает + Аккум | E77: Rus | F77: Vladimirova Kristina | G77: Ведущий специалист по административной работе | H77: РЕМОНТ/REPAIR | I77: Laptop, mouse,bag,keyboard | J77: Laptop Lenovo Thinkpad L580 | K77: 14000153/Z000045 | L77: наклеить | N77: СКЛАД | O77: PF12TW55 | P77: ="RUTL-" & RIGHT(O77,8) -> RUTL-PF12TW55 | R77: 9HNX7-28CB7-VYV34-GX3R7-R9CKC | Z77: 43236 | AA77: БЕЗ НДС 41754,78, С НДС 50920,47
A78: ДИМА | B78: Не подлежит ремонту, можно использовать как донора. | C78: Зуборев Дмитрий Алексеевич | D78: Не включается, пахнет горелым ремонт по гарантии Проблемы с клавиатурой (нажимаются англ. "H" / русская "Р" 13-02-2026 ВЕРНУЛСЯ К НАМ БЕЗ РЕМОНТА, ГАРАНТИЯ КОНЧИЛАСЬ | H78: can’t repair (need to dismiss) | I78: Laptop, mouse,bag | J78: Laptop IRBIS 15NBP3506 | K78: 100000003603 | L78: Наклеить | O78: F2715NBP35060821934 | P78: ="RUTL-" & RIGHT(O78,8) -> RUTL-60821934 | R78: Libre office | T78: Windows 10 Pro | U78: DJ7TX-6NH7T-Y8BDD-BRDBJ-WB49C | V78: ULTRAVNC / MESH | W78: No Administrator rights | X78: Климанов А | Y78: Акт 17.10.2025
B79: можно использовать как донора. | C79: Измайлова Юлия Геннадьевна (после замены на утиль) | D79: need to check | E79: Rus | F79: Izmailova Julia | G79: Инженер линии 1 категории | H79: MD, PAINT | I79: Laptop,mouse | J79: Laptop Lenovo t440p | K79: поставить на учет | L79: МОСКВА | N79: 1-03 офис окраски 2эт | O79: PC01A9BD | P79: ="RUTL-" & RIGHT(O79,8) -> RUTL-PC01A9BD | Q79: Внесены в Passwork | V79: ULTRAVNC / MESH | W79: No Administrator rights | X79: Летунов А. | Y79: Акт 20.01.2023
A80: ='ПК с 1 владельцем'!A360+1 -> #REF! | B80: можно использовать как донора. | C80: сломана петля | D80: Модернизация не требуется/normal (no need to upgrade) | E80: Rus | G80: Офис-ассистент | I80: Laptop, mouse,bag | J80: Laptop Lenovo V 130 | K80: 00000019366(11) | L80: инвентарник ОС наклеен | N80: 1-09 третий этаж | O80: R90T948D | P80: ="RUTL-" & RIGHT(O80,8) -> RUTL-R90T948D | Q80: Внесены в Passwork | R80: Microsoft Office профессиональный плюс 2019 | T80: Windows 10 Pro | U80: 3NRXC-JKQK6-JMX4R-XD66W-W44C2 | V80: ULTRAVNC / MESH | W80: No Administrator rights | X80: Кудрявцев Д. | Y80: Акт 06.03.2026 | Z80: 43661
G82: =(774+3+10+5+4+18+2+15+16+20+39+59)-(19+14+2) -> 930 | I82: всего по заводу (2023 год )513 PCs+10+1(для щербакова)=524 (2024 год) 97(тендер)+1(лаборатория)+130(тендер)+1(движки)+21(срочная)= 250 ИТОГО 774 2025 год 1+3+5+5+5+4 ( под ЖМР включая 1 проданный им от ХММР) 18 - по срочной закупке(приход от 14-03-2025)+2 пришли взамен сломанных 15 ПК по срочной заявке пришли в 11 августа 2025 16 ПК по срочной заявке 17 октября 2025 20 ПК по срочной заявке 14 ноября 28-11-2025 39 ПК по тендеру RDD 19-12-2025 59 ПК по тендеру RDD Утилизация/списание декабрь 2025 09-12-2025 списано/передано на утилизацию 9 ПК 12-12-2025 списано/передано на утилизацию 9 ПК 24-12-2025 списано/передано на утилизацию 14 ПК ИТОГО 930 2026 год 27-03-2026 ПК по тендеру (1 партия ) 53 ноутбука+ 38 A1 06-04-2026 ПК по тендеру (2 партия ) 80 A1 +9A2
L84: СПИСАНИЕ(проведено)
A85: 1 | B85: ЗАМЕНИЛИ В РЭДКОМ ACER НА MSI! АКТ неремонтопригодности "ввод в эксплуатацию 24.10.2024 / замена по гарантии акт о неремонтопригодности № 1" "ввод в эксплуатацию 24.10.2024 / замена по гарантии акт о неремонтопригодности № 2" Сторно из экспл от 01-04-2025 | C85: ЗАМЕНИЛИ РЭДКОМ НА MSI! | D85: 24.10.2024 ввели в эксплуатацию сторно из эксплуатации 01-04-2025, | E85: Заводской брак , поставщик поменял ПК на MSI | G85: Заводской брак , поставщик поменял ПК на MSI | H85: замена по браку | I85: Laptop | J85: Laptop Acer Extensa 15 | K85: 100000003339 | L85: Наклеить | M85: NXEGYER00H320087103400 | N85: Заводской брак , поставщик поменял ПК на MSI
A86: =A85+1 -> 2 | B86: ЗАМЕНИЛИ В РЭДКОМ ACER НА MSI! АКТ неремонтопригодности "ввод в эксплуатацию 24.10.2024 / замена по гарантии акт о неремонтопригодности № 1" "ввод в эксплуатацию 24.10.2024 / замена по гарантии акт о неремонтопригодности № 2" Сторно из экспл от 01-04-2025 | C86: ЗАМЕНИЛИ РЭДКОМ НА MSI! | D86: 24.10.2024 ввели в эксплуатацию сторно из эксплуатации 01-04-2025, | E86: Заводской брак , поставщик поменял ПК на MSI | G86: Заводской брак , поставщик поменял ПК на MSI | H86: замена по браку | I86: Laptop | J86: Laptop Acer Extensa 15 | K86: 100000003338 | L86: Наклеить | M86: NXEGYER00H320089493400 | N86: Заводской брак , поставщик поменял ПК на MSI
A87: =A86+1 -> 3 | B87: документы на списание подписаны | C87: отдали на утилизацию 24-12-2025 | E87: 💩 | G87: начали подготовку к утилизации | H87: утилизация 2025 | I87: Laptop | J87: laptop HP ProBook455(240000002) | K87: 00000000468 | L87: инвентарник MOC наклеен | M87: CND4434S1J | N87: разобраны/готовы к передаче ga
A88: =A87+1 -> 4 | B88: документы на списание подписаны | C88: отдали на утилизацию 24-12-2025 | E88: 💩 | G88: начали подготовку к утилизации | H88: утилизация 2025 | I88: Laptop | J88: Laptop Lenovo V 130 | K88: 00000019366(13) | L88: инвентарник MOC наклеен | M88: R90T9488 | N88: разобраны/готовы к передаче ga
A89: =A88+1 -> 5 | B89: документы на списание подписаны | C89: отдали на утилизацию 24-12-2025 | E89: 💩 | G89: начали подготовку к утилизации | H89: утилизация 2025 | I89: Laptop | J89: Laptop Lenovo V 130 | K89: 00000019366(1) | L89: инвентарник MOC наклеен | M89: R90SRSH8 | N89: разобраны/готовы к передаче ga
A90: =A89+1 -> 6 | B90: документы на списание подписаны | C90: отдали на утилизацию 24-12-2025 | E90: 💩 | G90: начали подготовку к утилизации | H90: утилизация 2025 | I90: Laptop, mouse,bag | J90: Laptop Lenovo V 130 | K90: 00000019366(8) | L90: инвентарник MOC наклеен | M90: R90T9481 | N90: разобраны/готовы к передаче ga
A91: =A90+1 -> 7 | B91: документы на списание подписаны | C91: отдали на утилизацию 24-12-2025 | E91: 💩 | G91: начали подготовку к утилизации | H91: утилизация 2025 | I91: Laptop | J91: Laptop Lenovo V510 | K91: 00000011577 | L91: инвентарник MOC наклеен | M91: LR08MD6L | N91: разобраны/готовы к передаче ga
A92: =A91+1 -> 8 | B92: документы на списание подписаны | C92: отдали на утилизацию 24-12-2025 | E92: 💩 | G92: начали подготовку к утилизации | H92: утилизация 2025 | I92: Laptop | J92: Laptop Lenovo V110 | K92: 00000010789 | L92: инвентарник MOC наклеен | M92: R90QFQ01 | N92: разобраны/готовы к передаче ga
A93: =A92+1 -> 9 | B93: документы на списание подписаны | C93: отдали на утилизацию 24-12-2025 | E93: 💩 | G93: начали подготовку к утилизации | H93: утилизация 2025 | I93: Laptop | J93: Laptop Lenovo V110 | K93: 00000010790 | L93: инвентарник MOC наклеен | M93: R90QFQ0B | N93: разобраны/готовы к передаче ga
A94: =A93+1 -> 10 | B94: документы на списание подписаны | C94: отдали на утилизацию 24-12-2025 | E94: 💩 | G94: начали подготовку к утилизации | H94: утилизация 2025 | I94: WorkStation.monitor Philips,mouse,keyboard | J94: WorkStation Acer Aspire TC-605+monitor Philips(240000006) | K94: 00000000010 | L94: инвентарник MOC наклеен | M94: DTSRQER08542400B653000 | N94: разобраны/готовы к передаче ga
A95: =A94+1 -> 11 | B95: документы на списание подписаны | C95: отдали на утилизацию 24-12-2025 | E95: 💩 | G95: начали подготовку к утилизации | H95: утилизация 2025 | I95: Desktop,monitor | J95: Lenovo ThinkCentre M73z | K95: 00000020993 | L95: инвентарник MOC наклеен | M95: PC017TCJ | N95: разобраны/готовы к передаче ga
A96: =A95+1 -> 12 | B96: документы на списание подписаны | C96: отдали на утилизацию 24-12-2025 | E96: 💩 | G96: начали подготовку к утилизации | H96: утилизация 2025 | I96: Desktop, Monitor(Lenovo 19" LT 1952p Black/240000011-0002)mouse, keyboard | J96: Lenovo ThinkCenter M73/240000011 | K96: 00000000332 | L96: инвентарник MOC наклеен | M96: PC017TH4 | N96: разобраны/готовы к передаче ga
A97: =A96+1 -> 13 | B97: документы на списание подписаны | C97: отдали на утилизацию 24-12-2025 | E97: 💩 | G97: начали подготовку к утилизации | H97: утилизация 2025 | I97: WorkStation,monitor,mouse,keyboard | J97: Lenovo ThinkCentre M73 | K97: 00000000314 | L97: инвентарник MOC наклеен | M97: PC017TCT | N97: разобраны/готовы к передаче ga
A98: =A97+1 -> 14 | B98: документы на списание подписаны | C98: отдали на утилизацию 24-12-2025 | E98: 💩 | G98: начали подготовку к утилизации | H98: утилизация 2025 | I98: Workstation, Monitor(Lenovo 19" LT 1952p Black/240000012-0002)mouse, keyboard | J98: Lenovo ThinkCenter M73((24000012)) | K98: 000000333 | L98: инвентарник MOC наклеен | M98: PC017TGK | N98: разобраны/готовы к передаче ga
... A103: =A102+1 -> 19 | B103: Заключение О нецелесообразности дальнейшего использования ИТ активов № RDC-BSS-10-2025-007От 30-10-2025 г. | C103: отдали на утилизацию 12-12-2025 | E103: 💩 | G103: документы на списание переданы на проверку FD 08-12-2025/ начали подготовку к утилизации | H103: утилизация 2025 | I103: Laptop | J103: Laptop LenovoX270 | K103: 140000069/Z000095 | L103: Наклеить | M103: PC0NBSGN | N103: разобраны/готовы к передаче ga
A104: =A103+1 -> 20 | B104: "Заключение О нецелесообразности дальнейшего использования ИТ активов № RDC-BSS-10-2025-003 От 30-10-2025 г. | C104: отдали на утилизацию 12-12-2025 | E104: 💩 | G104: документы на списание переданы на проверку FD 08-12-2025/ начали подготовку к утилизации | H104: утилизация 2025 | I104: Laptop | J104: Laptop Lenovo ThinkPad EDGE E570 | K104: 150000028/Z000006 | L104: Наклеить | M104: PF0NFU3K | N104: разобраны/готовы к передаче ga | O104: BC7J4-MN7BC-MY7J2-RT6FY-MY49C
A105: =A104+1 -> 21 | B105: "Заключение О нецелесообразности дальнейшего использования ИТ активов № RDC-BSS-10-2025-002 От 30-10-2025 г. | C105: отдали на утилизацию 12-12-2025 | D105: акумулятор офф | E105: 💩 | G105: документы на списание переданы на проверку FD 08-12-2025/ начали подготовку к утилизации | H105: утилизация 2025 | I105: Laptop | J105: Laptop Lenovo ThinkPad EDGE E570 | K105: 140000054/Z000108 | L105: Наклеить | M105: PF0W1977 | N105: разобраны/готовы к передаче ga
A106: =A105+1 -> 22 | B106: Заключение О нецелесообразности дальнейшего использования ИТ активов № RDC-BSS-10-2025-006От 30-10-2025 г. | C106: отдали на утилизацию 12-12-2025 | E106: 💩 | G106: документы на списание переданы на проверку FD 08-12-2025/ начали подготовку к утилизации | H106: утилизация 2025 | I106: Laptop | J106: Laptop Lenovo ThinkPad EDGE E560 | K106: 140000042/Z000126 | L106: Наклеить | M106: PF0LC4HW | N106: разобраны/готовы к передаче ga | O106: Installed Key:237XB-GDJ7B-MV8MH-98QJM-24367(Windows 7 Professional)
A107: =A106+1 -> 23 | B107: акумулятор + клавиатура офф Заключение О нецелесообразности дальнейшего использования ИТ активов № RDC-BSS-10-2025-005 От 30-10-2025 г. | C107: отдали на утилизацию 20-12-2025 | E107: 💩 | G107: документы на списание переданы на проверку FD 08-12-2025/ начали подготовку к утилизации | H107: утилизация 2025 | I107: Laptop | J107: Laptop Lenovo ThinkPad EDGE E560 | K107: 140000024/Z000055 | L107: Наклеить | M107: PF-0IP638 | N107: разобраны/готовы к передаче ga | O107: 77F4C-NCDHK-TWXFK-RMBHV-8HV82
A108: =A107+1 -> 24 | B108: Заключение О нецелесообразности дальнейшего использования ИТ активов № RDC-BSS-10-2025-004 От 30-10-2025 г. | C108: отдали на утилизацию 12-12-2025 | E108: 💩 | G108: документы на списание переданы на проверку FD 08-12-2025/ начали подготовку к утилизации | H108: утилизация 2025 | I108: Laptop | J108: Laptop Lenovo ThinkPad EDGE E560 | K108: 140000039/Z000128 | L108: Наклеить | M108: PF0L9ESP | N108: разобраны/готовы к передаче ga
A109: =A108+1 -> 25 | C109: отдали на утилизацию 09-12-2025 | E109: 💩 | G109: документы на списание подписаны(кит.форма) Лежит в коробке на утиль ( отдали на утилизацию 09-12-2025) | H109: утилизация 2025 | I109: Laptop | J109: Laptop LenovoT440p | K109: не на балансе | L109: MOSCOW(HMR) | M109: PC01389D | N109: разобраны/готовы к передаче ga
A110: =A109+1 -> 26 | C110: отдали на утилизацию 09-12-2025 | E110: 💩 | G110: документы на списание подписаны(кит.форма) Лежит в коробке на утиль ( отдали на утилизацию 09-12-2025) | H110: утилизация 2025 | I110: Desktop,monitor | J110: Desktop ThinkCentre Lenovo M92p | K110: не на балансе | L110: MOSCOW(HMR) | M110: PB02NZP2 | N110: разобраны/готовы к передаче ga
A111: =A110+1 -> 27 | C111: отдали на утилизацию 09-12-2025 | E111: 💩 | G111: документы на списание подписаны(кит.форма) Лежит в коробке на утиль ( отдали на утилизацию 09-12-2025) | H111: утилизация 2025 | I111: Desktop,monitor | J111: Desktop ThinkCentre Lenovo M92p | K111: не на балансе | L111: MOSCOW(HMR) | M111: PBP3W3V | N111: разобраны/готовы к передаче ga
A112: =A111+1 -> 28 | C112: отдали на утилизацию 09-12-2025 | E112: 💩 | G112: документы на списание подписаны(кит.форма) Лежит в коробке на утиль ( отдали на утилизацию 09-12-2025) | H112: утилизация 2025 | I112: Desktop,monitor | J112: M 73 Desktop | K112: не на балансе | L112: MOSCOW(HMR) | M112: PB02UAKC | N112: разобраны/готовы к передаче ga
A113: =A112+1 -> 29 | C113: отдали на утилизацию 09-12-2025 | E113: 💩 | G113: документы на списание подписаны(кит.форма) Лежит в коробке на утиль ( отдали на утилизацию 09-12-2025) | H113: утилизация 2025 | I113: Desktop,monitor | J113: M 93p Desktop | K113: не на балансе | L113: MOSCOW(HMR) | M113: S4G32593 | N113: разобраны/готовы к передаче ga
A114: =A113+1 -> 30 | C114: отдали на утилизацию 09-12-2025 | E114: 💩 | G114: документы на списание подписаны(кит.форма) Лежит в коробке на утиль ( отдали на утилизацию 09-12-2025) | H114: утилизация 2025 | I114: Desktop,monitor | J114: Desktop ThinkCentre Lenovo M92p | K114: не на балансе | L114: MOSCOW(HMR) | M114: PBP3W3Y | N114: разобраны/готовы к передаче ga
A115: =A114+1 -> 31 | C115: отдали на утилизацию 09-12-2025 | E115: 💩 | G115: документы на списание подписаны(кит.форма) Лежит в коробке на утиль ( отдали на утилизацию 09-12-2025) | H115: утилизация 2025 | I115: Desktop,monitor | J115: Lenovo ThinkCenter M73 | K115: не на балансе | L115: MOSCOW(HMR) | M115: S4G02565 | N115: разобраны/готовы к передаче ga
...

Sheet ОПГ РНДМоушен
A1: № | B1: Табельный номер / Employee ID | C1: Физлицо / Owner | D1: История модернизаций, ремонтов / Modernisation, repairing history | E1: Тип домена / Domain Type | F1: Имя на английском / English name | G1: Должность / Position (Rus / Eng) | H1: Отдел / Department | I1: Комплектация / Equipment | J1: Тип и модель ПК / PC type and model | K1: Инвентарный номер / Inventory number | L1: Инвентарный номер наклеен? / Is the inventory number affixed? | M1: где хранится информация о компе | N1: Местоположение / Location | O1: Серийный номер / Serial Number | P1: Имя компьютера / PC Domain Name | Q1: TeamPass, Passwork? | R1: Тип ПО офис / Office type | S1: Ключ офиса / License key Office | T1: ОС тип / OS Type | U1: Ключ ОС / Key OS | V1: ПО удалённого управления / Remote control | W1: Админ права / Admin permissions | X1: Кто подготовил / Who installed | Y1: Дата выдачи / Issue Date | Z1: Дата покупки / Purchasing Date | AA1: Примечание / Comment
A2: =#REF!+1 -> #REF! | B2: 12152 | C2: Башин Артем Геннадьевич | D2: обратно не принимать, пк подвергся вандализму | E2: Rus | F2: Bashin Artem | G2: Инженер по технологии силовых агрегатов 2 категории | H2: R&D, PTD, CTS | I2: Laptop, mouse | J2: Laptop IRBIS 15NBP3507 | K2: поставить на учет | L2: наклеить | N2: 1-07 четвертый этаж | O2: F2715NBP35070821711 | P2: ="RUTL-" & RIGHT(O2,8) -> RUTL-70821711 | Q2: Внесены в Passwork | R2: Libre office | T2: Windows 10 Pro - 22H2/19045 | U2: 3666N-9MDY9-6GH86-PMR8H-MBH22 | V2: ULTRAVNC / MESH | W2: No Administrator rights | X2: Кудрявцев Д. | Y2: Акт 21.05.2025
A3: =#REF!+1 -> #REF! | B3: 9261 | C3: Герасина Анастасия Сергеевна | D3: Модернизация не требуется/normal (no need to upgrade) | E3: Rus | F3: Gerasina Anastasia | G3: Специалист по управлению проектами | H3: R&D, PRJMD, PMS I | I3: Laptop, mouse,bag | J3: Laptop Lenovo L340 | K3: 10000001789 | L3: инвентарник ОС наклеен | N3: 1-07 четвертый этаж | O3: PF24ABRT | P3: ="RUTL-" & RIGHT(O3,8) -> RUTL-PF24ABRT | Q3: Внесены в Passwork | R3: MS Office | U3: DGC9N-BJ7FW-WJTWW-DR8DC-JB49G | V3: ULTRAVNC / MESH | X3: Летунов А. | Y3: Акт 27.08.2024
A4: ='ПК с 1 владельцем'!A322+1 -> 10 | B4: 1540 | C4: Никитин Александр Валерьевич | D4: Модернизация не требуется/normal (no need to upgrade) | E4: Rus | F4: Nikitin Aleksandr | G4: Специалист 3 категории | H4: R&D, PRJMD, PMS I | I4: Laptop,mouse+Lan-USB | J4: Laptop Lenovo V15 G1+Lan-USB | K4: 100000001627 | L4: Наклеить | M4: Внесен в ITSM AST0000878 | N4: 1-07 четвертый этаж | O4: PF2TXSE1 | P4: ="RUTL-" & RIGHT(O4,8) -> RUTL-PF2TXSE1 | R4: 2016 for home and business (BOX) | V4: ULTRAVNC | W4: Admin | Y4: Акт 30.09.2021
A5: 9 | C5: Используется для микроскопа | D5: НОВЫЙ/New(no need to upgrade) | G5: на перепродажу? | H5: R&D, lab | I5: WorkStation,monitor(не наш),mouse,keyboard | J5: Workstation Регард К00826/1(РДЦБ-000826) | K5: 10000003812 | L5: Наклеить | N5: 1-07 4 этаж, лаборатория | O5: 07E0210_O31B057075 | P5: ="RUTL-" & RIGHT(O5,8) -> RUTL-1B057075 | U5: VYN9P-JQVWF-T3P78-TG4KT-P7JXC
